{"Id":310,"Name":"Horned Bird","Type":"Animal","Properties":{"Description":null,"AttackRange":null,"AggressionRange":null,"IsSweatable":true},"DefensiveProfession":{"Name":"Evader","Links":{"$Url":"/professions/42"}},"ScanningProfession":{"Name":"Animal Investigator","Links":{"$Url":"/professions/1"}},"Planet":{"Name":"Cyrene","Links":{"$Url":"/planets/7"}},"Species":{"Name":"Horned Bird","Properties":{"CodexBaseCost":27.5,"CodexType":"Mob"},"Links":{"$Url":"/mobspecies/151"}},"Maturities":[{"Id":1731,"Name":"Adult","Properties":{"Description":null,"Health":440,"AttacksPerMinute":null,"Level":15,"RegenerationInterval":null,"RegenerationAmount":null,"MissChance":null,"Taming":{"IsTameable":false,"TamingLevel":null},"Attributes":{"Strength":10,"Agility":10,"Intelligence":10,"Psyche":10,"Stamina":44},"Defense":{"Stab":null,"Cut":null,"Impact":null,"Penetration":null,"Shrapnel":null,"Burn":null,"Cold":null,"Acid":null,"Electric":null}},"Attacks":[],"Mob":{"Name":"Horned Bird","Links":{"$Url":"/mobs/310"}},"Links":{"$Url":"/mobmaturities/1731"}},{"Id":1732,"Name":"Provider","Properties":{"Description":null,"Health":550,"AttacksPerMinute":null,"Level":19,"RegenerationInterval":null,"RegenerationAmount":null,"MissChance":null,"Taming":{"IsTameable":false,"TamingLevel":null},"Attributes":{"Strength":10,"Agility":10,"Intelligence":10,"Psyche":10,"Stamina":55},"Defense":{"Stab":null,"Cut":null,"Impact":null,"Penetration":null,"Shrapnel":null,"Burn":null,"Cold":null,"Acid":null,"Electric":null}},"Attacks":[],"Mob":{"Name":"Horned Bird","Links":{"$Url":"/mobs/310"}},"Links":{"$Url":"/mobmaturities/1732"}},{"Id":1733,"Name":"Alpha","Properties":{"Description":null,"Health":660,"AttacksPerMinute":null,"Level":27,"RegenerationInterval":null,"RegenerationAmount":null,"MissChance":null,"Taming":{"IsTameable":false,"TamingLevel":null},"Attributes":{"Strength":10,"Agility":10,"Intelligence":10,"Psyche":10,"Stamina":66},"Defense":{"Stab":null,"Cut":null,"Impact":null,"Penetration":null,"Shrapnel":null,"Burn":null,"Cold":null,"Acid":null,"Electric":null}},"Attacks":[],"Mob":{"Name":"Horned Bird","Links":{"$Url":"/mobs/310"}},"Links":{"$Url":"/mobmaturities/1733"}},{"Id":1734,"Name":"Mature","Properties":{"Description":null,"Health":330,"AttacksPerMinute":null,"Level":12,"RegenerationInterval":null,"RegenerationAmount":null,"MissChance":null,"Taming":{"IsTameable":false,"TamingLevel":null},"Attributes":{"Strength":10,"Agility":10,"Intelligence":10,"Psyche":10,"Stamina":33},"Defense":{"Stab":null,"Cut":null,"Impact":null,"Penetration":null,"Shrapnel":null,"Burn":null,"Cold":null,"Acid":null,"Electric":null}},"Attacks":[{"Name":"Primary","Damage":{"Stab":6,"Cut":6,"Impact":15,"Penetration":null,"Shrapnel":null,"Burn":null,"Cold":null,"Acid":null,"Electric":null},"TotalDamage":null,"IsAoE":false}],"Mob":{"Name":"Horned Bird","Links":{"$Url":"/mobs/310"}},"Links":{"$Url":"/mobmaturities/1734"}},{"Id":1735,"Name":"Young","Properties":{"Description":null,"Health":220,"AttacksPerMinute":null,"Level":8,"RegenerationInterval":null,"RegenerationAmount":null,"MissChance":null,"Taming":{"IsTameable":false,"TamingLevel":null},"Attributes":{"Strength":10,"Agility":10,"Intelligence":10,"Psyche":10,"Stamina":22},"Defense":{"Stab":null,"Cut":null,"Impact":null,"Penetration":null,"Shrapnel":null,"Burn":null,"Cold":null,"Acid":null,"Electric":null}},"Attacks":[{"Name":"Primary","Damage":{"Stab":3,"Cut":3,"Impact":12,"Penetration":null,"Shrapnel":null,"Burn":null,"Cold":null,"Acid":null,"Electric":null},"TotalDamage":null,"IsAoE":false}],"Mob":{"Name":"Horned Bird","Links":{"$Url":"/mobs/310"}},"Links":{"$Url":"/mobmaturities/1735"}}],"Spawns":[],"Loots":[{"Mob":{"Name":"Horned Bird","Planet":{"Name":"Cyrene","Links":{"$Url":"/planets/7"}},"Links":{"$Url":"/mobs/310"}},"Maturity":{"Name":"Provider","Links":{"$Url":"/mobmaturities/1732"}},"Item":{"Name":"Advanced Metal Extractor","Properties":{"Type":"Material"},"Links":{"$Url":"/materials/40"}},"Frequency":"Uncommon","LastVU":"17.15.1","IsEvent":false,"IsDropping":true},{"Mob":{"Name":"Horned Bird","Planet":{"Name":"Cyrene","Links":{"$Url":"/planets/7"}},"Links":{"$Url":"/mobs/310"}},"Maturity":{"Name":"Adult","Links":{"$Url":"/mobmaturities/1731"}},"Item":{"Name":"Advanced Mineral Extractor","Properties":{"Type":"Material"},"Links":{"$Url":"/materials/41"}},"Frequency":"Common","LastVU":"17.13.0","IsEvent":false,"IsDropping":true},{"Mob":{"Name":"Horned Bird","Planet":{"Name":"Cyrene","Links":{"$Url":"/planets/7"}},"Links":{"$Url":"/mobs/310"}},"Maturity":{"Name":"Alpha","Links":{"$Url":"/mobmaturities/1733"}},"Item":{"Name":"Animal Adrenal Oil","Properties":{"Type":"Material"},"Links":{"$Url":"/materials/115"}},"Frequency":"Common","LastVU":"17.13.0","IsEvent":false,"IsDropping":true},{"Mob":{"Name":"Horned Bird","Planet":{"Name":"Cyrene","Links":{"$Url":"/planets/7"}},"Links":{"$Url":"/mobs/310"}},"Maturity":{"Name":"Young","Links":{"$Url":"/mobmaturities/1735"}},"Item":{"Name":"Animal Eye Oil","Properties":{"Type":"Material"},"Links":{"$Url":"/materials/119"}},"Frequency":"Often","LastVU":"17.23.2.a","IsEvent":false,"IsDropping":true},{"Mob":{"Name":"Horned Bird","Planet":{"Name":"Cyrene","Links":{"$Url":"/planets/7"}},"Links":{"$Url":"/mobs/310"}},"Maturity":{"Name":"Young","Links":{"$Url":"/mobmaturities/1735"}},"Item":{"Name":"Animal Hide","Properties":{"Type":"Material"},"Links":{"$Url":"/materials/121"}},"Frequency":"Common","LastVU":"17.23.0","IsEvent":false,"IsDropping":true},{"Mob":{"Name":"Horned Bird","Planet":{"Name":"Cyrene","Links":{"$Url":"/planets/7"}},"Links":{"$Url":"/mobs/310"}},"Maturity":{"Name":"Young","Links":{"$Url":"/mobmaturities/1735"}},"Item":{"Name":"Animal Muscle Oil","Properties":{"Type":"Material"},"Links":{"$Url":"/materials/124"}},"Frequency":"Often","LastVU":"17.23.2.a","IsEvent":false,"IsDropping":true},{"Mob":{"Name":"Horned Bird","Planet":{"Name":"Cyrene","Links":{"$Url":"/planets/7"}},"Links":{"$Url":"/mobs/310"}},"Maturity":{"Name":"Young","Links":{"$Url":"/mobmaturities/1735"}},"Item":{"Name":"Animal Oil Residue","Properties":{"Type":"Material"},"Links":{"$Url":"/materials/125"}},"Frequency":"Often","LastVU":"17.23.2.a","IsEvent":false,"IsDropping":true},{"Mob":{"Name":"Horned Bird","Planet":{"Name":"Cyrene","Links":{"$Url":"/planets/7"}},"Links":{"$Url":"/mobs/310"}},"Maturity":{"Name":"Provider","Links":{"$Url":"/mobmaturities/1732"}},"Item":{"Name":"Animal Thyroid Oil","Properties":{"Type":"Material"},"Links":{"$Url":"/materials/128"}},"Frequency":"Common","LastVU":"17.23.2.a","IsEvent":false,"IsDropping":true},{"Mob":{"Name":"Horned Bird","Planet":{"Name":"Cyrene","Links":{"$Url":"/planets/7"}},"Links":{"$Url":"/mobs/310"}},"Maturity":{"Name":"Mature","Links":{"$Url":"/mobmaturities/1734"}},"Item":{"Name":"Basic Gem Extractor","Properties":{"Type":"Material"},"Links":{"$Url":"/materials/245"}},"Frequency":"Uncommon","LastVU":"17.13.0","IsEvent":false,"IsDropping":true},{"Mob":{"Name":"Horned Bird","Planet":{"Name":"Cyrene","Links":{"$Url":"/planets/7"}},"Links":{"$Url":"/mobs/310"}},"Maturity":{"Name":"Mature","Links":{"$Url":"/mobmaturities/1734"}},"Item":{"Name":"Basic Metal Extractor","Properties":{"Type":"Material"},"Links":{"$Url":"/materials/248"}},"Frequency":"Uncommon","LastVU":"17.13.0","IsEvent":false,"IsDropping":true},{"Mob":{"Name":"Horned Bird","Planet":{"Name":"Cyrene","Links":{"$Url":"/planets/7"}},"Links":{"$Url":"/mobs/310"}},"Maturity":{"Name":"Young","Links":{"$Url":"/mobmaturities/1735"}},"Item":{"Name":"Big Bird Wing","Properties":{"Type":"Material"},"Links":{"$Url":"/materials/308"}},"Frequency":"Common","LastVU":"17.18.1","IsEvent":false,"IsDropping":true},{"Mob":{"Name":"Horned Bird","Planet":{"Name":"Cyrene","Links":{"$Url":"/planets/7"}},"Links":{"$Url":"/mobs/310"}},"Maturity":{"Name":"Young","Links":{"$Url":"/mobmaturities/1735"}},"Item":{"Name":"Diluted Cloth Extractor","Properties":{"Type":"Material"},"Links":{"$Url":"/materials/611"}},"Frequency":"Often","LastVU":"17.18.1","IsEvent":false,"IsDropping":true},{"Mob":{"Name":"Horned Bird","Planet":{"Name":"Cyrene","Links":{"$Url":"/planets/7"}},"Links":{"$Url":"/mobs/310"}},"Maturity":{"Name":"Young","Links":{"$Url":"/mobmaturities/1735"}},"Item":{"Name":"Electronic Stabilizing Component","Properties":{"Type":"Material"},"Links":{"$Url":"/materials/665"}},"Frequency":"Common","LastVU":"17.23.2.a","IsEvent":false,"IsDropping":true},{"Mob":{"Name":"Horned Bird","Planet":{"Name":"Cyrene","Links":{"$Url":"/planets/7"}},"Links":{"$Url":"/mobs/310"}},"Maturity":{"Name":"Young","Links":{"$Url":"/mobmaturities/1735"}},"Item":{"Name":"Fine Wool","Properties":{"Type":"Material"},"Links":{"$Url":"/materials/795"}},"Frequency":"Uncommon","LastVU":"17.23.2.a","IsEvent":false,"IsDropping":true},{"Mob":{"Name":"Horned Bird","Planet":{"Name":"Cyrene","Links":{"$Url":"/planets/7"}},"Links":{"$Url":"/mobs/310"}},"Maturity":{"Name":"Adult","Links":{"$Url":"/mobmaturities/1731"}},"Item":{"Name":"Interactive Simplifier Component","Properties":{"Type":"Material"},"Links":{"$Url":"/materials/1134"}},"Frequency":"Common","LastVU":"17.23.2.a","IsEvent":false,"IsDropping":true},{"Mob":{"Name":"Horned Bird","Planet":{"Name":"Cyrene","Links":{"$Url":"/planets/7"}},"Links":{"$Url":"/mobs/310"}},"Maturity":{"Name":"Young","Links":{"$Url":"/mobmaturities/1735"}},"Item":{"Name":"Paint Can (Dark Green)","Properties":{"Type":"Material"},"Links":{"$Url":"/materials/1654"}},"Frequency":"Uncommon","LastVU":"17.13.0","IsEvent":false,"IsDropping":true},{"Mob":{"Name":"Horned Bird","Planet":{"Name":"Cyrene","Links":{"$Url":"/planets/7"}},"Links":{"$Url":"/mobs/310"}},"Maturity":{"Name":"Adult","Links":{"$Url":"/mobmaturities/1731"}},"Item":{"Name":"Paint Can (Dark Purple)","Properties":{"Type":"Material"},"Links":{"$Url":"/materials/1657"}},"Frequency":"Uncommon","LastVU":"17.2.2a","IsEvent":false,"IsDropping":true},{"Mob":{"Name":"Horned Bird","Planet":{"Name":"Cyrene","Links":{"$Url":"/planets/7"}},"Links":{"$Url":"/mobs/310"}},"Maturity":{"Name":"Young","Links":{"$Url":"/mobmaturities/1735"}},"Item":{"Name":"Paint Can (Green)","Properties":{"Type":"Material"},"Links":{"$Url":"/materials/1662"}},"Frequency":"Common","LastVU":"17.13.0","IsEvent":false,"IsDropping":true},{"Mob":{"Name":"Horned Bird","Planet":{"Name":"Cyrene","Links":{"$Url":"/planets/7"}},"Links":{"$Url":"/mobs/310"}},"Maturity":{"Name":"Adult","Links":{"$Url":"/mobmaturities/1731"}},"Item":{"Name":"Paint Can (Mauve)","Properties":{"Type":"Material"},"Links":{"$Url":"/materials/1664"}},"Frequency":"Common","LastVU":"17.13.0","IsEvent":false,"IsDropping":true},{"Mob":{"Name":"Horned Bird","Planet":{"Name":"Cyrene","Links":{"$Url":"/planets/7"}},"Links":{"$Url":"/mobs/310"}},"Maturity":{"Name":"Mature","Links":{"$Url":"/mobmaturities/1734"}},"Item":{"Name":"Paint Can (Pink)","Properties":{"Type":"Material"},"Links":{"$Url":"/materials/1668"}},"Frequency":"Common","LastVU":"17.22.2","IsEvent":false,"IsDropping":true},{"Mob":{"Name":"Horned Bird","Planet":{"Name":"Cyrene","Links":{"$Url":"/planets/7"}},"Links":{"$Url":"/mobs/310"}},"Maturity":{"Name":"Young","Links":{"$Url":"/mobmaturities/1735"}},"Item":{"Name":"Paint Can (Turqoise)","Properties":{"Type":"Material"},"Links":{"$Url":"/materials/1673"}},"Frequency":"Common","LastVU":"17.13.0","IsEvent":false,"IsDropping":true},{"Mob":{"Name":"Horned Bird","Planet":{"Name":"Cyrene","Links":{"$Url":"/planets/7"}},"Links":{"$Url":"/mobs/310"}},"Maturity":{"Name":"Young","Links":{"$Url":"/mobmaturities/1735"}},"Item":{"Name":"Socket 1 Component","Properties":{"Type":"Material"},"Links":{"$Url":"/materials/2181"}},"Frequency":"Common","LastVU":"17.22.3","IsEvent":false,"IsDropping":true},{"Mob":{"Name":"Horned Bird","Planet":{"Name":"Cyrene","Links":{"$Url":"/planets/7"}},"Links":{"$Url":"/mobs/310"}},"Maturity":{"Name":"Adult","Links":{"$Url":"/mobmaturities/1731"}},"Item":{"Name":"Socket 2 Component","Properties":{"Type":"Material"},"Links":{"$Url":"/materials/2182"}},"Frequency":"Uncommon","LastVU":"17.23.2.a","IsEvent":false,"IsDropping":true},{"Mob":{"Name":"Horned Bird","Planet":{"Name":"Cyrene","Links":{"$Url":"/planets/7"}},"Links":{"$Url":"/mobs/310"}},"Maturity":{"Name":"Young","Links":{"$Url":"/mobmaturities/1735"}},"Item":{"Name":"Soft Hide","Properties":{"Type":"Material"},"Links":{"$Url":"/materials/2193"}},"Frequency":"Common","LastVU":"17.18.1","IsEvent":false,"IsDropping":true},{"Mob":{"Name":"Horned Bird","Planet":{"Name":"Cyrene","Links":{"$Url":"/planets/7"}},"Links":{"$Url":"/mobs/310"}},"Maturity":{"Name":"Young","Links":{"$Url":"/mobmaturities/1735"}},"Item":{"Name":"Strong Cloth Extractor","Properties":{"Type":"Material"},"Links":{"$Url":"/materials/2254"}},"Frequency":"Often","LastVU":"17.13.0","IsEvent":false,"IsDropping":true},{"Mob":{"Name":"Horned Bird","Planet":{"Name":"Cyrene","Links":{"$Url":"/planets/7"}},"Links":{"$Url":"/mobs/310"}},"Maturity":{"Name":"Young","Links":{"$Url":"/mobmaturities/1735"}},"Item":{"Name":"Wool","Properties":{"Type":"Material"},"Links":{"$Url":"/materials/2533"}},"Frequency":"Common","LastVU":"17.23.2.a","IsEvent":false,"IsDropping":true}],"Links":{"$Url":"/mobs/310"}}