{"Id":781,"Name":"Megalodon","Type":"Animal","Properties":{"Description":null,"AttackRange":null,"AggressionRange":null,"IsSweatable":false},"DefensiveProfession":{"Name":"Evader","Links":{"$Url":"/professions/42"}},"ScanningProfession":{"Name":"Animal Investigator","Links":{"$Url":"/professions/1"}},"Planet":{"Name":"Next Island","Links":{"$Url":"/planets/6"}},"Species":{"Name":"Shark","Properties":{"CodexBaseCost":125,"CodexType":"Mob"},"Links":{"$Url":"/mobspecies/249"}},"Maturities":[{"Id":2306,"Name":"Default","Properties":{"Description":null,"Health":170000,"AttacksPerMinute":null,"Level":640,"RegenerationInterval":null,"RegenerationAmount":null,"MissChance":null,"Taming":{"IsTameable":false,"TamingLevel":null},"Attributes":{"Strength":165,"Agility":110,"Intelligence":90,"Psyche":60,"Stamina":17000},"Defense":{"Stab":null,"Cut":null,"Impact":null,"Penetration":null,"Shrapnel":null,"Burn":null,"Cold":null,"Acid":null,"Electric":null}},"Attacks":[],"Mob":{"Name":"Megalodon","Links":{"$Url":"/mobs/781"}},"Links":{"$Url":"/mobmaturities/2306"}}],"Spawns":[],"Loots":[{"Mob":{"Name":"Megalodon","Planet":{"Name":"Next Island","Links":{"$Url":"/planets/6"}},"Links":{"$Url":"/mobs/781"}},"Maturity":{"Name":null,"Links":{"$Url":"/mobmaturities/null"}},"Item":{"Name":"Animal Oil Residue","Properties":{"Type":"Material"},"Links":{"$Url":"/materials/125"}},"Frequency":"Very often","LastVU":"17.12.1","IsEvent":false,"IsDropping":true},{"Mob":{"Name":"Megalodon","Planet":{"Name":"Next Island","Links":{"$Url":"/planets/6"}},"Links":{"$Url":"/mobs/781"}},"Maturity":{"Name":null,"Links":{"$Url":"/mobmaturities/null"}},"Item":{"Name":"Animal Pancreas Oil","Properties":{"Type":"Material"},"Links":{"$Url":"/materials/126"}},"Frequency":"Very often","LastVU":"17.12.1","IsEvent":false,"IsDropping":true},{"Mob":{"Name":"Megalodon","Planet":{"Name":"Next Island","Links":{"$Url":"/planets/6"}},"Links":{"$Url":"/mobs/781"}},"Maturity":{"Name":null,"Links":{"$Url":"/mobmaturities/null"}},"Item":{"Name":"High Definition GUI Component","Properties":{"Type":"Material"},"Links":{"$Url":"/materials/1058"}},"Frequency":"Often","LastVU":"17.12.1","IsEvent":false,"IsDropping":true}],"Links":{"$Url":"/mobs/781"}}