{"Id":388,"Name":"Mayhem Mulmun","Type":"Mutant","Properties":{"Description":null,"AttackRange":null,"AggressionRange":null,"IsSweatable":false},"DefensiveProfession":{"Name":"Evader","Links":{"$Url":"/professions/42"}},"ScanningProfession":{"Name":"Mutant Investigator","Links":{"$Url":"/professions/47"}},"Planet":{"Name":"Calypso","Links":{"$Url":"/planets/1"}},"Species":{"Name":"Mulmun","Properties":{"CodexBaseCost":63.75,"CodexType":"Mob"},"Links":{"$Url":"/mobspecies/89"}},"Maturities":[{"Id":2248,"Name":"2","Properties":{"Description":null,"Health":900,"AttacksPerMinute":null,"Level":9,"RegenerationInterval":null,"RegenerationAmount":null,"MissChance":null,"Taming":{"IsTameable":false,"TamingLevel":null},"Attributes":{"Strength":12,"Agility":10,"Intelligence":2,"Psyche":2,"Stamina":90},"Defense":{"Stab":null,"Cut":null,"Impact":null,"Penetration":null,"Shrapnel":null,"Burn":null,"Cold":null,"Acid":null,"Electric":null}},"Attacks":[],"Mob":{"Name":"Mayhem Mulmun","Links":{"$Url":"/mobs/388"}},"Links":{"$Url":"/mobmaturities/2248"}},{"Id":2247,"Name":"1","Properties":{"Description":null,"Health":640,"AttacksPerMinute":null,"Level":7,"RegenerationInterval":null,"RegenerationAmount":null,"MissChance":null,"Taming":{"IsTameable":false,"TamingLevel":null},"Attributes":{"Strength":12,"Agility":10,"Intelligence":1,"Psyche":2,"Stamina":64},"Defense":{"Stab":null,"Cut":null,"Impact":null,"Penetration":null,"Shrapnel":null,"Burn":null,"Cold":null,"Acid":null,"Electric":null}},"Attacks":[],"Mob":{"Name":"Mayhem Mulmun","Links":{"$Url":"/mobs/388"}},"Links":{"$Url":"/mobmaturities/2247"}},{"Id":2249,"Name":"3","Properties":{"Description":null,"Health":1130,"AttacksPerMinute":null,"Level":13,"RegenerationInterval":null,"RegenerationAmount":null,"MissChance":null,"Taming":{"IsTameable":false,"TamingLevel":null},"Attributes":{"Strength":12,"Agility":10,"Intelligence":3,"Psyche":2,"Stamina":113},"Defense":{"Stab":null,"Cut":null,"Impact":null,"Penetration":null,"Shrapnel":null,"Burn":null,"Cold":null,"Acid":null,"Electric":null}},"Attacks":[],"Mob":{"Name":"Mayhem Mulmun","Links":{"$Url":"/mobs/388"}},"Links":{"$Url":"/mobmaturities/2249"}},{"Id":2250,"Name":"4","Properties":{"Description":null,"Health":1400,"AttacksPerMinute":null,"Level":16,"RegenerationInterval":null,"RegenerationAmount":null,"MissChance":null,"Taming":{"IsTameable":false,"TamingLevel":null},"Attributes":{"Strength":12,"Agility":10,"Intelligence":4,"Psyche":2,"Stamina":140},"Defense":{"Stab":null,"Cut":null,"Impact":null,"Penetration":null,"Shrapnel":null,"Burn":null,"Cold":null,"Acid":null,"Electric":null}},"Attacks":[],"Mob":{"Name":"Mayhem Mulmun","Links":{"$Url":"/mobs/388"}},"Links":{"$Url":"/mobmaturities/2250"}},{"Id":2251,"Name":"5","Properties":{"Description":null,"Health":1550,"AttacksPerMinute":null,"Level":19,"RegenerationInterval":null,"RegenerationAmount":null,"MissChance":null,"Taming":{"IsTameable":false,"TamingLevel":null},"Attributes":{"Strength":12,"Agility":10,"Intelligence":5,"Psyche":2,"Stamina":155},"Defense":{"Stab":null,"Cut":null,"Impact":null,"Penetration":null,"Shrapnel":null,"Burn":null,"Cold":null,"Acid":null,"Electric":null}},"Attacks":[],"Mob":{"Name":"Mayhem Mulmun","Links":{"$Url":"/mobs/388"}},"Links":{"$Url":"/mobmaturities/2251"}},{"Id":2252,"Name":"6","Properties":{"Description":null,"Health":1700,"AttacksPerMinute":null,"Level":23,"RegenerationInterval":null,"RegenerationAmount":null,"MissChance":null,"Taming":{"IsTameable":false,"TamingLevel":null},"Attributes":{"Strength":12,"Agility":10,"Intelligence":6,"Psyche":2,"Stamina":170},"Defense":{"Stab":null,"Cut":null,"Impact":null,"Penetration":null,"Shrapnel":null,"Burn":null,"Cold":null,"Acid":null,"Electric":null}},"Attacks":[],"Mob":{"Name":"Mayhem Mulmun","Links":{"$Url":"/mobs/388"}},"Links":{"$Url":"/mobmaturities/2252"}},{"Id":2253,"Name":"7","Properties":{"Description":null,"Health":1850,"AttacksPerMinute":null,"Level":28,"RegenerationInterval":null,"RegenerationAmount":null,"MissChance":null,"Taming":{"IsTameable":false,"TamingLevel":null},"Attributes":{"Strength":12,"Agility":10,"Intelligence":7,"Psyche":2,"Stamina":185},"Defense":{"Stab":null,"Cut":null,"Impact":null,"Penetration":null,"Shrapnel":null,"Burn":null,"Cold":null,"Acid":null,"Electric":null}},"Attacks":[],"Mob":{"Name":"Mayhem Mulmun","Links":{"$Url":"/mobs/388"}},"Links":{"$Url":"/mobmaturities/2253"}},{"Id":2254,"Name":"8","Properties":{"Description":null,"Health":1960,"AttacksPerMinute":null,"Level":34,"RegenerationInterval":null,"RegenerationAmount":null,"MissChance":null,"Taming":{"IsTameable":false,"TamingLevel":null},"Attributes":{"Strength":12,"Agility":10,"Intelligence":8,"Psyche":2,"Stamina":196},"Defense":{"Stab":null,"Cut":null,"Impact":null,"Penetration":null,"Shrapnel":null,"Burn":null,"Cold":null,"Acid":null,"Electric":null}},"Attacks":[],"Mob":{"Name":"Mayhem Mulmun","Links":{"$Url":"/mobs/388"}},"Links":{"$Url":"/mobmaturities/2254"}},{"Id":2255,"Name":"9","Properties":{"Description":null,"Health":2080,"AttacksPerMinute":null,"Level":40,"RegenerationInterval":null,"RegenerationAmount":null,"MissChance":null,"Taming":{"IsTameable":false,"TamingLevel":null},"Attributes":{"Strength":12,"Agility":10,"Intelligence":9,"Psyche":2,"Stamina":208},"Defense":{"Stab":null,"Cut":null,"Impact":null,"Penetration":null,"Shrapnel":null,"Burn":null,"Cold":null,"Acid":null,"Electric":null}},"Attacks":[],"Mob":{"Name":"Mayhem Mulmun","Links":{"$Url":"/mobs/388"}},"Links":{"$Url":"/mobmaturities/2255"}},{"Id":2256,"Name":"10","Properties":{"Description":null,"Health":2260,"AttacksPerMinute":null,"Level":44,"RegenerationInterval":null,"RegenerationAmount":null,"MissChance":null,"Taming":{"IsTameable":false,"TamingLevel":null},"Attributes":{"Strength":12,"Agility":10,"Intelligence":10,"Psyche":2,"Stamina":226},"Defense":{"Stab":null,"Cut":null,"Impact":null,"Penetration":null,"Shrapnel":null,"Burn":null,"Cold":null,"Acid":null,"Electric":null}},"Attacks":[],"Mob":{"Name":"Mayhem Mulmun","Links":{"$Url":"/mobs/388"}},"Links":{"$Url":"/mobmaturities/2256"}}],"Spawns":[],"Loots":[{"Mob":{"Name":"Mayhem Mulmun","Planet":{"Name":"Calypso","Links":{"$Url":"/planets/1"}},"Links":{"$Url":"/mobs/388"}},"Maturity":{"Name":"1","Links":{"$Url":"/mobmaturities/2247"}},"Item":{"Name":"Output Amplifier Component","Properties":{"Type":"Material"},"Links":{"$Url":"/materials/1625"}},"Frequency":"Uncommon","LastVU":"17.20.1a","IsEvent":false,"IsDropping":true},{"Mob":{"Name":"Mayhem Mulmun","Planet":{"Name":"Calypso","Links":{"$Url":"/planets/1"}},"Links":{"$Url":"/mobs/388"}},"Maturity":{"Name":"1","Links":{"$Url":"/mobmaturities/2247"}},"Item":{"Name":"Mayhem Token","Properties":{"Type":"Material"},"Links":{"$Url":"/materials/2803"}},"Frequency":"Uncommon","LastVU":"17.2.2","IsEvent":false,"IsDropping":true},{"Mob":{"Name":"Mayhem Mulmun","Planet":{"Name":"Calypso","Links":{"$Url":"/planets/1"}},"Links":{"$Url":"/mobs/388"}},"Maturity":{"Name":"1","Links":{"$Url":"/mobmaturities/2247"}},"Item":{"Name":"Summer Strongbox","Properties":{"Type":"Material"},"Links":{"$Url":"/materials/2876"}},"Frequency":"Uncommon","LastVU":"17.2.2","IsEvent":false,"IsDropping":true},{"Mob":{"Name":"Mayhem Mulmun","Planet":{"Name":"Calypso","Links":{"$Url":"/planets/1"}},"Links":{"$Url":"/mobs/388"}},"Maturity":{"Name":"8","Links":{"$Url":"/mobmaturities/2254"}},"Item":{"Name":"A&P Series Mayhem SB-90, Adjusted (L)","Properties":{"Type":"Weapon"},"Links":{"$Url":"/weapons/64"}},"Frequency":"Extremely rare","LastVU":"17.2.2","IsEvent":false,"IsDropping":true},{"Mob":{"Name":"Mayhem Mulmun","Planet":{"Name":"Calypso","Links":{"$Url":"/planets/1"}},"Links":{"$Url":"/mobs/388"}},"Maturity":{"Name":"5","Links":{"$Url":"/mobmaturities/2251"}},"Item":{"Name":"A&P Series Mayhem LR-60, Augmented (L)","Properties":{"Type":"Weapon"},"Links":{"$Url":"/weapons/62"}},"Frequency":"Rare","LastVU":"17.20.1a","IsEvent":false,"IsDropping":true},{"Mob":{"Name":"Mayhem Mulmun","Planet":{"Name":"Calypso","Links":{"$Url":"/planets/1"}},"Links":{"$Url":"/mobs/388"}},"Maturity":{"Name":"1","Links":{"$Url":"/mobmaturities/2247"}},"Item":{"Name":"Arsonistic Chip 1 (L)","Properties":{"Type":"Weapon"},"Links":{"$Url":"/weapons/217"}},"Frequency":"Rare","LastVU":"17.20.1a","IsEvent":false,"IsDropping":true},{"Mob":{"Name":"Mayhem Mulmun","Planet":{"Name":"Calypso","Links":{"$Url":"/planets/1"}},"Links":{"$Url":"/mobs/388"}},"Maturity":{"Name":"5","Links":{"$Url":"/mobmaturities/2251"}},"Item":{"Name":"Mayhem Foot Guards (L)","Properties":{"Type":"Armor"},"Links":{"$Url":"/armors/990"}},"Frequency":"Unknown","LastVU":"17.20.1a","IsEvent":false,"IsDropping":true},{"Mob":{"Name":"Mayhem Mulmun","Planet":{"Name":"Calypso","Links":{"$Url":"/planets/1"}},"Links":{"$Url":"/mobs/388"}},"Maturity":{"Name":"5","Links":{"$Url":"/mobmaturities/2251"}},"Item":{"Name":"Mayhem Helmet (L)","Properties":{"Type":"Armor"},"Links":{"$Url":"/armors/996"}},"Frequency":"Rare","LastVU":"17.20.1a","IsEvent":false,"IsDropping":true}],"Links":{"$Url":"/mobs/388"}}