{"Id":767,"Name":"Great White Shark","Type":"Animal","Properties":{"Description":null,"AttackRange":null,"AggressionRange":null,"IsSweatable":false},"DefensiveProfession":{"Name":"Evader","Links":{"$Url":"/professions/42"}},"ScanningProfession":{"Name":"Animal Investigator","Links":{"$Url":"/professions/1"}},"Planet":{"Name":"Next Island","Links":{"$Url":"/planets/6"}},"Species":{"Name":"Shark","Properties":{"CodexBaseCost":125,"CodexType":"Mob"},"Links":{"$Url":"/mobspecies/249"}},"Maturities":[{"Id":1573,"Name":"Old","Properties":{"Description":null,"Health":2400,"AttacksPerMinute":null,"Level":31,"RegenerationInterval":null,"RegenerationAmount":null,"MissChance":null,"Taming":{"IsTameable":false,"TamingLevel":null},"Attributes":{"Strength":90,"Agility":45,"Intelligence":20,"Psyche":20,"Stamina":240},"Defense":{"Stab":null,"Cut":null,"Impact":null,"Penetration":null,"Shrapnel":null,"Burn":null,"Cold":null,"Acid":null,"Electric":null}},"Attacks":[{"Name":"Primary","Damage":{"Stab":33,"Cut":33,"Impact":33,"Penetration":null,"Shrapnel":null,"Burn":null,"Cold":null,"Acid":null,"Electric":null},"TotalDamage":null,"IsAoE":false}],"Mob":{"Name":"Great White Shark","Links":{"$Url":"/mobs/767"}},"Links":{"$Url":"/mobmaturities/1573"}},{"Id":1574,"Name":"Jaws","Properties":{"Description":null,"Health":3200,"AttacksPerMinute":null,"Level":35,"RegenerationInterval":null,"RegenerationAmount":null,"MissChance":null,"Taming":{"IsTameable":false,"TamingLevel":null},"Attributes":{"Strength":110,"Agility":65,"Intelligence":40,"Psyche":40,"Stamina":320},"Defense":{"Stab":null,"Cut":null,"Impact":null,"Penetration":null,"Shrapnel":null,"Burn":null,"Cold":null,"Acid":null,"Electric":null}},"Attacks":[],"Mob":{"Name":"Great White Shark","Links":{"$Url":"/mobs/767"}},"Links":{"$Url":"/mobmaturities/1574"}},{"Id":1575,"Name":"Old Alpha","Properties":{"Description":null,"Health":3600,"AttacksPerMinute":null,"Level":43,"RegenerationInterval":null,"RegenerationAmount":null,"MissChance":null,"Taming":{"IsTameable":false,"TamingLevel":null},"Attributes":{"Strength":35,"Agility":35,"Intelligence":20,"Psyche":15,"Stamina":360},"Defense":{"Stab":null,"Cut":null,"Impact":null,"Penetration":null,"Shrapnel":null,"Burn":null,"Cold":null,"Acid":null,"Electric":null}},"Attacks":[],"Mob":{"Name":"Great White Shark","Links":{"$Url":"/mobs/767"}},"Links":{"$Url":"/mobmaturities/1575"}},{"Id":1576,"Name":"Provider","Properties":{"Description":null,"Health":2600,"AttacksPerMinute":null,"Level":33,"RegenerationInterval":null,"RegenerationAmount":null,"MissChance":null,"Taming":{"IsTameable":false,"TamingLevel":null},"Attributes":{"Strength":90,"Agility":45,"Intelligence":20,"Psyche":20,"Stamina":260},"Defense":{"Stab":null,"Cut":null,"Impact":null,"Penetration":null,"Shrapnel":null,"Burn":null,"Cold":null,"Acid":null,"Electric":null}},"Attacks":[],"Mob":{"Name":"Great White Shark","Links":{"$Url":"/mobs/767"}},"Links":{"$Url":"/mobmaturities/1576"}},{"Id":1577,"Name":"Alpha","Properties":{"Description":null,"Health":3400,"AttacksPerMinute":null,"Level":41,"RegenerationInterval":null,"RegenerationAmount":null,"MissChance":null,"Taming":{"IsTameable":false,"TamingLevel":null},"Attributes":{"Strength":35,"Agility":35,"Intelligence":30,"Psyche":10,"Stamina":340},"Defense":{"Stab":null,"Cut":null,"Impact":null,"Penetration":null,"Shrapnel":null,"Burn":null,"Cold":null,"Acid":null,"Electric":null}},"Attacks":[],"Mob":{"Name":"Great White Shark","Links":{"$Url":"/mobs/767"}},"Links":{"$Url":"/mobmaturities/1577"}},{"Id":1578,"Name":"Dominant","Properties":{"Description":null,"Health":3200,"AttacksPerMinute":null,"Level":38,"RegenerationInterval":null,"RegenerationAmount":null,"MissChance":null,"Taming":{"IsTameable":false,"TamingLevel":null},"Attributes":{"Strength":30,"Agility":35,"Intelligence":10,"Psyche":10,"Stamina":320},"Defense":{"Stab":null,"Cut":null,"Impact":null,"Penetration":null,"Shrapnel":null,"Burn":null,"Cold":null,"Acid":null,"Electric":null}},"Attacks":[],"Mob":{"Name":"Great White Shark","Links":{"$Url":"/mobs/767"}},"Links":{"$Url":"/mobmaturities/1578"}},{"Id":1579,"Name":"Mature","Properties":{"Description":null,"Health":2200,"AttacksPerMinute":null,"Level":25,"RegenerationInterval":null,"RegenerationAmount":null,"MissChance":null,"Taming":{"IsTameable":false,"TamingLevel":null},"Attributes":{"Strength":90,"Agility":45,"Intelligence":20,"Psyche":20,"Stamina":220},"Defense":{"Stab":null,"Cut":null,"Impact":null,"Penetration":null,"Shrapnel":null,"Burn":null,"Cold":null,"Acid":null,"Electric":null}},"Attacks":[],"Mob":{"Name":"Great White Shark","Links":{"$Url":"/mobs/767"}},"Links":{"$Url":"/mobmaturities/1579"}},{"Id":1580,"Name":"Young","Properties":{"Description":null,"Health":2000,"AttacksPerMinute":null,"Level":23,"RegenerationInterval":null,"RegenerationAmount":null,"MissChance":null,"Taming":{"IsTameable":false,"TamingLevel":null},"Attributes":{"Strength":90,"Agility":45,"Intelligence":20,"Psyche":20,"Stamina":200},"Defense":{"Stab":null,"Cut":null,"Impact":null,"Penetration":null,"Shrapnel":null,"Burn":null,"Cold":null,"Acid":null,"Electric":null}},"Attacks":[],"Mob":{"Name":"Great White Shark","Links":{"$Url":"/mobs/767"}},"Links":{"$Url":"/mobmaturities/1580"}},{"Id":1581,"Name":"Prowler","Properties":{"Description":null,"Health":3800,"AttacksPerMinute":null,"Level":46,"RegenerationInterval":null,"RegenerationAmount":null,"MissChance":null,"Taming":{"IsTameable":false,"TamingLevel":null},"Attributes":{"Strength":40,"Agility":35,"Intelligence":30,"Psyche":10,"Stamina":380},"Defense":{"Stab":null,"Cut":null,"Impact":null,"Penetration":null,"Shrapnel":null,"Burn":null,"Cold":null,"Acid":null,"Electric":null}},"Attacks":[],"Mob":{"Name":"Great White Shark","Links":{"$Url":"/mobs/767"}},"Links":{"$Url":"/mobmaturities/1581"}},{"Id":1582,"Name":"Stalker","Properties":{"Description":null,"Health":4000,"AttacksPerMinute":null,"Level":49,"RegenerationInterval":null,"RegenerationAmount":null,"MissChance":null,"Taming":{"IsTameable":false,"TamingLevel":null},"Attributes":{"Strength":40,"Agility":35,"Intelligence":20,"Psyche":10,"Stamina":400},"Defense":{"Stab":null,"Cut":null,"Impact":null,"Penetration":null,"Shrapnel":null,"Burn":null,"Cold":null,"Acid":null,"Electric":null}},"Attacks":[],"Mob":{"Name":"Great White Shark","Links":{"$Url":"/mobs/767"}},"Links":{"$Url":"/mobmaturities/1582"}}],"Spawns":[],"Loots":[{"Mob":{"Name":"Great White Shark","Planet":{"Name":"Next Island","Links":{"$Url":"/planets/6"}},"Links":{"$Url":"/mobs/767"}},"Maturity":{"Name":"Mature","Links":{"$Url":"/mobmaturities/1579"}},"Item":{"Name":"Adaptive Fire Rate Component","Properties":{"Type":"Material"},"Links":{"$Url":"/materials/24"}},"Frequency":"Common","LastVU":"17.22.3","IsEvent":false,"IsDropping":true},{"Mob":{"Name":"Great White Shark","Planet":{"Name":"Next Island","Links":{"$Url":"/planets/6"}},"Links":{"$Url":"/mobs/767"}},"Maturity":{"Name":"Dominant","Links":{"$Url":"/mobmaturities/1578"}},"Item":{"Name":"Advanced Gem Extractor","Properties":{"Type":"Material"},"Links":{"$Url":"/materials/36"}},"Frequency":"Common","LastVU":"17.22.3","IsEvent":false,"IsDropping":true},{"Mob":{"Name":"Great White Shark","Planet":{"Name":"Next Island","Links":{"$Url":"/planets/6"}},"Links":{"$Url":"/mobs/767"}},"Maturity":{"Name":"Dominant","Links":{"$Url":"/mobmaturities/1578"}},"Item":{"Name":"Advanced Metal Extractor","Properties":{"Type":"Material"},"Links":{"$Url":"/materials/40"}},"Frequency":"Common","LastVU":"17.21.2","IsEvent":false,"IsDropping":true},{"Mob":{"Name":"Great White Shark","Planet":{"Name":"Next Island","Links":{"$Url":"/planets/6"}},"Links":{"$Url":"/mobs/767"}},"Maturity":{"Name":"Mature","Links":{"$Url":"/mobmaturities/1579"}},"Item":{"Name":"Animal Adrenal Oil","Properties":{"Type":"Material"},"Links":{"$Url":"/materials/115"}},"Frequency":"Often","LastVU":"17.23.2.a","IsEvent":false,"IsDropping":true},{"Mob":{"Name":"Great White Shark","Planet":{"Name":"Next Island","Links":{"$Url":"/planets/6"}},"Links":{"$Url":"/mobs/767"}},"Maturity":{"Name":"Old","Links":{"$Url":"/mobmaturities/1573"}},"Item":{"Name":"Animal Eye Oil","Properties":{"Type":"Material"},"Links":{"$Url":"/materials/119"}},"Frequency":"Very often","LastVU":"17.23.2.a","IsEvent":false,"IsDropping":true},{"Mob":{"Name":"Great White Shark","Planet":{"Name":"Next Island","Links":{"$Url":"/planets/6"}},"Links":{"$Url":"/mobs/767"}},"Maturity":{"Name":"Young","Links":{"$Url":"/mobmaturities/1580"}},"Item":{"Name":"Animal Hide","Properties":{"Type":"Material"},"Links":{"$Url":"/materials/121"}},"Frequency":"Common","LastVU":"17.22.3","IsEvent":false,"IsDropping":true},{"Mob":{"Name":"Great White Shark","Planet":{"Name":"Next Island","Links":{"$Url":"/planets/6"}},"Links":{"$Url":"/mobs/767"}},"Maturity":{"Name":"Old Alpha","Links":{"$Url":"/mobmaturities/1575"}},"Item":{"Name":"Animal Kidney Oil","Properties":{"Type":"Material"},"Links":{"$Url":"/materials/122"}},"Frequency":"Common","LastVU":"17.22.3","IsEvent":false,"IsDropping":true},{"Mob":{"Name":"Great White Shark","Planet":{"Name":"Next Island","Links":{"$Url":"/planets/6"}},"Links":{"$Url":"/mobs/767"}},"Maturity":{"Name":null,"Links":{"$Url":"/mobmaturities/null"}},"Item":{"Name":"Animal Liver Oil","Properties":{"Type":"Material"},"Links":{"$Url":"/materials/123"}},"Frequency":"Often","LastVU":"17.13.0","IsEvent":false,"IsDropping":true},{"Mob":{"Name":"Great White Shark","Planet":{"Name":"Next Island","Links":{"$Url":"/planets/6"}},"Links":{"$Url":"/mobs/767"}},"Maturity":{"Name":"Old","Links":{"$Url":"/mobmaturities/1573"}},"Item":{"Name":"Animal Oil Residue","Properties":{"Type":"Material"},"Links":{"$Url":"/materials/125"}},"Frequency":"Very often","LastVU":"17.23.2.a","IsEvent":false,"IsDropping":true},{"Mob":{"Name":"Great White Shark","Planet":{"Name":"Next Island","Links":{"$Url":"/planets/6"}},"Links":{"$Url":"/mobs/767"}},"Maturity":{"Name":"Dominant","Links":{"$Url":"/mobmaturities/1578"}},"Item":{"Name":"Animal Pancreas Oil","Properties":{"Type":"Material"},"Links":{"$Url":"/materials/126"}},"Frequency":"Very often","LastVU":"17.22.3","IsEvent":false,"IsDropping":true},{"Mob":{"Name":"Great White Shark","Planet":{"Name":"Next Island","Links":{"$Url":"/planets/6"}},"Links":{"$Url":"/mobs/767"}},"Maturity":{"Name":"Old","Links":{"$Url":"/mobmaturities/1573"}},"Item":{"Name":"Animal Thyroid Oil","Properties":{"Type":"Material"},"Links":{"$Url":"/materials/128"}},"Frequency":"Very often","LastVU":"17.22.3","IsEvent":false,"IsDropping":true},{"Mob":{"Name":"Great White Shark","Planet":{"Name":"Next Island","Links":{"$Url":"/planets/6"}},"Links":{"$Url":"/mobs/767"}},"Maturity":{"Name":"Dominant","Links":{"$Url":"/mobmaturities/1578"}},"Item":{"Name":"Basic Cloth Extractor","Properties":{"Type":"Material"},"Links":{"$Url":"/materials/239"}},"Frequency":"Uncommon","LastVU":"17.22.3","IsEvent":false,"IsDropping":true},{"Mob":{"Name":"Great White Shark","Planet":{"Name":"Next Island","Links":{"$Url":"/planets/6"}},"Links":{"$Url":"/mobs/767"}},"Maturity":{"Name":"Provider","Links":{"$Url":"/mobmaturities/1576"}},"Item":{"Name":"Basic Stone Extractor","Properties":{"Type":"Material"},"Links":{"$Url":"/materials/267"}},"Frequency":"Often","LastVU":"17.22.3","IsEvent":false,"IsDropping":true},{"Mob":{"Name":"Great White Shark","Planet":{"Name":"Next Island","Links":{"$Url":"/planets/6"}},"Links":{"$Url":"/mobs/767"}},"Maturity":{"Name":"Old","Links":{"$Url":"/mobmaturities/1573"}},"Item":{"Name":"Bio ID Verification","Properties":{"Type":"Material"},"Links":{"$Url":"/materials/316"}},"Frequency":"Uncommon","LastVU":"17.22.3","IsEvent":false,"IsDropping":true},{"Mob":{"Name":"Great White Shark","Planet":{"Name":"Next Island","Links":{"$Url":"/planets/6"}},"Links":{"$Url":"/mobs/767"}},"Maturity":{"Name":"Stalker","Links":{"$Url":"/mobmaturities/1582"}},"Item":{"Name":"Cosmetic Pen (White)","Properties":{"Type":"Material"},"Links":{"$Url":"/materials/528"}},"Frequency":"Uncommon","LastVU":"17.13.0","IsEvent":false,"IsDropping":true},{"Mob":{"Name":"Great White Shark","Planet":{"Name":"Next Island","Links":{"$Url":"/planets/6"}},"Links":{"$Url":"/mobs/767"}},"Maturity":{"Name":"Old","Links":{"$Url":"/mobmaturities/1573"}},"Item":{"Name":"Danburite Crystal","Properties":{"Type":"Material"},"Links":{"$Url":"/materials/587"}},"Frequency":"Very often","LastVU":"17.23.2.a","IsEvent":false,"IsDropping":true},{"Mob":{"Name":"Great White Shark","Planet":{"Name":"Next Island","Links":{"$Url":"/planets/6"}},"Links":{"$Url":"/mobs/767"}},"Maturity":{"Name":"Stalker","Links":{"$Url":"/mobmaturities/1582"}},"Item":{"Name":"Face Paint (Green)","Properties":{"Type":"Material"},"Links":{"$Url":"/materials/750"}},"Frequency":"Uncommon","LastVU":"17.22.3","IsEvent":false,"IsDropping":true},{"Mob":{"Name":"Great White Shark","Planet":{"Name":"Next Island","Links":{"$Url":"/planets/6"}},"Links":{"$Url":"/mobs/767"}},"Maturity":{"Name":"Stalker","Links":{"$Url":"/mobmaturities/1582"}},"Item":{"Name":"Face Paint (Pale Brown)","Properties":{"Type":"Material"},"Links":{"$Url":"/materials/755"}},"Frequency":"Uncommon","LastVU":"17.22.3","IsEvent":false,"IsDropping":true},{"Mob":{"Name":"Great White Shark","Planet":{"Name":"Next Island","Links":{"$Url":"/planets/6"}},"Links":{"$Url":"/mobs/767"}},"Maturity":{"Name":"Old Alpha","Links":{"$Url":"/mobmaturities/1575"}},"Item":{"Name":"Fine Wool","Properties":{"Type":"Material"},"Links":{"$Url":"/materials/795"}},"Frequency":"Common","LastVU":"17.22.3","IsEvent":false,"IsDropping":true},{"Mob":{"Name":"Great White Shark","Planet":{"Name":"Next Island","Links":{"$Url":"/planets/6"}},"Links":{"$Url":"/mobs/767"}},"Maturity":{"Name":"Prowler","Links":{"$Url":"/mobmaturities/1581"}},"Item":{"Name":"Infrasound Emitter Component","Properties":{"Type":"Material"},"Links":{"$Url":"/materials/1129"}},"Frequency":"Uncommon","LastVU":"17.22.3","IsEvent":false,"IsDropping":true},{"Mob":{"Name":"Great White Shark","Planet":{"Name":"Next Island","Links":{"$Url":"/planets/6"}},"Links":{"$Url":"/mobs/767"}},"Maturity":{"Name":"Dominant","Links":{"$Url":"/mobmaturities/1578"}},"Item":{"Name":"Output Amplifier Component","Properties":{"Type":"Material"},"Links":{"$Url":"/materials/1625"}},"Frequency":"Uncommon","LastVU":"17.13.0","IsEvent":false,"IsDropping":true},{"Mob":{"Name":"Great White Shark","Planet":{"Name":"Next Island","Links":{"$Url":"/planets/6"}},"Links":{"$Url":"/mobs/767"}},"Maturity":{"Name":"Dominant","Links":{"$Url":"/mobmaturities/1578"}},"Item":{"Name":"Paint Can (Brown)","Properties":{"Type":"Material"},"Links":{"$Url":"/materials/1647"}},"Frequency":"Common","LastVU":"17.22.3","IsEvent":false,"IsDropping":true},{"Mob":{"Name":"Great White Shark","Planet":{"Name":"Next Island","Links":{"$Url":"/planets/6"}},"Links":{"$Url":"/mobs/767"}},"Maturity":{"Name":null,"Links":{"$Url":"/mobmaturities/null"}},"Item":{"Name":"Paint Can (Dark Blue)","Properties":{"Type":"Material"},"Links":{"$Url":"/materials/1652"}},"Frequency":"Common","LastVU":"17.17.1a","IsEvent":false,"IsDropping":true},{"Mob":{"Name":"Great White Shark","Planet":{"Name":"Next Island","Links":{"$Url":"/planets/6"}},"Links":{"$Url":"/mobs/767"}},"Maturity":{"Name":"Old","Links":{"$Url":"/mobmaturities/1573"}},"Item":{"Name":"Paint Can (Dark Lavender)","Properties":{"Type":"Material"},"Links":{"$Url":"/materials/1655"}},"Frequency":"Uncommon","LastVU":"17.17.1","IsEvent":false,"IsDropping":true},{"Mob":{"Name":"Great White Shark","Planet":{"Name":"Next Island","Links":{"$Url":"/planets/6"}},"Links":{"$Url":"/mobs/767"}},"Maturity":{"Name":"Young","Links":{"$Url":"/mobmaturities/1580"}},"Item":{"Name":"Paint Can (Navy)","Properties":{"Type":"Material"},"Links":{"$Url":"/materials/1665"}},"Frequency":"Uncommon","LastVU":"17.22.3","IsEvent":false,"IsDropping":true},{"Mob":{"Name":"Great White Shark","Planet":{"Name":"Next Island","Links":{"$Url":"/planets/6"}},"Links":{"$Url":"/mobs/767"}},"Maturity":{"Name":"Old","Links":{"$Url":"/mobmaturities/1573"}},"Item":{"Name":"Paint Can (Yellow)","Properties":{"Type":"Material"},"Links":{"$Url":"/materials/1677"}},"Frequency":"Common","LastVU":"17.22.3","IsEvent":false,"IsDropping":true},{"Mob":{"Name":"Great White Shark","Planet":{"Name":"Next Island","Links":{"$Url":"/planets/6"}},"Links":{"$Url":"/mobs/767"}},"Maturity":{"Name":"Prowler","Links":{"$Url":"/mobmaturities/1581"}},"Item":{"Name":"Powder (Tan)","Properties":{"Type":"Material"},"Links":{"$Url":"/materials/1765"}},"Frequency":"Uncommon","LastVU":"17.22.3","IsEvent":false,"IsDropping":true},{"Mob":{"Name":"Great White Shark","Planet":{"Name":"Next Island","Links":{"$Url":"/planets/6"}},"Links":{"$Url":"/mobs/767"}},"Maturity":{"Name":"Young","Links":{"$Url":"/mobmaturities/1580"}},"Item":{"Name":"Rationalizer Component","Properties":{"Type":"Material"},"Links":{"$Url":"/materials/1836"}},"Frequency":"Common","LastVU":"17.22.3","IsEvent":false,"IsDropping":true},{"Mob":{"Name":"Great White Shark","Planet":{"Name":"Next Island","Links":{"$Url":"/planets/6"}},"Links":{"$Url":"/mobs/767"}},"Maturity":{"Name":"Provider","Links":{"$Url":"/mobmaturities/1576"}},"Item":{"Name":"Socket 2 Component","Properties":{"Type":"Material"},"Links":{"$Url":"/materials/2182"}},"Frequency":"Common","LastVU":"17.22.3","IsEvent":false,"IsDropping":true},{"Mob":{"Name":"Great White Shark","Planet":{"Name":"Next Island","Links":{"$Url":"/planets/6"}},"Links":{"$Url":"/mobs/767"}},"Maturity":{"Name":"Young","Links":{"$Url":"/mobmaturities/1580"}},"Item":{"Name":"Socket 3 Component","Properties":{"Type":"Material"},"Links":{"$Url":"/materials/2183"}},"Frequency":"Uncommon","LastVU":"17.22.3","IsEvent":false,"IsDropping":true},{"Mob":{"Name":"Great White Shark","Planet":{"Name":"Next Island","Links":{"$Url":"/planets/6"}},"Links":{"$Url":"/mobs/767"}},"Maturity":{"Name":null,"Links":{"$Url":"/mobmaturities/null"}},"Item":{"Name":"Socket 4 Component","Properties":{"Type":"Material"},"Links":{"$Url":"/materials/2184"}},"Frequency":"Common","LastVU":"17.22.3","IsEvent":false,"IsDropping":true},{"Mob":{"Name":"Great White Shark","Planet":{"Name":"Next Island","Links":{"$Url":"/planets/6"}},"Links":{"$Url":"/mobs/767"}},"Maturity":{"Name":null,"Links":{"$Url":"/mobmaturities/null"}},"Item":{"Name":"Socket 5 Component","Properties":{"Type":"Material"},"Links":{"$Url":"/materials/2185"}},"Frequency":"Common","LastVU":"17.22.3","IsEvent":false,"IsDropping":true},{"Mob":{"Name":"Great White Shark","Planet":{"Name":"Next Island","Links":{"$Url":"/planets/6"}},"Links":{"$Url":"/mobs/767"}},"Maturity":{"Name":"Provider","Links":{"$Url":"/mobmaturities/1576"}},"Item":{"Name":"Soft Hide","Properties":{"Type":"Material"},"Links":{"$Url":"/materials/2193"}},"Frequency":"Common","LastVU":"17.22.3","IsEvent":false,"IsDropping":true},{"Mob":{"Name":"Great White Shark","Planet":{"Name":"Next Island","Links":{"$Url":"/planets/6"}},"Links":{"$Url":"/mobs/767"}},"Maturity":{"Name":"Old","Links":{"$Url":"/mobmaturities/1573"}},"Item":{"Name":"Super Charger Component","Properties":{"Type":"Material"},"Links":{"$Url":"/materials/2270"}},"Frequency":"Common","LastVU":"17.19.1","IsEvent":false,"IsDropping":true},{"Mob":{"Name":"Great White Shark","Planet":{"Name":"Next Island","Links":{"$Url":"/planets/6"}},"Links":{"$Url":"/mobs/767"}},"Maturity":{"Name":"Old","Links":{"$Url":"/mobmaturities/1573"}},"Item":{"Name":"Thin Wool","Properties":{"Type":"Material"},"Links":{"$Url":"/materials/2347"}},"Frequency":"Common","LastVU":"17.22.3","IsEvent":false,"IsDropping":true},{"Mob":{"Name":"Great White Shark","Planet":{"Name":"Next Island","Links":{"$Url":"/planets/6"}},"Links":{"$Url":"/mobs/767"}},"Maturity":{"Name":null,"Links":{"$Url":"/mobmaturities/null"}},"Item":{"Name":"Tier 2 Component","Properties":{"Type":"Material"},"Links":{"$Url":"/materials/2355"}},"Frequency":"Common","LastVU":"17.22.3","IsEvent":false,"IsDropping":true},{"Mob":{"Name":"Great White Shark","Planet":{"Name":"Next Island","Links":{"$Url":"/planets/6"}},"Links":{"$Url":"/mobs/767"}},"Maturity":{"Name":"Dominant","Links":{"$Url":"/mobmaturities/1578"}},"Item":{"Name":"Tier 3 Component","Properties":{"Type":"Material"},"Links":{"$Url":"/materials/2356"}},"Frequency":"Uncommon","LastVU":"17.17.1a","IsEvent":false,"IsDropping":true},{"Mob":{"Name":"Great White Shark","Planet":{"Name":"Next Island","Links":{"$Url":"/planets/6"}},"Links":{"$Url":"/mobs/767"}},"Maturity":{"Name":"Stalker","Links":{"$Url":"/mobmaturities/1582"}},"Item":{"Name":"Tier 5 Component","Properties":{"Type":"Material"},"Links":{"$Url":"/materials/2358"}},"Frequency":"Common","LastVU":"17.22.3","IsEvent":false,"IsDropping":true},{"Mob":{"Name":"Great White Shark","Planet":{"Name":"Next Island","Links":{"$Url":"/planets/6"}},"Links":{"$Url":"/mobs/767"}},"Maturity":{"Name":"Provider","Links":{"$Url":"/mobmaturities/1576"}},"Item":{"Name":"Wool","Properties":{"Type":"Material"},"Links":{"$Url":"/materials/2533"}},"Frequency":"Common","LastVU":"17.22.3","IsEvent":false,"IsDropping":true},{"Mob":{"Name":"Great White Shark","Planet":{"Name":"Next Island","Links":{"$Url":"/planets/6"}},"Links":{"$Url":"/mobs/767"}},"Maturity":{"Name":"Provider","Links":{"$Url":"/mobmaturities/1576"}},"Item":{"Name":"Kinetic Attack Nanochip 8 (L)","Properties":{"Type":"Weapon"},"Links":{"$Url":"/weapons/1774"}},"Frequency":"Rare","LastVU":"17.3.0","IsEvent":false,"IsDropping":true},{"Mob":{"Name":"Great White Shark","Planet":{"Name":"Next Island","Links":{"$Url":"/planets/6"}},"Links":{"$Url":"/mobs/767"}},"Maturity":{"Name":"Provider","Links":{"$Url":"/mobmaturities/1576"}},"Item":{"Name":"Corrosive Attack Nanochip 8 (L)","Properties":{"Type":"Weapon"},"Links":{"$Url":"/weapons/605"}},"Frequency":"Rare","LastVU":"17.3.0","IsEvent":false,"IsDropping":true},{"Mob":{"Name":"Great White Shark","Planet":{"Name":"Next Island","Links":{"$Url":"/planets/6"}},"Links":{"$Url":"/mobs/767"}},"Maturity":{"Name":"Young","Links":{"$Url":"/mobmaturities/1580"}},"Item":{"Name":"Eir Mk 1","Properties":{"Type":"MedicalTool"},"Links":{"$Url":"/medicaltools/233"}},"Frequency":"Extremely rare","LastVU":"17.22.2","IsEvent":false,"IsDropping":true},{"Mob":{"Name":"Great White Shark","Planet":{"Name":"Next Island","Links":{"$Url":"/planets/6"}},"Links":{"$Url":"/mobs/767"}},"Maturity":{"Name":"Stalker","Links":{"$Url":"/mobmaturities/1582"}},"Item":{"Name":"Empty Skill Implant (L)","Properties":{"Type":"MiscTool"},"Links":{"$Url":"/misctools/157"}},"Frequency":"Rare","LastVU":"17.7","IsEvent":false,"IsDropping":true},{"Mob":{"Name":"Great White Shark","Planet":{"Name":"Next Island","Links":{"$Url":"/planets/6"}},"Links":{"$Url":"/mobs/767"}},"Maturity":{"Name":null,"Links":{"$Url":"/mobmaturities/null"}},"Item":{"Name":"Teleportation Chip 2","Properties":{"Type":"TeleportationChip"},"Links":{"$Url":"/teleportationchips/10007"}},"Frequency":"Extremely rare","LastVU":"17.7","IsEvent":false,"IsDropping":true}],"Links":{"$Url":"/mobs/767"}}