{"Id":631,"Name":"Teladon","Type":"Animal","Properties":{"Description":null,"AttackRange":null,"AggressionRange":null,"IsSweatable":true},"DefensiveProfession":{"Name":"Evader","Links":{"$Url":"/professions/42"}},"ScanningProfession":{"Name":"Animal Investigator","Links":{"$Url":"/professions/1"}},"Planet":{"Name":"Arkadia","Links":{"$Url":"/planets/2"}},"Species":{"Name":"Teladon","Properties":{"CodexBaseCost":237.5,"CodexType":"Mob"},"Links":{"$Url":"/mobspecies/224"}},"Maturities":[{"Id":4008,"Name":"Alpha","Properties":{"Description":null,"Health":4000,"AttacksPerMinute":null,"Level":55,"RegenerationInterval":null,"RegenerationAmount":null,"MissChance":null,"Taming":{"IsTameable":false,"TamingLevel":null},"Attributes":{"Strength":460,"Agility":11,"Intelligence":10,"Psyche":10,"Stamina":400},"Defense":{"Stab":null,"Cut":null,"Impact":null,"Penetration":null,"Shrapnel":null,"Burn":null,"Cold":null,"Acid":null,"Electric":null}},"Attacks":[{"Name":"Primary","Damage":{"Stab":36,"Cut":72,"Impact":72,"Penetration":null,"Shrapnel":null,"Burn":null,"Cold":null,"Acid":null,"Electric":null},"TotalDamage":null,"IsAoE":false}],"Mob":{"Name":"Teladon","Links":{"$Url":"/mobs/631"}},"Links":{"$Url":"/mobmaturities/4008"}},{"Id":4000,"Name":"Champion","Properties":{"Description":null,"Health":8110,"AttacksPerMinute":null,"Level":100,"RegenerationInterval":null,"RegenerationAmount":null,"MissChance":null,"Taming":{"IsTameable":false,"TamingLevel":null},"Attributes":{"Strength":490,"Agility":18,"Intelligence":100,"Psyche":10,"Stamina":811},"Defense":{"Stab":null,"Cut":null,"Impact":null,"Penetration":null,"Shrapnel":null,"Burn":null,"Cold":null,"Acid":null,"Electric":null}},"Attacks":[],"Mob":{"Name":"Teladon","Links":{"$Url":"/mobs/631"}},"Links":{"$Url":"/mobmaturities/4000"}},{"Id":4007,"Name":"Dominant","Properties":{"Description":null,"Health":3700,"AttacksPerMinute":null,"Level":50,"RegenerationInterval":null,"RegenerationAmount":null,"MissChance":null,"Taming":{"IsTameable":false,"TamingLevel":null},"Attributes":{"Strength":450,"Agility":10,"Intelligence":10,"Psyche":10,"Stamina":370},"Defense":{"Stab":null,"Cut":null,"Impact":null,"Penetration":null,"Shrapnel":null,"Burn":null,"Cold":null,"Acid":null,"Electric":null}},"Attacks":[{"Name":"Primary","Damage":{"Stab":33,"Cut":66,"Impact":66,"Penetration":null,"Shrapnel":null,"Burn":null,"Cold":null,"Acid":null,"Electric":null},"TotalDamage":null,"IsAoE":false}],"Mob":{"Name":"Teladon","Links":{"$Url":"/mobs/631"}},"Links":{"$Url":"/mobmaturities/4007"}},{"Id":4006,"Name":"Guardian","Properties":{"Description":null,"Health":3400,"AttacksPerMinute":null,"Level":47,"RegenerationInterval":null,"RegenerationAmount":null,"MissChance":null,"Taming":{"IsTameable":false,"TamingLevel":null},"Attributes":{"Strength":440,"Agility":9,"Intelligence":10,"Psyche":10,"Stamina":340},"Defense":{"Stab":null,"Cut":null,"Impact":null,"Penetration":null,"Shrapnel":null,"Burn":null,"Cold":null,"Acid":null,"Electric":null}},"Attacks":[{"Name":"Primary","Damage":{"Stab":31,"Cut":62,"Impact":62,"Penetration":null,"Shrapnel":null,"Burn":null,"Cold":null,"Acid":null,"Electric":null},"TotalDamage":null,"IsAoE":false}],"Mob":{"Name":"Teladon","Links":{"$Url":"/mobs/631"}},"Links":{"$Url":"/mobmaturities/4006"}},{"Id":4001,"Name":"Matriarch","Properties":{"Description":null,"Health":9730,"AttacksPerMinute":null,"Level":120,"RegenerationInterval":null,"RegenerationAmount":null,"MissChance":null,"Taming":{"IsTameable":false,"TamingLevel":null},"Attributes":{"Strength":490,"Agility":18,"Intelligence":100,"Psyche":10,"Stamina":973},"Defense":{"Stab":null,"Cut":null,"Impact":null,"Penetration":null,"Shrapnel":null,"Burn":null,"Cold":null,"Acid":null,"Electric":null}},"Attacks":[],"Mob":{"Name":"Teladon","Links":{"$Url":"/mobs/631"}},"Links":{"$Url":"/mobmaturities/4001"}},{"Id":4005,"Name":"Mature","Properties":{"Description":null,"Health":2300,"AttacksPerMinute":null,"Level":32,"RegenerationInterval":null,"RegenerationAmount":null,"MissChance":null,"Taming":{"IsTameable":false,"TamingLevel":null},"Attributes":{"Strength":410,"Agility":6,"Intelligence":10,"Psyche":10,"Stamina":230},"Defense":{"Stab":null,"Cut":null,"Impact":null,"Penetration":null,"Shrapnel":null,"Burn":null,"Cold":null,"Acid":null,"Electric":null}},"Attacks":[{"Name":"Primary","Damage":{"Stab":20,"Cut":40,"Impact":40,"Penetration":null,"Shrapnel":null,"Burn":null,"Cold":null,"Acid":null,"Electric":null},"TotalDamage":null,"IsAoE":false}],"Mob":{"Name":"Teladon","Links":{"$Url":"/mobs/631"}},"Links":{"$Url":"/mobmaturities/4005"}},{"Id":4004,"Name":"Old","Properties":{"Description":null,"Health":2650,"AttacksPerMinute":null,"Level":36,"RegenerationInterval":null,"RegenerationAmount":null,"MissChance":null,"Taming":{"IsTameable":false,"TamingLevel":null},"Attributes":{"Strength":420,"Agility":7,"Intelligence":10,"Psyche":10,"Stamina":265},"Defense":{"Stab":null,"Cut":null,"Impact":null,"Penetration":null,"Shrapnel":null,"Burn":null,"Cold":null,"Acid":null,"Electric":null}},"Attacks":[{"Name":"Primary","Damage":{"Stab":23,"Cut":46,"Impact":46,"Penetration":null,"Shrapnel":null,"Burn":null,"Cold":null,"Acid":null,"Electric":null},"TotalDamage":null,"IsAoE":false}],"Mob":{"Name":"Teladon","Links":{"$Url":"/mobs/631"}},"Links":{"$Url":"/mobmaturities/4004"}},{"Id":4009,"Name":"Old Alpha","Properties":{"Description":null,"Health":4400,"AttacksPerMinute":null,"Level":61,"RegenerationInterval":null,"RegenerationAmount":null,"MissChance":null,"Taming":{"IsTameable":false,"TamingLevel":null},"Attributes":{"Strength":470,"Agility":12,"Intelligence":10,"Psyche":10,"Stamina":440},"Defense":{"Stab":null,"Cut":null,"Impact":null,"Penetration":null,"Shrapnel":null,"Burn":null,"Cold":null,"Acid":null,"Electric":null}},"Attacks":[{"Name":"Primary","Damage":{"Stab":40,"Cut":80,"Impact":80,"Penetration":null,"Shrapnel":null,"Burn":null,"Cold":null,"Acid":null,"Electric":null},"TotalDamage":null,"IsAoE":false}],"Mob":{"Name":"Teladon","Links":{"$Url":"/mobs/631"}},"Links":{"$Url":"/mobmaturities/4009"}},{"Id":4002,"Name":"Patriarch","Properties":{"Description":null,"Health":12160,"AttacksPerMinute":null,"Level":146,"RegenerationInterval":null,"RegenerationAmount":null,"MissChance":null,"Taming":{"IsTameable":false,"TamingLevel":null},"Attributes":{"Strength":490,"Agility":20,"Intelligence":110,"Psyche":10,"Stamina":1216},"Defense":{"Stab":null,"Cut":null,"Impact":null,"Penetration":null,"Shrapnel":null,"Burn":null,"Cold":null,"Acid":null,"Electric":null}},"Attacks":[],"Mob":{"Name":"Teladon","Links":{"$Url":"/mobs/631"}},"Links":{"$Url":"/mobmaturities/4002"}},{"Id":3999,"Name":"Prime","Properties":{"Description":null,"Health":6760,"AttacksPerMinute":null,"Level":89,"RegenerationInterval":null,"RegenerationAmount":null,"MissChance":null,"Taming":{"IsTameable":false,"TamingLevel":null},"Attributes":{"Strength":490,"Agility":14,"Intelligence":100,"Psyche":10,"Stamina":676},"Defense":{"Stab":null,"Cut":null,"Impact":null,"Penetration":null,"Shrapnel":null,"Burn":null,"Cold":null,"Acid":null,"Electric":null}},"Attacks":[],"Mob":{"Name":"Teladon","Links":{"$Url":"/mobs/631"}},"Links":{"$Url":"/mobmaturities/3999"}},{"Id":4003,"Name":"Provider","Properties":{"Description":null,"Health":3050,"AttacksPerMinute":null,"Level":42,"RegenerationInterval":null,"RegenerationAmount":null,"MissChance":null,"Taming":{"IsTameable":false,"TamingLevel":null},"Attributes":{"Strength":430,"Agility":8,"Intelligence":10,"Psyche":10,"Stamina":305},"Defense":{"Stab":null,"Cut":null,"Impact":null,"Penetration":null,"Shrapnel":null,"Burn":null,"Cold":null,"Acid":null,"Electric":null}},"Attacks":[{"Name":"Primary","Damage":{"Stab":27,"Cut":54,"Impact":54,"Penetration":null,"Shrapnel":null,"Burn":null,"Cold":null,"Acid":null,"Electric":null},"TotalDamage":null,"IsAoE":false}],"Mob":{"Name":"Teladon","Links":{"$Url":"/mobs/631"}},"Links":{"$Url":"/mobmaturities/4003"}},{"Id":4010,"Name":"Prowler","Properties":{"Description":null,"Health":4900,"AttacksPerMinute":null,"Level":66,"RegenerationInterval":null,"RegenerationAmount":null,"MissChance":null,"Taming":{"IsTameable":false,"TamingLevel":null},"Attributes":{"Strength":480,"Agility":13,"Intelligence":10,"Psyche":10,"Stamina":490},"Defense":{"Stab":null,"Cut":null,"Impact":null,"Penetration":null,"Shrapnel":null,"Burn":null,"Cold":null,"Acid":null,"Electric":null}},"Attacks":[{"Name":"Primary","Damage":{"Stab":44,"Cut":88,"Impact":88,"Penetration":null,"Shrapnel":null,"Burn":null,"Cold":null,"Acid":null,"Electric":null},"TotalDamage":null,"IsAoE":false}],"Mob":{"Name":"Teladon","Links":{"$Url":"/mobs/631"}},"Links":{"$Url":"/mobmaturities/4010"}},{"Id":4011,"Name":"Stalker","Properties":{"Description":null,"Health":5200,"AttacksPerMinute":null,"Level":70,"RegenerationInterval":null,"RegenerationAmount":null,"MissChance":null,"Taming":{"IsTameable":false,"TamingLevel":null},"Attributes":{"Strength":490,"Agility":14,"Intelligence":10,"Psyche":10,"Stamina":520},"Defense":{"Stab":null,"Cut":null,"Impact":null,"Penetration":null,"Shrapnel":null,"Burn":null,"Cold":null,"Acid":null,"Electric":null}},"Attacks":[{"Name":"Primary","Damage":{"Stab":46,"Cut":92,"Impact":92,"Penetration":null,"Shrapnel":null,"Burn":null,"Cold":null,"Acid":null,"Electric":null},"TotalDamage":null,"IsAoE":false}],"Mob":{"Name":"Teladon","Links":{"$Url":"/mobs/631"}},"Links":{"$Url":"/mobmaturities/4011"}},{"Id":3998,"Name":"Young","Properties":{"Description":null,"Health":1900,"AttacksPerMinute":null,"Level":27,"RegenerationInterval":null,"RegenerationAmount":null,"MissChance":null,"Taming":{"IsTameable":false,"TamingLevel":null},"Attributes":{"Strength":400,"Agility":5,"Intelligence":10,"Psyche":10,"Stamina":190},"Defense":{"Stab":null,"Cut":null,"Impact":null,"Penetration":null,"Shrapnel":null,"Burn":null,"Cold":null,"Acid":null,"Electric":null}},"Attacks":[{"Name":"Primary","Damage":{"Stab":16,"Cut":32,"Impact":32,"Penetration":null,"Shrapnel":null,"Burn":null,"Cold":null,"Acid":null,"Electric":null},"TotalDamage":null,"IsAoE":false}],"Mob":{"Name":"Teladon","Links":{"$Url":"/mobs/631"}},"Links":{"$Url":"/mobmaturities/3998"}}],"Spawns":[],"Loots":[{"Mob":{"Name":"Teladon","Planet":{"Name":"Arkadia","Links":{"$Url":"/planets/2"}},"Links":{"$Url":"/mobs/631"}},"Maturity":{"Name":"Young","Links":{"$Url":"/mobmaturities/71"}},"Item":{"Name":"Adaptive Fire Rate Component","Properties":{"Type":"Material"},"Links":{"$Url":"/materials/24"}},"Frequency":"Uncommon","LastVU":"17.21.2","IsEvent":false,"IsDropping":true},{"Mob":{"Name":"Teladon","Planet":{"Name":"Arkadia","Links":{"$Url":"/planets/2"}},"Links":{"$Url":"/mobs/631"}},"Maturity":{"Name":"Young","Links":{"$Url":"/mobmaturities/71"}},"Item":{"Name":"Advanced Cloth Extractor","Properties":{"Type":"Material"},"Links":{"$Url":"/materials/31"}},"Frequency":"Uncommon","LastVU":"17.15.1","IsEvent":false,"IsDropping":true},{"Mob":{"Name":"Teladon","Planet":{"Name":"Arkadia","Links":{"$Url":"/planets/2"}},"Links":{"$Url":"/mobs/631"}},"Maturity":{"Name":"Young","Links":{"$Url":"/mobmaturities/71"}},"Item":{"Name":"Animal Adrenal Oil","Properties":{"Type":"Material"},"Links":{"$Url":"/materials/115"}},"Frequency":"Common","LastVU":"17.22.3","IsEvent":false,"IsDropping":true},{"Mob":{"Name":"Teladon","Planet":{"Name":"Arkadia","Links":{"$Url":"/planets/2"}},"Links":{"$Url":"/mobs/631"}},"Maturity":{"Name":"Prime","Links":{"$Url":"/mobmaturities/47"}},"Item":{"Name":"Animal Heart Oil","Properties":{"Type":"Material"},"Links":{"$Url":"/materials/120"}},"Frequency":"Uncommon","LastVU":null,"IsEvent":false,"IsDropping":false},{"Mob":{"Name":"Teladon","Planet":{"Name":"Arkadia","Links":{"$Url":"/planets/2"}},"Links":{"$Url":"/mobs/631"}},"Maturity":{"Name":"Young","Links":{"$Url":"/mobmaturities/71"}},"Item":{"Name":"Animal Hide","Properties":{"Type":"Material"},"Links":{"$Url":"/materials/121"}},"Frequency":"Often","LastVU":"17.21.2","IsEvent":false,"IsDropping":true},{"Mob":{"Name":"Teladon","Planet":{"Name":"Arkadia","Links":{"$Url":"/planets/2"}},"Links":{"$Url":"/mobs/631"}},"Maturity":{"Name":null,"Links":{"$Url":"/mobmaturities/null"}},"Item":{"Name":"Animal Kidney Oil","Properties":{"Type":"Material"},"Links":{"$Url":"/materials/122"}},"Frequency":"Uncommon","LastVU":"17.15.1","IsEvent":false,"IsDropping":true},{"Mob":{"Name":"Teladon","Planet":{"Name":"Arkadia","Links":{"$Url":"/planets/2"}},"Links":{"$Url":"/mobs/631"}},"Maturity":{"Name":null,"Links":{"$Url":"/mobmaturities/null"}},"Item":{"Name":"Animal Liver Oil","Properties":{"Type":"Material"},"Links":{"$Url":"/materials/123"}},"Frequency":"Common","LastVU":"17.15.1","IsEvent":false,"IsDropping":true},{"Mob":{"Name":"Teladon","Planet":{"Name":"Arkadia","Links":{"$Url":"/planets/2"}},"Links":{"$Url":"/mobs/631"}},"Maturity":{"Name":"Young","Links":{"$Url":"/mobmaturities/71"}},"Item":{"Name":"Animal Oil Residue","Properties":{"Type":"Material"},"Links":{"$Url":"/materials/125"}},"Frequency":"Very often","LastVU":"17.22.3","IsEvent":false,"IsDropping":true},{"Mob":{"Name":"Teladon","Planet":{"Name":"Arkadia","Links":{"$Url":"/planets/2"}},"Links":{"$Url":"/mobs/631"}},"Maturity":{"Name":"Young","Links":{"$Url":"/mobmaturities/71"}},"Item":{"Name":"Animal Pancreas Oil","Properties":{"Type":"Material"},"Links":{"$Url":"/materials/126"}},"Frequency":"Common","LastVU":"17.20.1a","IsEvent":false,"IsDropping":true},{"Mob":{"Name":"Teladon","Planet":{"Name":"Arkadia","Links":{"$Url":"/planets/2"}},"Links":{"$Url":"/mobs/631"}},"Maturity":{"Name":"Stalker","Links":{"$Url":"/mobmaturities/75"}},"Item":{"Name":"Animal Spleen Oil","Properties":{"Type":"Material"},"Links":{"$Url":"/materials/127"}},"Frequency":"Uncommon","LastVU":"17.15.1","IsEvent":false,"IsDropping":true},{"Mob":{"Name":"Teladon","Planet":{"Name":"Arkadia","Links":{"$Url":"/planets/2"}},"Links":{"$Url":"/mobs/631"}},"Maturity":{"Name":"Young","Links":{"$Url":"/mobmaturities/71"}},"Item":{"Name":"Basic Leather Extractor","Properties":{"Type":"Material"},"Links":{"$Url":"/materials/247"}},"Frequency":"Uncommon","LastVU":"17.21.2","IsEvent":false,"IsDropping":true},{"Mob":{"Name":"Teladon","Planet":{"Name":"Arkadia","Links":{"$Url":"/planets/2"}},"Links":{"$Url":"/mobs/631"}},"Maturity":{"Name":"Young","Links":{"$Url":"/mobmaturities/71"}},"Item":{"Name":"Basic Wood Extractor","Properties":{"Type":"Material"},"Links":{"$Url":"/materials/279"}},"Frequency":"Uncommon","LastVU":"17.21.2","IsEvent":false,"IsDropping":true},{"Mob":{"Name":"Teladon","Planet":{"Name":"Arkadia","Links":{"$Url":"/planets/2"}},"Links":{"$Url":"/mobs/631"}},"Maturity":{"Name":"Young","Links":{"$Url":"/mobmaturities/71"}},"Item":{"Name":"Corria Timber","Properties":{"Type":"Material"},"Links":{"$Url":"/materials/520"}},"Frequency":"Common","LastVU":"17.21.2","IsEvent":false,"IsDropping":true},{"Mob":{"Name":"Teladon","Planet":{"Name":"Arkadia","Links":{"$Url":"/planets/2"}},"Links":{"$Url":"/mobs/631"}},"Maturity":{"Name":"Young","Links":{"$Url":"/mobmaturities/71"}},"Item":{"Name":"Diluted Mineral Extractor","Properties":{"Type":"Material"},"Links":{"$Url":"/materials/612"}},"Frequency":"Common","LastVU":"17.15.1","IsEvent":false,"IsDropping":true},{"Mob":{"Name":"Teladon","Planet":{"Name":"Arkadia","Links":{"$Url":"/planets/2"}},"Links":{"$Url":"/mobs/631"}},"Maturity":{"Name":"Young","Links":{"$Url":"/mobmaturities/71"}},"Item":{"Name":"Enhanced Metal Extractor","Properties":{"Type":"Material"},"Links":{"$Url":"/materials/694"}},"Frequency":"Uncommon","LastVU":"17.0.5","IsEvent":false,"IsDropping":true},{"Mob":{"Name":"Teladon","Planet":{"Name":"Arkadia","Links":{"$Url":"/planets/2"}},"Links":{"$Url":"/mobs/631"}},"Maturity":{"Name":"Young","Links":{"$Url":"/mobmaturities/71"}},"Item":{"Name":"Fine Hide","Properties":{"Type":"Material"},"Links":{"$Url":"/materials/789"}},"Frequency":"Uncommon","LastVU":"17.20.1a","IsEvent":false,"IsDropping":true},{"Mob":{"Name":"Teladon","Planet":{"Name":"Arkadia","Links":{"$Url":"/planets/2"}},"Links":{"$Url":"/mobs/631"}},"Maturity":{"Name":"Young","Links":{"$Url":"/mobmaturities/71"}},"Item":{"Name":"Fine Wool","Properties":{"Type":"Material"},"Links":{"$Url":"/materials/795"}},"Frequency":"Common","LastVU":"17.21.2","IsEvent":false,"IsDropping":true},{"Mob":{"Name":"Teladon","Planet":{"Name":"Arkadia","Links":{"$Url":"/planets/2"}},"Links":{"$Url":"/mobs/631"}},"Maturity":{"Name":"Young","Links":{"$Url":"/mobmaturities/71"}},"Item":{"Name":"High Definition GUI Component","Properties":{"Type":"Material"},"Links":{"$Url":"/materials/1058"}},"Frequency":"Uncommon","LastVU":"17.20.1a","IsEvent":false,"IsDropping":true},{"Mob":{"Name":"Teladon","Planet":{"Name":"Arkadia","Links":{"$Url":"/planets/2"}},"Links":{"$Url":"/mobs/631"}},"Maturity":{"Name":"Guardian","Links":{"$Url":"/mobmaturities/60"}},"Item":{"Name":"Infrasound Emitter Component","Properties":{"Type":"Material"},"Links":{"$Url":"/materials/1129"}},"Frequency":"Uncommon","LastVU":"17.15.1","IsEvent":false,"IsDropping":true},{"Mob":{"Name":"Teladon","Planet":{"Name":"Arkadia","Links":{"$Url":"/planets/2"}},"Links":{"$Url":"/mobs/631"}},"Maturity":{"Name":null,"Links":{"$Url":"/mobmaturities/null"}},"Item":{"Name":"Make Up Remover Smooth","Properties":{"Type":"Material"},"Links":{"$Url":"/materials/1381"}},"Frequency":"Uncommon","LastVU":"17.20.1a","IsEvent":false,"IsDropping":true},{"Mob":{"Name":"Teladon","Planet":{"Name":"Arkadia","Links":{"$Url":"/planets/2"}},"Links":{"$Url":"/mobs/631"}},"Maturity":{"Name":"Young","Links":{"$Url":"/mobmaturities/71"}},"Item":{"Name":"Output Amplifier Component","Properties":{"Type":"Material"},"Links":{"$Url":"/materials/1625"}},"Frequency":"Uncommon","LastVU":"17.15.1","IsEvent":false,"IsDropping":true},{"Mob":{"Name":"Teladon","Planet":{"Name":"Arkadia","Links":{"$Url":"/planets/2"}},"Links":{"$Url":"/mobs/631"}},"Maturity":{"Name":null,"Links":{"$Url":"/mobmaturities/null"}},"Item":{"Name":"Paint Can (Burgundy)","Properties":{"Type":"Material"},"Links":{"$Url":"/materials/1648"}},"Frequency":"Uncommon","LastVU":"17.20.1a","IsEvent":false,"IsDropping":true},{"Mob":{"Name":"Teladon","Planet":{"Name":"Arkadia","Links":{"$Url":"/planets/2"}},"Links":{"$Url":"/mobs/631"}},"Maturity":{"Name":"Young","Links":{"$Url":"/mobmaturities/71"}},"Item":{"Name":"Paint Can (Burnt Umber)","Properties":{"Type":"Material"},"Links":{"$Url":"/materials/1649"}},"Frequency":"Uncommon","LastVU":"17.21.2","IsEvent":false,"IsDropping":true},{"Mob":{"Name":"Teladon","Planet":{"Name":"Arkadia","Links":{"$Url":"/planets/2"}},"Links":{"$Url":"/mobs/631"}},"Maturity":{"Name":"Young","Links":{"$Url":"/mobmaturities/71"}},"Item":{"Name":"Paint Can (Cornsilk)","Properties":{"Type":"Material"},"Links":{"$Url":"/materials/1650"}},"Frequency":"Uncommon","LastVU":"17.15.1","IsEvent":false,"IsDropping":true},{"Mob":{"Name":"Teladon","Planet":{"Name":"Arkadia","Links":{"$Url":"/planets/2"}},"Links":{"$Url":"/mobs/631"}},"Maturity":{"Name":null,"Links":{"$Url":"/mobmaturities/null"}},"Item":{"Name":"Paint Can (Dark Lavender)","Properties":{"Type":"Material"},"Links":{"$Url":"/materials/1655"}},"Frequency":"Uncommon","LastVU":"17.15.1","IsEvent":false,"IsDropping":true},{"Mob":{"Name":"Teladon","Planet":{"Name":"Arkadia","Links":{"$Url":"/planets/2"}},"Links":{"$Url":"/mobs/631"}},"Maturity":{"Name":"Young","Links":{"$Url":"/mobmaturities/71"}},"Item":{"Name":"Paint Can (Dark Steel Blue)","Properties":{"Type":"Material"},"Links":{"$Url":"/materials/1659"}},"Frequency":"Uncommon","LastVU":"17.15.1","IsEvent":false,"IsDropping":true},{"Mob":{"Name":"Teladon","Planet":{"Name":"Arkadia","Links":{"$Url":"/planets/2"}},"Links":{"$Url":"/mobs/631"}},"Maturity":{"Name":"Young","Links":{"$Url":"/mobmaturities/71"}},"Item":{"Name":"Paint Can (Mauve)","Properties":{"Type":"Material"},"Links":{"$Url":"/materials/1664"}},"Frequency":"Uncommon","LastVU":"17.21.2","IsEvent":false,"IsDropping":true},{"Mob":{"Name":"Teladon","Planet":{"Name":"Arkadia","Links":{"$Url":"/planets/2"}},"Links":{"$Url":"/mobs/631"}},"Maturity":{"Name":"Young","Links":{"$Url":"/mobmaturities/71"}},"Item":{"Name":"Paint Can (Orange)","Properties":{"Type":"Material"},"Links":{"$Url":"/materials/1667"}},"Frequency":"Common","LastVU":"17.15.1","IsEvent":false,"IsDropping":true},{"Mob":{"Name":"Teladon","Planet":{"Name":"Arkadia","Links":{"$Url":"/planets/2"}},"Links":{"$Url":"/mobs/631"}},"Maturity":{"Name":"Guardian","Links":{"$Url":"/mobmaturities/60"}},"Item":{"Name":"Paint Can (Silver)","Properties":{"Type":"Material"},"Links":{"$Url":"/materials/1671"}},"Frequency":"Uncommon","LastVU":"17.15.1","IsEvent":false,"IsDropping":true},{"Mob":{"Name":"Teladon","Planet":{"Name":"Arkadia","Links":{"$Url":"/planets/2"}},"Links":{"$Url":"/mobs/631"}},"Maturity":{"Name":"Young","Links":{"$Url":"/mobmaturities/71"}},"Item":{"Name":"Paint Can (Steel Blue)","Properties":{"Type":"Material"},"Links":{"$Url":"/materials/1672"}},"Frequency":"Uncommon","LastVU":"17.20.1a","IsEvent":false,"IsDropping":true},{"Mob":{"Name":"Teladon","Planet":{"Name":"Arkadia","Links":{"$Url":"/planets/2"}},"Links":{"$Url":"/mobs/631"}},"Maturity":{"Name":"Young","Links":{"$Url":"/mobmaturities/71"}},"Item":{"Name":"Second-Rate Cloth Extractor","Properties":{"Type":"Material"},"Links":{"$Url":"/materials/2108"}},"Frequency":"Common","LastVU":"17.21.2","IsEvent":false,"IsDropping":true},{"Mob":{"Name":"Teladon","Planet":{"Name":"Arkadia","Links":{"$Url":"/planets/2"}},"Links":{"$Url":"/mobs/631"}},"Maturity":{"Name":null,"Links":{"$Url":"/mobmaturities/null"}},"Item":{"Name":"Socket 3 Component","Properties":{"Type":"Material"},"Links":{"$Url":"/materials/2183"}},"Frequency":"Common","LastVU":"17.20.1a","IsEvent":false,"IsDropping":true},{"Mob":{"Name":"Teladon","Planet":{"Name":"Arkadia","Links":{"$Url":"/planets/2"}},"Links":{"$Url":"/mobs/631"}},"Maturity":{"Name":"Young","Links":{"$Url":"/mobmaturities/71"}},"Item":{"Name":"Socket 4 Component","Properties":{"Type":"Material"},"Links":{"$Url":"/materials/2184"}},"Frequency":"Common","LastVU":"17.15.1","IsEvent":false,"IsDropping":true},{"Mob":{"Name":"Teladon","Planet":{"Name":"Arkadia","Links":{"$Url":"/planets/2"}},"Links":{"$Url":"/mobs/631"}},"Maturity":{"Name":"Young","Links":{"$Url":"/mobmaturities/71"}},"Item":{"Name":"Socket 5 Component","Properties":{"Type":"Material"},"Links":{"$Url":"/materials/2185"}},"Frequency":"Uncommon","LastVU":"17.15.1","IsEvent":false,"IsDropping":true},{"Mob":{"Name":"Teladon","Planet":{"Name":"Arkadia","Links":{"$Url":"/planets/2"}},"Links":{"$Url":"/mobs/631"}},"Maturity":{"Name":"Guardian","Links":{"$Url":"/mobmaturities/60"}},"Item":{"Name":"Socket 6 Component","Properties":{"Type":"Material"},"Links":{"$Url":"/materials/2186"}},"Frequency":"Uncommon","LastVU":"17.15.1","IsEvent":false,"IsDropping":true},{"Mob":{"Name":"Teladon","Planet":{"Name":"Arkadia","Links":{"$Url":"/planets/2"}},"Links":{"$Url":"/mobs/631"}},"Maturity":{"Name":"Prime","Links":{"$Url":"/mobmaturities/47"}},"Item":{"Name":"Socket 8 Component","Properties":{"Type":"Material"},"Links":{"$Url":"/materials/2188"}},"Frequency":"Common","LastVU":null,"IsEvent":false,"IsDropping":false},{"Mob":{"Name":"Teladon","Planet":{"Name":"Arkadia","Links":{"$Url":"/planets/2"}},"Links":{"$Url":"/mobs/631"}},"Maturity":{"Name":"Prime","Links":{"$Url":"/mobmaturities/47"}},"Item":{"Name":"Socket 9 Component","Properties":{"Type":"Material"},"Links":{"$Url":"/materials/2189"}},"Frequency":"Common","LastVU":null,"IsEvent":false,"IsDropping":false},{"Mob":{"Name":"Teladon","Planet":{"Name":"Arkadia","Links":{"$Url":"/planets/2"}},"Links":{"$Url":"/mobs/631"}},"Maturity":{"Name":"Young","Links":{"$Url":"/mobmaturities/71"}},"Item":{"Name":"Soft Hide","Properties":{"Type":"Material"},"Links":{"$Url":"/materials/2193"}},"Frequency":"Uncommon","LastVU":"17.15.1","IsEvent":false,"IsDropping":true},{"Mob":{"Name":"Teladon","Planet":{"Name":"Arkadia","Links":{"$Url":"/planets/2"}},"Links":{"$Url":"/mobs/631"}},"Maturity":{"Name":"Young","Links":{"$Url":"/mobmaturities/71"}},"Item":{"Name":"Super Charger Component","Properties":{"Type":"Material"},"Links":{"$Url":"/materials/2270"}},"Frequency":"Uncommon","LastVU":"17.15.1","IsEvent":false,"IsDropping":true},{"Mob":{"Name":"Teladon","Planet":{"Name":"Arkadia","Links":{"$Url":"/planets/2"}},"Links":{"$Url":"/mobs/631"}},"Maturity":{"Name":"Young","Links":{"$Url":"/mobmaturities/71"}},"Item":{"Name":"Teladon Foot","Properties":{"Type":"Material"},"Links":{"$Url":"/materials/2317"}},"Frequency":"Uncommon","LastVU":"17.21.2","IsEvent":false,"IsDropping":true},{"Mob":{"Name":"Teladon","Planet":{"Name":"Arkadia","Links":{"$Url":"/planets/2"}},"Links":{"$Url":"/mobs/631"}},"Maturity":{"Name":"Young","Links":{"$Url":"/mobmaturities/71"}},"Item":{"Name":"Teladon Hide","Properties":{"Type":"Material"},"Links":{"$Url":"/materials/2318"}},"Frequency":"Common","LastVU":"17.21.2","IsEvent":false,"IsDropping":true},{"Mob":{"Name":"Teladon","Planet":{"Name":"Arkadia","Links":{"$Url":"/planets/2"}},"Links":{"$Url":"/mobs/631"}},"Maturity":{"Name":"Young","Links":{"$Url":"/mobmaturities/71"}},"Item":{"Name":"Teladon Tail Spike","Properties":{"Type":"Material"},"Links":{"$Url":"/materials/2321"}},"Frequency":"Common","LastVU":"17.21.2","IsEvent":false,"IsDropping":true},{"Mob":{"Name":"Teladon","Planet":{"Name":"Arkadia","Links":{"$Url":"/planets/2"}},"Links":{"$Url":"/mobs/631"}},"Maturity":{"Name":"Young","Links":{"$Url":"/mobmaturities/71"}},"Item":{"Name":"Thin Wool","Properties":{"Type":"Material"},"Links":{"$Url":"/materials/2347"}},"Frequency":"Common","LastVU":"17.15.1","IsEvent":false,"IsDropping":true},{"Mob":{"Name":"Teladon","Planet":{"Name":"Arkadia","Links":{"$Url":"/planets/2"}},"Links":{"$Url":"/mobs/631"}},"Maturity":{"Name":"Young","Links":{"$Url":"/mobmaturities/71"}},"Item":{"Name":"Tier 3 Component","Properties":{"Type":"Material"},"Links":{"$Url":"/materials/2356"}},"Frequency":"Uncommon","LastVU":"17.20.1a","IsEvent":false,"IsDropping":true},{"Mob":{"Name":"Teladon","Planet":{"Name":"Arkadia","Links":{"$Url":"/planets/2"}},"Links":{"$Url":"/mobs/631"}},"Maturity":{"Name":null,"Links":{"$Url":"/mobmaturities/null"}},"Item":{"Name":"Tier 4 Component","Properties":{"Type":"Material"},"Links":{"$Url":"/materials/2357"}},"Frequency":"Uncommon","LastVU":"17.15.1","IsEvent":false,"IsDropping":true},{"Mob":{"Name":"Teladon","Planet":{"Name":"Arkadia","Links":{"$Url":"/planets/2"}},"Links":{"$Url":"/mobs/631"}},"Maturity":{"Name":"Alpha","Links":{"$Url":"/mobmaturities/76"}},"Item":{"Name":"Tier 5 Component","Properties":{"Type":"Material"},"Links":{"$Url":"/materials/2358"}},"Frequency":"Uncommon","LastVU":"17.15.1","IsEvent":false,"IsDropping":true},{"Mob":{"Name":"Teladon","Planet":{"Name":"Arkadia","Links":{"$Url":"/planets/2"}},"Links":{"$Url":"/mobs/631"}},"Maturity":{"Name":"Prime","Links":{"$Url":"/mobmaturities/47"}},"Item":{"Name":"Tier 8 Component","Properties":{"Type":"Material"},"Links":{"$Url":"/materials/2361"}},"Frequency":"Uncommon","LastVU":null,"IsEvent":false,"IsDropping":false},{"Mob":{"Name":"Teladon","Planet":{"Name":"Arkadia","Links":{"$Url":"/planets/2"}},"Links":{"$Url":"/mobs/631"}},"Maturity":{"Name":"Young","Links":{"$Url":"/mobmaturities/71"}},"Item":{"Name":"Wool","Properties":{"Type":"Material"},"Links":{"$Url":"/materials/2533"}},"Frequency":"Common","LastVU":"17.21.2","IsEvent":false,"IsDropping":true},{"Mob":{"Name":"Teladon","Planet":{"Name":"Arkadia","Links":{"$Url":"/planets/2"}},"Links":{"$Url":"/mobs/631"}},"Maturity":{"Name":"Stalker","Links":{"$Url":"/mobmaturities/75"}},"Item":{"Name":"8 Coins Silver","Properties":{"Type":"Material"},"Links":{"$Url":"/materials/2923"}},"Frequency":"Common","LastVU":"17.22.2","IsEvent":false,"IsDropping":true},{"Mob":{"Name":"Teladon","Planet":{"Name":"Arkadia","Links":{"$Url":"/planets/2"}},"Links":{"$Url":"/mobs/631"}},"Maturity":{"Name":"Stalker","Links":{"$Url":"/mobmaturities/75"}},"Item":{"Name":"8 Coins Gold","Properties":{"Type":"Material"},"Links":{"$Url":"/materials/2924"}},"Frequency":"Common","LastVU":"17.22.2","IsEvent":false,"IsDropping":true},{"Mob":{"Name":"Teladon","Planet":{"Name":"Arkadia","Links":{"$Url":"/planets/2"}},"Links":{"$Url":"/mobs/631"}},"Maturity":{"Name":"Young","Links":{"$Url":"/mobmaturities/71"}},"Item":{"Name":"Piron PBR-52 (L)","Properties":{"Type":"Weapon"},"Links":{"$Url":"/weapons/2334"}},"Frequency":"Uncommon","LastVU":"17.21.2","IsEvent":false,"IsDropping":true},{"Mob":{"Name":"Teladon","Planet":{"Name":"Arkadia","Links":{"$Url":"/planets/2"}},"Links":{"$Url":"/mobs/631"}},"Maturity":{"Name":"Guardian","Links":{"$Url":"/mobmaturities/60"}},"Item":{"Name":"Empty Skill Implant (L)","Properties":{"Type":"MiscTool"},"Links":{"$Url":"/misctools/157"}},"Frequency":"Rare","LastVU":"17.6.1","IsEvent":false,"IsDropping":true},{"Mob":{"Name":"Teladon","Planet":{"Name":"Arkadia","Links":{"$Url":"/planets/2"}},"Links":{"$Url":"/mobs/631"}},"Maturity":{"Name":"Young","Links":{"$Url":"/mobmaturities/71"}},"Item":{"Name":"Longreach III (L)","Properties":{"Type":"WeaponVisionAttachment"},"Links":{"$Url":"/weaponvisionattachments/28"}},"Frequency":"Uncommon","LastVU":"17.21.2","IsEvent":false,"IsDropping":true},{"Mob":{"Name":"Teladon","Planet":{"Name":"Arkadia","Links":{"$Url":"/planets/2"}},"Links":{"$Url":"/mobs/631"}},"Maturity":{"Name":"Young","Links":{"$Url":"/mobmaturities/71"}},"Item":{"Name":"Bullseye V (L)","Properties":{"Type":"WeaponVisionAttachment"},"Links":{"$Url":"/weaponvisionattachments/60"}},"Frequency":"Uncommon","LastVU":"17.21.2","IsEvent":false,"IsDropping":true}],"Links":{"$Url":"/mobs/631"}}