{"Id":615,"Name":"Sumima (Calypso)","Type":"Animal","Properties":{"Description":null,"AttackRange":null,"AggressionRange":null,"IsSweatable":true},"DefensiveProfession":{"Name":"Evader","Links":{"$Url":"/professions/42"}},"ScanningProfession":{"Name":"Animal Investigator","Links":{"$Url":"/professions/1"}},"Planet":{"Name":"Calypso","Links":{"$Url":"/planets/1"}},"Species":{"Name":"Sumima","Properties":{"CodexBaseCost":181.25,"CodexType":"Mob"},"Links":{"$Url":"/mobspecies/125"}},"Maturities":[{"Id":3900,"Name":"Mature","Properties":{"Description":null,"Health":1520,"AttacksPerMinute":null,"Level":25,"RegenerationInterval":null,"RegenerationAmount":null,"MissChance":null,"Taming":{"IsTameable":false,"TamingLevel":null},"Attributes":{"Strength":44,"Agility":42,"Intelligence":20,"Psyche":20,"Stamina":152},"Defense":{"Stab":null,"Cut":null,"Impact":null,"Penetration":null,"Shrapnel":null,"Burn":null,"Cold":null,"Acid":null,"Electric":null}},"Attacks":[],"Mob":{"Name":"Sumima (Calypso)","Links":{"$Url":"/mobs/615"}},"Links":{"$Url":"/mobmaturities/3900"}},{"Id":3901,"Name":"Provider","Properties":{"Description":null,"Health":1650,"AttacksPerMinute":null,"Level":29,"RegenerationInterval":null,"RegenerationAmount":null,"MissChance":null,"Taming":{"IsTameable":false,"TamingLevel":null},"Attributes":{"Strength":50,"Agility":47,"Intelligence":22,"Psyche":22,"Stamina":165},"Defense":{"Stab":null,"Cut":null,"Impact":null,"Penetration":null,"Shrapnel":null,"Burn":null,"Cold":null,"Acid":null,"Electric":null}},"Attacks":[],"Mob":{"Name":"Sumima (Calypso)","Links":{"$Url":"/mobs/615"}},"Links":{"$Url":"/mobmaturities/3901"}},{"Id":3902,"Name":"Dominant","Properties":{"Description":null,"Health":1780,"AttacksPerMinute":null,"Level":33,"RegenerationInterval":null,"RegenerationAmount":null,"MissChance":null,"Taming":{"IsTameable":false,"TamingLevel":null},"Attributes":{"Strength":55,"Agility":53,"Intelligence":23,"Psyche":23,"Stamina":178},"Defense":{"Stab":null,"Cut":null,"Impact":null,"Penetration":null,"Shrapnel":null,"Burn":null,"Cold":null,"Acid":null,"Electric":null}},"Attacks":[],"Mob":{"Name":"Sumima (Calypso)","Links":{"$Url":"/mobs/615"}},"Links":{"$Url":"/mobmaturities/3902"}},{"Id":3903,"Name":"Alpha","Properties":{"Description":null,"Health":1840,"AttacksPerMinute":null,"Level":35,"RegenerationInterval":null,"RegenerationAmount":null,"MissChance":null,"Taming":{"IsTameable":false,"TamingLevel":null},"Attributes":{"Strength":58,"Agility":56,"Intelligence":23,"Psyche":23,"Stamina":184},"Defense":{"Stab":null,"Cut":null,"Impact":null,"Penetration":null,"Shrapnel":null,"Burn":null,"Cold":null,"Acid":null,"Electric":null}},"Attacks":[],"Mob":{"Name":"Sumima (Calypso)","Links":{"$Url":"/mobs/615"}},"Links":{"$Url":"/mobmaturities/3903"}},{"Id":3904,"Name":"Guardian","Properties":{"Description":null,"Health":1710,"AttacksPerMinute":null,"Level":31,"RegenerationInterval":null,"RegenerationAmount":null,"MissChance":null,"Taming":{"IsTameable":false,"TamingLevel":null},"Attributes":{"Strength":53,"Agility":51,"Intelligence":22,"Psyche":22,"Stamina":171},"Defense":{"Stab":null,"Cut":null,"Impact":null,"Penetration":null,"Shrapnel":null,"Burn":null,"Cold":null,"Acid":null,"Electric":null}},"Attacks":[],"Mob":{"Name":"Sumima (Calypso)","Links":{"$Url":"/mobs/615"}},"Links":{"$Url":"/mobmaturities/3904"}},{"Id":3905,"Name":"Old Alpha","Properties":{"Description":null,"Health":1910,"AttacksPerMinute":null,"Level":36,"RegenerationInterval":null,"RegenerationAmount":null,"MissChance":null,"Taming":{"IsTameable":false,"TamingLevel":null},"Attributes":{"Strength":61,"Agility":59,"Intelligence":24,"Psyche":24,"Stamina":191},"Defense":{"Stab":null,"Cut":null,"Impact":null,"Penetration":null,"Shrapnel":null,"Burn":null,"Cold":null,"Acid":null,"Electric":null}},"Attacks":[],"Mob":{"Name":"Sumima (Calypso)","Links":{"$Url":"/mobs/615"}},"Links":{"$Url":"/mobmaturities/3905"}},{"Id":3906,"Name":"Prowler","Properties":{"Description":null,"Health":1970,"AttacksPerMinute":null,"Level":39,"RegenerationInterval":null,"RegenerationAmount":null,"MissChance":null,"Taming":{"IsTameable":false,"TamingLevel":null},"Attributes":{"Strength":64,"Agility":61,"Intelligence":242,"Psyche":24,"Stamina":197},"Defense":{"Stab":null,"Cut":null,"Impact":null,"Penetration":null,"Shrapnel":null,"Burn":null,"Cold":null,"Acid":null,"Electric":null}},"Attacks":[],"Mob":{"Name":"Sumima (Calypso)","Links":{"$Url":"/mobs/615"}},"Links":{"$Url":"/mobmaturities/3906"}},{"Id":3907,"Name":"Stalker","Properties":{"Description":null,"Health":2040,"AttacksPerMinute":null,"Level":41,"RegenerationInterval":null,"RegenerationAmount":null,"MissChance":null,"Taming":{"IsTameable":false,"TamingLevel":null},"Attributes":{"Strength":67,"Agility":64,"Intelligence":25,"Psyche":25,"Stamina":204},"Defense":{"Stab":null,"Cut":null,"Impact":null,"Penetration":null,"Shrapnel":null,"Burn":null,"Cold":null,"Acid":null,"Electric":null}},"Attacks":[],"Mob":{"Name":"Sumima (Calypso)","Links":{"$Url":"/mobs/615"}},"Links":{"$Url":"/mobmaturities/3907"}},{"Id":3908,"Name":"Young","Properties":{"Description":null,"Health":1450,"AttacksPerMinute":null,"Level":23,"RegenerationInterval":null,"RegenerationAmount":null,"MissChance":null,"Taming":{"IsTameable":false,"TamingLevel":null},"Attributes":{"Strength":41,"Agility":40,"Intelligence":20,"Psyche":20,"Stamina":145},"Defense":{"Stab":null,"Cut":null,"Impact":null,"Penetration":null,"Shrapnel":null,"Burn":null,"Cold":null,"Acid":null,"Electric":null}},"Attacks":[],"Mob":{"Name":"Sumima (Calypso)","Links":{"$Url":"/mobs/615"}},"Links":{"$Url":"/mobmaturities/3908"}},{"Id":3909,"Name":"Old","Properties":{"Description":null,"Health":1580,"AttacksPerMinute":null,"Level":27,"RegenerationInterval":null,"RegenerationAmount":null,"MissChance":null,"Taming":{"IsTameable":false,"TamingLevel":null},"Attributes":{"Strength":47,"Agility":44,"Intelligence":21,"Psyche":21,"Stamina":158},"Defense":{"Stab":null,"Cut":null,"Impact":null,"Penetration":null,"Shrapnel":null,"Burn":null,"Cold":null,"Acid":null,"Electric":null}},"Attacks":[],"Mob":{"Name":"Sumima (Calypso)","Links":{"$Url":"/mobs/615"}},"Links":{"$Url":"/mobmaturities/3909"}}],"Spawns":[{"Id":3232,"Name":"Sumima (Calypso) - Mature/Old/Young","Properties":{"Description":null,"Density":3,"IsShared":false,"IsEvent":false,"Notes":"4% tax","Type":"MobArea","Shape":"Polygon","Data":{"vertices":[49685.61,73390.65,50260.35,73431.07,50552.76,73602.86,51147.66,73582.65,51419.91,73471.49,51974.48,72329.6,51903.9,72178.02,51924.07,71925.39,52135.81,71773.81,52135.81,71248.34,51994.65,71116.97,51661.9,71106.86,51208.16,71420.13,50956.08,71480.76,50633.42,71450.44,49927.6,70874.44,49867.1,70914.86,49907.43,71258.44,50038.52,71561.6,49705.77,71733.39,49665.44,72299.28,49554.52,72592.34,49816.69,72865.18,49816.69,73057.18,49625.11,73218.86,49685.61,73390.65]},"Coordinates":{"Longitude":50763,"Latitude":72486,"Altitude":150}},"Planet":{"Name":"Calypso","Properties":{"TechnicalName":"Calypso"},"Links":{"$Url":"/planets/1"}},"Maturities":[{"IsRare":false,"Maturity":{"Id":3900,"Name":"Mature","Properties":{"Description":null,"Health":1520,"AttacksPerMinute":null,"Level":25,"RegenerationInterval":null,"RegenerationAmount":null,"MissChance":null,"Taming":{"IsTameable":false,"TamingLevel":null},"Attributes":{"Strength":44,"Agility":42,"Intelligence":20,"Psyche":20,"Stamina":152},"Defense":{"Stab":null,"Cut":null,"Impact":null,"Penetration":null,"Shrapnel":null,"Burn":null,"Cold":null,"Acid":null,"Electric":null}},"Attacks":[],"Mob":{"Name":"Sumima (Calypso)","Links":{"$Url":"/mobs/615"}},"Links":{"$Url":"/mobmaturities/3900"}}},{"IsRare":false,"Maturity":{"Id":3908,"Name":"Young","Properties":{"Description":null,"Health":1450,"AttacksPerMinute":null,"Level":23,"RegenerationInterval":null,"RegenerationAmount":null,"MissChance":null,"Taming":{"IsTameable":false,"TamingLevel":null},"Attributes":{"Strength":41,"Agility":40,"Intelligence":20,"Psyche":20,"Stamina":145},"Defense":{"Stab":null,"Cut":null,"Impact":null,"Penetration":null,"Shrapnel":null,"Burn":null,"Cold":null,"Acid":null,"Electric":null}},"Attacks":[],"Mob":{"Name":"Sumima (Calypso)","Links":{"$Url":"/mobs/615"}},"Links":{"$Url":"/mobmaturities/3908"}}},{"IsRare":false,"Maturity":{"Id":3909,"Name":"Old","Properties":{"Description":null,"Health":1580,"AttacksPerMinute":null,"Level":27,"RegenerationInterval":null,"RegenerationAmount":null,"MissChance":null,"Taming":{"IsTameable":false,"TamingLevel":null},"Attributes":{"Strength":47,"Agility":44,"Intelligence":21,"Psyche":21,"Stamina":158},"Defense":{"Stab":null,"Cut":null,"Impact":null,"Penetration":null,"Shrapnel":null,"Burn":null,"Cold":null,"Acid":null,"Electric":null}},"Attacks":[],"Mob":{"Name":"Sumima (Calypso)","Links":{"$Url":"/mobs/615"}},"Links":{"$Url":"/mobmaturities/3909"}}}],"Links":{"$Url":"/mobspawns/3232"}},{"Id":3233,"Name":"Sumima (Calypso) - Mature/Old/Provider/Young, Exarosaur - Young","Properties":{"Description":null,"Density":3,"IsShared":false,"IsEvent":false,"Notes":"","Type":"MobArea","Shape":"Polygon","Data":{"vertices":[18030.66,63598.4,19563.3,63598.4,19457.93,63387.2,19400.45,63243.2,18193.5,63243.2,18145.6,63454.4,18001.92,63492.8,18030.66,63598.4]},"Coordinates":{"Longitude":18535,"Latitude":63421,"Altitude":150}},"Planet":{"Name":"Calypso","Properties":{"TechnicalName":"Calypso"},"Links":{"$Url":"/planets/1"}},"Maturities":[{"IsRare":false,"Maturity":{"Id":3900,"Name":"Mature","Properties":{"Description":null,"Health":1520,"AttacksPerMinute":null,"Level":25,"RegenerationInterval":null,"RegenerationAmount":null,"MissChance":null,"Taming":{"IsTameable":false,"TamingLevel":null},"Attributes":{"Strength":44,"Agility":42,"Intelligence":20,"Psyche":20,"Stamina":152},"Defense":{"Stab":null,"Cut":null,"Impact":null,"Penetration":null,"Shrapnel":null,"Burn":null,"Cold":null,"Acid":null,"Electric":null}},"Attacks":[],"Mob":{"Name":"Sumima (Calypso)","Links":{"$Url":"/mobs/615"}},"Links":{"$Url":"/mobmaturities/3900"}}},{"IsRare":false,"Maturity":{"Id":3901,"Name":"Provider","Properties":{"Description":null,"Health":1650,"AttacksPerMinute":null,"Level":29,"RegenerationInterval":null,"RegenerationAmount":null,"MissChance":null,"Taming":{"IsTameable":false,"TamingLevel":null},"Attributes":{"Strength":50,"Agility":47,"Intelligence":22,"Psyche":22,"Stamina":165},"Defense":{"Stab":null,"Cut":null,"Impact":null,"Penetration":null,"Shrapnel":null,"Burn":null,"Cold":null,"Acid":null,"Electric":null}},"Attacks":[],"Mob":{"Name":"Sumima (Calypso)","Links":{"$Url":"/mobs/615"}},"Links":{"$Url":"/mobmaturities/3901"}}},{"IsRare":false,"Maturity":{"Id":3908,"Name":"Young","Properties":{"Description":null,"Health":1450,"AttacksPerMinute":null,"Level":23,"RegenerationInterval":null,"RegenerationAmount":null,"MissChance":null,"Taming":{"IsTameable":false,"TamingLevel":null},"Attributes":{"Strength":41,"Agility":40,"Intelligence":20,"Psyche":20,"Stamina":145},"Defense":{"Stab":null,"Cut":null,"Impact":null,"Penetration":null,"Shrapnel":null,"Burn":null,"Cold":null,"Acid":null,"Electric":null}},"Attacks":[],"Mob":{"Name":"Sumima (Calypso)","Links":{"$Url":"/mobs/615"}},"Links":{"$Url":"/mobmaturities/3908"}}},{"IsRare":false,"Maturity":{"Id":3909,"Name":"Old","Properties":{"Description":null,"Health":1580,"AttacksPerMinute":null,"Level":27,"RegenerationInterval":null,"RegenerationAmount":null,"MissChance":null,"Taming":{"IsTameable":false,"TamingLevel":null},"Attributes":{"Strength":47,"Agility":44,"Intelligence":21,"Psyche":21,"Stamina":158},"Defense":{"Stab":null,"Cut":null,"Impact":null,"Penetration":null,"Shrapnel":null,"Burn":null,"Cold":null,"Acid":null,"Electric":null}},"Attacks":[],"Mob":{"Name":"Sumima (Calypso)","Links":{"$Url":"/mobs/615"}},"Links":{"$Url":"/mobmaturities/3909"}}}],"Links":{"$Url":"/mobspawns/3233"}},{"Id":3234,"Name":"Sumima (Calypso) - Guardian/Mature/Old/Provider","Properties":{"Description":null,"Density":3,"IsShared":false,"IsEvent":false,"Notes":"Rare Dominant","Type":"MobArea","Shape":"Polygon","Data":{"vertices":[19533.68,63170.02,20175.48,63150.82,20357.48,63160.42,20482.01,63275.62,20520.32,63707.62,20980.11,63746.02,20903.48,63995.62,20970.53,63986.02,21056.75,63803.62,21133.38,63755.62,20980.11,63496.42,20970.53,63266.02,20874.74,63054.82,20683.16,62930.02,20558.64,62699.62,20491.58,62488.42,20319.16,62344.42,20070.11,62219.62,19782.74,62594.02,19840.21,62786.02,19533.68,63170.02]},"Coordinates":{"Longitude":20205,"Latitude":62787,"Altitude":150}},"Planet":{"Name":"Calypso","Properties":{"TechnicalName":"Calypso"},"Links":{"$Url":"/planets/1"}},"Maturities":[{"IsRare":false,"Maturity":{"Id":3900,"Name":"Mature","Properties":{"Description":null,"Health":1520,"AttacksPerMinute":null,"Level":25,"RegenerationInterval":null,"RegenerationAmount":null,"MissChance":null,"Taming":{"IsTameable":false,"TamingLevel":null},"Attributes":{"Strength":44,"Agility":42,"Intelligence":20,"Psyche":20,"Stamina":152},"Defense":{"Stab":null,"Cut":null,"Impact":null,"Penetration":null,"Shrapnel":null,"Burn":null,"Cold":null,"Acid":null,"Electric":null}},"Attacks":[],"Mob":{"Name":"Sumima (Calypso)","Links":{"$Url":"/mobs/615"}},"Links":{"$Url":"/mobmaturities/3900"}}},{"IsRare":false,"Maturity":{"Id":3901,"Name":"Provider","Properties":{"Description":null,"Health":1650,"AttacksPerMinute":null,"Level":29,"RegenerationInterval":null,"RegenerationAmount":null,"MissChance":null,"Taming":{"IsTameable":false,"TamingLevel":null},"Attributes":{"Strength":50,"Agility":47,"Intelligence":22,"Psyche":22,"Stamina":165},"Defense":{"Stab":null,"Cut":null,"Impact":null,"Penetration":null,"Shrapnel":null,"Burn":null,"Cold":null,"Acid":null,"Electric":null}},"Attacks":[],"Mob":{"Name":"Sumima (Calypso)","Links":{"$Url":"/mobs/615"}},"Links":{"$Url":"/mobmaturities/3901"}}},{"IsRare":false,"Maturity":{"Id":3904,"Name":"Guardian","Properties":{"Description":null,"Health":1710,"AttacksPerMinute":null,"Level":31,"RegenerationInterval":null,"RegenerationAmount":null,"MissChance":null,"Taming":{"IsTameable":false,"TamingLevel":null},"Attributes":{"Strength":53,"Agility":51,"Intelligence":22,"Psyche":22,"Stamina":171},"Defense":{"Stab":null,"Cut":null,"Impact":null,"Penetration":null,"Shrapnel":null,"Burn":null,"Cold":null,"Acid":null,"Electric":null}},"Attacks":[],"Mob":{"Name":"Sumima (Calypso)","Links":{"$Url":"/mobs/615"}},"Links":{"$Url":"/mobmaturities/3904"}}},{"IsRare":false,"Maturity":{"Id":3909,"Name":"Old","Properties":{"Description":null,"Health":1580,"AttacksPerMinute":null,"Level":27,"RegenerationInterval":null,"RegenerationAmount":null,"MissChance":null,"Taming":{"IsTameable":false,"TamingLevel":null},"Attributes":{"Strength":47,"Agility":44,"Intelligence":21,"Psyche":21,"Stamina":158},"Defense":{"Stab":null,"Cut":null,"Impact":null,"Penetration":null,"Shrapnel":null,"Burn":null,"Cold":null,"Acid":null,"Electric":null}},"Attacks":[],"Mob":{"Name":"Sumima (Calypso)","Links":{"$Url":"/mobs/615"}},"Links":{"$Url":"/mobmaturities/3909"}}}],"Links":{"$Url":"/mobspawns/3234"}},{"Id":3235,"Name":"Sumima (Calypso) - Mature/Old/Provider, Snarg - Mature/Old/Young, TskTsk - Soldier/Watcher","Properties":{"Description":null,"Density":3,"IsShared":false,"IsEvent":false,"Notes":"","Type":"MobArea","Shape":"Polygon","Data":{"vertices":[19626.7,63619.2,20488.81,63696,20460.07,63312,20335.55,63187.2,19530.91,63196.8,19454.28,63264,19626.7,63619.2]},"Coordinates":{"Longitude":20226,"Latitude":63430,"Altitude":150}},"Planet":{"Name":"Calypso","Properties":{"TechnicalName":"Calypso"},"Links":{"$Url":"/planets/1"}},"Maturities":[{"IsRare":false,"Maturity":{"Id":3680,"Name":"Young","Properties":{"Description":null,"Health":320,"AttacksPerMinute":null,"Level":7,"RegenerationInterval":null,"RegenerationAmount":null,"MissChance":null,"Taming":{"IsTameable":false,"TamingLevel":null},"Attributes":{"Strength":53,"Agility":30,"Intelligence":4,"Psyche":1,"Stamina":32},"Defense":{"Stab":null,"Cut":null,"Impact":null,"Penetration":null,"Shrapnel":null,"Burn":null,"Cold":null,"Acid":null,"Electric":null}},"Attacks":[],"Mob":{"Name":"Snarg","Links":{"$Url":"/mobs/589"}},"Links":{"$Url":"/mobmaturities/3680"}}},{"IsRare":false,"Maturity":{"Id":3681,"Name":"Mature","Properties":{"Description":null,"Health":380,"AttacksPerMinute":null,"Level":8,"RegenerationInterval":null,"RegenerationAmount":null,"MissChance":null,"Taming":{"IsTameable":false,"TamingLevel":null},"Attributes":{"Strength":54,"Agility":30,"Intelligence":4,"Psyche":2,"Stamina":38},"Defense":{"Stab":null,"Cut":null,"Impact":null,"Penetration":null,"Shrapnel":null,"Burn":null,"Cold":null,"Acid":null,"Electric":null}},"Attacks":[],"Mob":{"Name":"Snarg","Links":{"$Url":"/mobs/589"}},"Links":{"$Url":"/mobmaturities/3681"}}},{"IsRare":false,"Maturity":{"Id":3682,"Name":"Old","Properties":{"Description":null,"Health":490,"AttacksPerMinute":null,"Level":10,"RegenerationInterval":null,"RegenerationAmount":null,"MissChance":null,"Taming":{"IsTameable":false,"TamingLevel":null},"Attributes":{"Strength":55,"Agility":32,"Intelligence":4,"Psyche":2,"Stamina":49},"Defense":{"Stab":null,"Cut":null,"Impact":null,"Penetration":null,"Shrapnel":null,"Burn":null,"Cold":null,"Acid":null,"Electric":null}},"Attacks":[],"Mob":{"Name":"Snarg","Links":{"$Url":"/mobs/589"}},"Links":{"$Url":"/mobmaturities/3682"}}},{"IsRare":false,"Maturity":{"Id":3900,"Name":"Mature","Properties":{"Description":null,"Health":1520,"AttacksPerMinute":null,"Level":25,"RegenerationInterval":null,"RegenerationAmount":null,"MissChance":null,"Taming":{"IsTameable":false,"TamingLevel":null},"Attributes":{"Strength":44,"Agility":42,"Intelligence":20,"Psyche":20,"Stamina":152},"Defense":{"Stab":null,"Cut":null,"Impact":null,"Penetration":null,"Shrapnel":null,"Burn":null,"Cold":null,"Acid":null,"Electric":null}},"Attacks":[],"Mob":{"Name":"Sumima (Calypso)","Links":{"$Url":"/mobs/615"}},"Links":{"$Url":"/mobmaturities/3900"}}},{"IsRare":false,"Maturity":{"Id":3901,"Name":"Provider","Properties":{"Description":null,"Health":1650,"AttacksPerMinute":null,"Level":29,"RegenerationInterval":null,"RegenerationAmount":null,"MissChance":null,"Taming":{"IsTameable":false,"TamingLevel":null},"Attributes":{"Strength":50,"Agility":47,"Intelligence":22,"Psyche":22,"Stamina":165},"Defense":{"Stab":null,"Cut":null,"Impact":null,"Penetration":null,"Shrapnel":null,"Burn":null,"Cold":null,"Acid":null,"Electric":null}},"Attacks":[],"Mob":{"Name":"Sumima (Calypso)","Links":{"$Url":"/mobs/615"}},"Links":{"$Url":"/mobmaturities/3901"}}},{"IsRare":false,"Maturity":{"Id":3909,"Name":"Old","Properties":{"Description":null,"Health":1580,"AttacksPerMinute":null,"Level":27,"RegenerationInterval":null,"RegenerationAmount":null,"MissChance":null,"Taming":{"IsTameable":false,"TamingLevel":null},"Attributes":{"Strength":47,"Agility":44,"Intelligence":21,"Psyche":21,"Stamina":158},"Defense":{"Stab":null,"Cut":null,"Impact":null,"Penetration":null,"Shrapnel":null,"Burn":null,"Cold":null,"Acid":null,"Electric":null}},"Attacks":[],"Mob":{"Name":"Sumima (Calypso)","Links":{"$Url":"/mobs/615"}},"Links":{"$Url":"/mobmaturities/3909"}}},{"IsRare":false,"Maturity":{"Id":4247,"Name":"Soldier","Properties":{"Description":null,"Health":870,"AttacksPerMinute":22,"Level":17,"RegenerationInterval":null,"RegenerationAmount":null,"MissChance":null,"Taming":{"IsTameable":false,"TamingLevel":null},"Attributes":{"Strength":26,"Agility":63,"Intelligence":22,"Psyche":23,"Stamina":87},"Defense":{"Stab":null,"Cut":null,"Impact":null,"Penetration":null,"Shrapnel":null,"Burn":null,"Cold":null,"Acid":null,"Electric":null}},"Attacks":[],"Mob":{"Name":"TskTsk","Links":{"$Url":"/mobs/674"}},"Links":{"$Url":"/mobmaturities/4247"}}},{"IsRare":false,"Maturity":{"Id":4248,"Name":"Watcher","Properties":{"Description":null,"Health":790,"AttacksPerMinute":22,"Level":16,"RegenerationInterval":null,"RegenerationAmount":null,"MissChance":null,"Taming":{"IsTameable":false,"TamingLevel":null},"Attributes":{"Strength":24,"Agility":61,"Intelligence":21,"Psyche":22,"Stamina":79},"Defense":{"Stab":null,"Cut":null,"Impact":null,"Penetration":null,"Shrapnel":null,"Burn":null,"Cold":null,"Acid":null,"Electric":null}},"Attacks":[],"Mob":{"Name":"TskTsk","Links":{"$Url":"/mobs/674"}},"Links":{"$Url":"/mobmaturities/4248"}}}],"Links":{"$Url":"/mobspawns/3235"}},{"Id":3236,"Name":"Sumima (Calypso) - Alpha/Dominant/Old Alpha/Prowler/Stalker, Gokibusagi - Alpha/Old Alpha/Prowler","Properties":{"Description":null,"Density":3,"IsShared":false,"IsEvent":false,"Notes":"3.99% tax","Type":"MobArea","Shape":"Polygon","Data":{"vertices":[51419.4,70166.4,51486.46,69955.2,52291.09,69801.6,52329.41,69648,52463.51,69552,52808.36,69897.6,52635.94,70406.4,52338.99,70550.4,52195.3,70560,52080.35,70377.6,51438.56,70195.2,51419.4,70166.4]},"Coordinates":{"Longitude":52350,"Latitude":70150,"Altitude":150}},"Planet":{"Name":"Calypso","Properties":{"TechnicalName":"Calypso"},"Links":{"$Url":"/planets/1"}},"Maturities":[{"IsRare":false,"Maturity":{"Id":1536,"Name":"Alpha","Properties":{"Description":null,"Health":590,"AttacksPerMinute":null,"Level":21,"RegenerationInterval":null,"RegenerationAmount":null,"MissChance":null,"Taming":{"IsTameable":false,"TamingLevel":null},"Attributes":{"Strength":39,"Agility":38,"Intelligence":10,"Psyche":10,"Stamina":59},"Defense":{"Stab":null,"Cut":null,"Impact":null,"Penetration":null,"Shrapnel":null,"Burn":null,"Cold":null,"Acid":null,"Electric":null}},"Attacks":[],"Mob":{"Name":"Gokibusagi","Links":{"$Url":"/mobs/281"}},"Links":{"$Url":"/mobmaturities/1536"}}},{"IsRare":false,"Maturity":{"Id":1538,"Name":"Prowler","Properties":{"Description":null,"Health":670,"AttacksPerMinute":null,"Level":23,"RegenerationInterval":null,"RegenerationAmount":null,"MissChance":null,"Taming":{"IsTameable":false,"TamingLevel":null},"Attributes":{"Strength":43,"Agility":50,"Intelligence":10,"Psyche":10,"Stamina":67},"Defense":{"Stab":null,"Cut":null,"Impact":null,"Penetration":null,"Shrapnel":null,"Burn":null,"Cold":null,"Acid":null,"Electric":null}},"Attacks":[],"Mob":{"Name":"Gokibusagi","Links":{"$Url":"/mobs/281"}},"Links":{"$Url":"/mobmaturities/1538"}}},{"IsRare":false,"Maturity":{"Id":1540,"Name":"Old Alpha","Properties":{"Description":null,"Health":610,"AttacksPerMinute":null,"Level":22,"RegenerationInterval":null,"RegenerationAmount":null,"MissChance":null,"Taming":{"IsTameable":false,"TamingLevel":null},"Attributes":{"Strength":40,"Agility":40,"Intelligence":10,"Psyche":10,"Stamina":61},"Defense":{"Stab":null,"Cut":null,"Impact":null,"Penetration":null,"Shrapnel":null,"Burn":null,"Cold":null,"Acid":null,"Electric":null}},"Attacks":[],"Mob":{"Name":"Gokibusagi","Links":{"$Url":"/mobs/281"}},"Links":{"$Url":"/mobmaturities/1540"}}},{"IsRare":false,"Maturity":{"Id":3902,"Name":"Dominant","Properties":{"Description":null,"Health":1780,"AttacksPerMinute":null,"Level":33,"RegenerationInterval":null,"RegenerationAmount":null,"MissChance":null,"Taming":{"IsTameable":false,"TamingLevel":null},"Attributes":{"Strength":55,"Agility":53,"Intelligence":23,"Psyche":23,"Stamina":178},"Defense":{"Stab":null,"Cut":null,"Impact":null,"Penetration":null,"Shrapnel":null,"Burn":null,"Cold":null,"Acid":null,"Electric":null}},"Attacks":[],"Mob":{"Name":"Sumima (Calypso)","Links":{"$Url":"/mobs/615"}},"Links":{"$Url":"/mobmaturities/3902"}}},{"IsRare":false,"Maturity":{"Id":3903,"Name":"Alpha","Properties":{"Description":null,"Health":1840,"AttacksPerMinute":null,"Level":35,"RegenerationInterval":null,"RegenerationAmount":null,"MissChance":null,"Taming":{"IsTameable":false,"TamingLevel":null},"Attributes":{"Strength":58,"Agility":56,"Intelligence":23,"Psyche":23,"Stamina":184},"Defense":{"Stab":null,"Cut":null,"Impact":null,"Penetration":null,"Shrapnel":null,"Burn":null,"Cold":null,"Acid":null,"Electric":null}},"Attacks":[],"Mob":{"Name":"Sumima (Calypso)","Links":{"$Url":"/mobs/615"}},"Links":{"$Url":"/mobmaturities/3903"}}},{"IsRare":false,"Maturity":{"Id":3905,"Name":"Old Alpha","Properties":{"Description":null,"Health":1910,"AttacksPerMinute":null,"Level":36,"RegenerationInterval":null,"RegenerationAmount":null,"MissChance":null,"Taming":{"IsTameable":false,"TamingLevel":null},"Attributes":{"Strength":61,"Agility":59,"Intelligence":24,"Psyche":24,"Stamina":191},"Defense":{"Stab":null,"Cut":null,"Impact":null,"Penetration":null,"Shrapnel":null,"Burn":null,"Cold":null,"Acid":null,"Electric":null}},"Attacks":[],"Mob":{"Name":"Sumima (Calypso)","Links":{"$Url":"/mobs/615"}},"Links":{"$Url":"/mobmaturities/3905"}}},{"IsRare":false,"Maturity":{"Id":3906,"Name":"Prowler","Properties":{"Description":null,"Health":1970,"AttacksPerMinute":null,"Level":39,"RegenerationInterval":null,"RegenerationAmount":null,"MissChance":null,"Taming":{"IsTameable":false,"TamingLevel":null},"Attributes":{"Strength":64,"Agility":61,"Intelligence":242,"Psyche":24,"Stamina":197},"Defense":{"Stab":null,"Cut":null,"Impact":null,"Penetration":null,"Shrapnel":null,"Burn":null,"Cold":null,"Acid":null,"Electric":null}},"Attacks":[],"Mob":{"Name":"Sumima (Calypso)","Links":{"$Url":"/mobs/615"}},"Links":{"$Url":"/mobmaturities/3906"}}},{"IsRare":false,"Maturity":{"Id":3907,"Name":"Stalker","Properties":{"Description":null,"Health":2040,"AttacksPerMinute":null,"Level":41,"RegenerationInterval":null,"RegenerationAmount":null,"MissChance":null,"Taming":{"IsTameable":false,"TamingLevel":null},"Attributes":{"Strength":67,"Agility":64,"Intelligence":25,"Psyche":25,"Stamina":204},"Defense":{"Stab":null,"Cut":null,"Impact":null,"Penetration":null,"Shrapnel":null,"Burn":null,"Cold":null,"Acid":null,"Electric":null}},"Attacks":[],"Mob":{"Name":"Sumima (Calypso)","Links":{"$Url":"/mobs/615"}},"Links":{"$Url":"/mobmaturities/3907"}}}],"Links":{"$Url":"/mobspawns/3236"}},{"Id":3237,"Name":"Sumima (Calypso) - Guardian/Mature/Old/Provider/Young, Exarosaur - Young","Properties":{"Description":null,"Density":3,"IsShared":false,"IsEvent":false,"Notes":"","Type":"MobArea","Shape":"Polygon","Data":{"vertices":[16851.98,63241.6,17168.09,63452.8,17273.46,63568,17541.67,63760,17761.99,63712,17656.62,63366.4,17714.09,63193.6,17532.09,62944,17330.93,62723.2,17215.99,62742.4,17120.2,62713.6,16938.2,62848,16880.72,62963.2,16871.14,63145.6,16851.98,63241.6]},"Coordinates":{"Longitude":17207,"Latitude":63079,"Altitude":150}},"Planet":{"Name":"Calypso","Properties":{"TechnicalName":"Calypso"},"Links":{"$Url":"/planets/1"}},"Maturities":[{"IsRare":false,"Maturity":{"Id":3900,"Name":"Mature","Properties":{"Description":null,"Health":1520,"AttacksPerMinute":null,"Level":25,"RegenerationInterval":null,"RegenerationAmount":null,"MissChance":null,"Taming":{"IsTameable":false,"TamingLevel":null},"Attributes":{"Strength":44,"Agility":42,"Intelligence":20,"Psyche":20,"Stamina":152},"Defense":{"Stab":null,"Cut":null,"Impact":null,"Penetration":null,"Shrapnel":null,"Burn":null,"Cold":null,"Acid":null,"Electric":null}},"Attacks":[],"Mob":{"Name":"Sumima (Calypso)","Links":{"$Url":"/mobs/615"}},"Links":{"$Url":"/mobmaturities/3900"}}},{"IsRare":false,"Maturity":{"Id":3901,"Name":"Provider","Properties":{"Description":null,"Health":1650,"AttacksPerMinute":null,"Level":29,"RegenerationInterval":null,"RegenerationAmount":null,"MissChance":null,"Taming":{"IsTameable":false,"TamingLevel":null},"Attributes":{"Strength":50,"Agility":47,"Intelligence":22,"Psyche":22,"Stamina":165},"Defense":{"Stab":null,"Cut":null,"Impact":null,"Penetration":null,"Shrapnel":null,"Burn":null,"Cold":null,"Acid":null,"Electric":null}},"Attacks":[],"Mob":{"Name":"Sumima (Calypso)","Links":{"$Url":"/mobs/615"}},"Links":{"$Url":"/mobmaturities/3901"}}},{"IsRare":false,"Maturity":{"Id":3904,"Name":"Guardian","Properties":{"Description":null,"Health":1710,"AttacksPerMinute":null,"Level":31,"RegenerationInterval":null,"RegenerationAmount":null,"MissChance":null,"Taming":{"IsTameable":false,"TamingLevel":null},"Attributes":{"Strength":53,"Agility":51,"Intelligence":22,"Psyche":22,"Stamina":171},"Defense":{"Stab":null,"Cut":null,"Impact":null,"Penetration":null,"Shrapnel":null,"Burn":null,"Cold":null,"Acid":null,"Electric":null}},"Attacks":[],"Mob":{"Name":"Sumima (Calypso)","Links":{"$Url":"/mobs/615"}},"Links":{"$Url":"/mobmaturities/3904"}}},{"IsRare":false,"Maturity":{"Id":3908,"Name":"Young","Properties":{"Description":null,"Health":1450,"AttacksPerMinute":null,"Level":23,"RegenerationInterval":null,"RegenerationAmount":null,"MissChance":null,"Taming":{"IsTameable":false,"TamingLevel":null},"Attributes":{"Strength":41,"Agility":40,"Intelligence":20,"Psyche":20,"Stamina":145},"Defense":{"Stab":null,"Cut":null,"Impact":null,"Penetration":null,"Shrapnel":null,"Burn":null,"Cold":null,"Acid":null,"Electric":null}},"Attacks":[],"Mob":{"Name":"Sumima (Calypso)","Links":{"$Url":"/mobs/615"}},"Links":{"$Url":"/mobmaturities/3908"}}},{"IsRare":false,"Maturity":{"Id":3909,"Name":"Old","Properties":{"Description":null,"Health":1580,"AttacksPerMinute":null,"Level":27,"RegenerationInterval":null,"RegenerationAmount":null,"MissChance":null,"Taming":{"IsTameable":false,"TamingLevel":null},"Attributes":{"Strength":47,"Agility":44,"Intelligence":21,"Psyche":21,"Stamina":158},"Defense":{"Stab":null,"Cut":null,"Impact":null,"Penetration":null,"Shrapnel":null,"Burn":null,"Cold":null,"Acid":null,"Electric":null}},"Attacks":[],"Mob":{"Name":"Sumima (Calypso)","Links":{"$Url":"/mobs/615"}},"Links":{"$Url":"/mobmaturities/3909"}}}],"Links":{"$Url":"/mobspawns/3237"}},{"Id":3238,"Name":"Sumima (Calypso) - Guardian/Mature/Old/Provider/Young","Properties":{"Description":null,"Density":3,"IsShared":false,"IsEvent":false,"Notes":"","Type":"MobArea","Shape":"Polygon","Data":{"vertices":[21289.24,62452.21,21375.45,62039.41,21806.51,62001.01,21519.14,62337.01,21289.24,62452.21]},"Coordinates":{"Longitude":21487,"Latitude":62166,"Altitude":150}},"Planet":{"Name":"Calypso","Properties":{"TechnicalName":"Calypso"},"Links":{"$Url":"/planets/1"}},"Maturities":[{"IsRare":false,"Maturity":{"Id":3900,"Name":"Mature","Properties":{"Description":null,"Health":1520,"AttacksPerMinute":null,"Level":25,"RegenerationInterval":null,"RegenerationAmount":null,"MissChance":null,"Taming":{"IsTameable":false,"TamingLevel":null},"Attributes":{"Strength":44,"Agility":42,"Intelligence":20,"Psyche":20,"Stamina":152},"Defense":{"Stab":null,"Cut":null,"Impact":null,"Penetration":null,"Shrapnel":null,"Burn":null,"Cold":null,"Acid":null,"Electric":null}},"Attacks":[],"Mob":{"Name":"Sumima (Calypso)","Links":{"$Url":"/mobs/615"}},"Links":{"$Url":"/mobmaturities/3900"}}},{"IsRare":false,"Maturity":{"Id":3901,"Name":"Provider","Properties":{"Description":null,"Health":1650,"AttacksPerMinute":null,"Level":29,"RegenerationInterval":null,"RegenerationAmount":null,"MissChance":null,"Taming":{"IsTameable":false,"TamingLevel":null},"Attributes":{"Strength":50,"Agility":47,"Intelligence":22,"Psyche":22,"Stamina":165},"Defense":{"Stab":null,"Cut":null,"Impact":null,"Penetration":null,"Shrapnel":null,"Burn":null,"Cold":null,"Acid":null,"Electric":null}},"Attacks":[],"Mob":{"Name":"Sumima (Calypso)","Links":{"$Url":"/mobs/615"}},"Links":{"$Url":"/mobmaturities/3901"}}},{"IsRare":false,"Maturity":{"Id":3904,"Name":"Guardian","Properties":{"Description":null,"Health":1710,"AttacksPerMinute":null,"Level":31,"RegenerationInterval":null,"RegenerationAmount":null,"MissChance":null,"Taming":{"IsTameable":false,"TamingLevel":null},"Attributes":{"Strength":53,"Agility":51,"Intelligence":22,"Psyche":22,"Stamina":171},"Defense":{"Stab":null,"Cut":null,"Impact":null,"Penetration":null,"Shrapnel":null,"Burn":null,"Cold":null,"Acid":null,"Electric":null}},"Attacks":[],"Mob":{"Name":"Sumima (Calypso)","Links":{"$Url":"/mobs/615"}},"Links":{"$Url":"/mobmaturities/3904"}}},{"IsRare":false,"Maturity":{"Id":3908,"Name":"Young","Properties":{"Description":null,"Health":1450,"AttacksPerMinute":null,"Level":23,"RegenerationInterval":null,"RegenerationAmount":null,"MissChance":null,"Taming":{"IsTameable":false,"TamingLevel":null},"Attributes":{"Strength":41,"Agility":40,"Intelligence":20,"Psyche":20,"Stamina":145},"Defense":{"Stab":null,"Cut":null,"Impact":null,"Penetration":null,"Shrapnel":null,"Burn":null,"Cold":null,"Acid":null,"Electric":null}},"Attacks":[],"Mob":{"Name":"Sumima (Calypso)","Links":{"$Url":"/mobs/615"}},"Links":{"$Url":"/mobmaturities/3908"}}},{"IsRare":false,"Maturity":{"Id":3909,"Name":"Old","Properties":{"Description":null,"Health":1580,"AttacksPerMinute":null,"Level":27,"RegenerationInterval":null,"RegenerationAmount":null,"MissChance":null,"Taming":{"IsTameable":false,"TamingLevel":null},"Attributes":{"Strength":47,"Agility":44,"Intelligence":21,"Psyche":21,"Stamina":158},"Defense":{"Stab":null,"Cut":null,"Impact":null,"Penetration":null,"Shrapnel":null,"Burn":null,"Cold":null,"Acid":null,"Electric":null}},"Attacks":[],"Mob":{"Name":"Sumima (Calypso)","Links":{"$Url":"/mobs/615"}},"Links":{"$Url":"/mobmaturities/3909"}}}],"Links":{"$Url":"/mobspawns/3238"}}],"Loots":[{"Mob":{"Name":"Sumima (Calypso)","Planet":{"Name":"Calypso","Links":{"$Url":"/planets/1"}},"Links":{"$Url":"/mobs/615"}},"Maturity":{"Name":"Young","Links":{"$Url":"/mobmaturities/3908"}},"Item":{"Name":"Animal Adrenal Oil","Properties":{"Type":"Material"},"Links":{"$Url":"/materials/115"}},"Frequency":"Very often","LastVU":"17.23.2.a","IsEvent":false,"IsDropping":true},{"Mob":{"Name":"Sumima (Calypso)","Planet":{"Name":"Calypso","Links":{"$Url":"/planets/1"}},"Links":{"$Url":"/mobs/615"}},"Maturity":{"Name":null,"Links":{"$Url":"/mobmaturities/null"}},"Item":{"Name":"Animal Hide","Properties":{"Type":"Material"},"Links":{"$Url":"/materials/121"}},"Frequency":"Often","LastVU":"17","IsEvent":false,"IsDropping":true},{"Mob":{"Name":"Sumima (Calypso)","Planet":{"Name":"Calypso","Links":{"$Url":"/planets/1"}},"Links":{"$Url":"/mobs/615"}},"Maturity":{"Name":null,"Links":{"$Url":"/mobmaturities/null"}},"Item":{"Name":"Basic Cloth Extractor","Properties":{"Type":"Material"},"Links":{"$Url":"/materials/239"}},"Frequency":"Uncommon","LastVU":"17.20.1a","IsEvent":false,"IsDropping":true},{"Mob":{"Name":"Sumima (Calypso)","Planet":{"Name":"Calypso","Links":{"$Url":"/planets/1"}},"Links":{"$Url":"/mobs/615"}},"Maturity":{"Name":"Mature","Links":{"$Url":"/mobmaturities/3900"}},"Item":{"Name":"Enhanced Cloth Extractor","Properties":{"Type":"Material"},"Links":{"$Url":"/materials/692"}},"Frequency":"Uncommon","LastVU":"17.20.1a","IsEvent":false,"IsDropping":true},{"Mob":{"Name":"Sumima (Calypso)","Planet":{"Name":"Calypso","Links":{"$Url":"/planets/1"}},"Links":{"$Url":"/mobs/615"}},"Maturity":{"Name":"Young","Links":{"$Url":"/mobmaturities/3908"}},"Item":{"Name":"Output Amplifier Component","Properties":{"Type":"Material"},"Links":{"$Url":"/materials/1625"}},"Frequency":"Common","LastVU":"17.23.2.a","IsEvent":false,"IsDropping":true},{"Mob":{"Name":"Sumima (Calypso)","Planet":{"Name":"Calypso","Links":{"$Url":"/planets/1"}},"Links":{"$Url":"/mobs/615"}},"Maturity":{"Name":"Mature","Links":{"$Url":"/mobmaturities/3900"}},"Item":{"Name":"Paint Can (Red)","Properties":{"Type":"Material"},"Links":{"$Url":"/materials/1670"}},"Frequency":"Uncommon","LastVU":"17.21.2","IsEvent":false,"IsDropping":true},{"Mob":{"Name":"Sumima (Calypso)","Planet":{"Name":"Calypso","Links":{"$Url":"/planets/1"}},"Links":{"$Url":"/mobs/615"}},"Maturity":{"Name":"Young","Links":{"$Url":"/mobmaturities/3908"}},"Item":{"Name":"Soft Hide","Properties":{"Type":"Material"},"Links":{"$Url":"/materials/2193"}},"Frequency":"Common","LastVU":"17.23.2.a","IsEvent":false,"IsDropping":true},{"Mob":{"Name":"Sumima (Calypso)","Planet":{"Name":"Calypso","Links":{"$Url":"/planets/1"}},"Links":{"$Url":"/mobs/615"}},"Maturity":{"Name":"Young","Links":{"$Url":"/mobmaturities/3908"}},"Item":{"Name":"Corrosive Attack Nanochip 8 (L)","Properties":{"Type":"Weapon"},"Links":{"$Url":"/weapons/605"}},"Frequency":"Uncommon","LastVU":"17.0.4","IsEvent":false,"IsDropping":true},{"Mob":{"Name":"Sumima (Calypso)","Planet":{"Name":"Calypso","Links":{"$Url":"/planets/1"}},"Links":{"$Url":"/mobs/615"}},"Maturity":{"Name":"Young","Links":{"$Url":"/mobmaturities/3908"}},"Item":{"Name":"EWE LC-200 Scout (L)","Properties":{"Type":"Weapon"},"Links":{"$Url":"/weapons/941"}},"Frequency":"Uncommon","LastVU":"17.1.2","IsEvent":false,"IsDropping":true},{"Mob":{"Name":"Sumima (Calypso)","Planet":{"Name":"Calypso","Links":{"$Url":"/planets/1"}},"Links":{"$Url":"/mobs/615"}},"Maturity":{"Name":"Young","Links":{"$Url":"/mobmaturities/3908"}},"Item":{"Name":"Chronicle Shin Guards (L)","Properties":{"Type":"Armor"},"Links":{"$Url":"/armors/389"}},"Frequency":"Rare","LastVU":"17.15.1","IsEvent":false,"IsDropping":true},{"Mob":{"Name":"Sumima (Calypso)","Planet":{"Name":"Calypso","Links":{"$Url":"/planets/1"}},"Links":{"$Url":"/mobs/615"}},"Maturity":{"Name":"Mature","Links":{"$Url":"/mobmaturities/3900"}},"Item":{"Name":"Empty Skill Implant (L)","Properties":{"Type":"MiscTool"},"Links":{"$Url":"/misctools/157"}},"Frequency":"Rare","LastVU":"17.23.2.a","IsEvent":false,"IsDropping":true},{"Mob":{"Name":"Sumima (Calypso)","Planet":{"Name":"Calypso","Links":{"$Url":"/planets/1"}},"Links":{"$Url":"/mobs/615"}},"Maturity":{"Name":"Young","Links":{"$Url":"/mobmaturities/3908"}},"Item":{"Name":"Regeneration Chip 4 (L)","Properties":{"Type":"MedicalChip"},"Links":{"$Url":"/medicalchips/18"}},"Frequency":"Uncommon","LastVU":"17.23.2.a","IsEvent":false,"IsDropping":true},{"Mob":{"Name":"Sumima (Calypso)","Planet":{"Name":"Calypso","Links":{"$Url":"/planets/1"}},"Links":{"$Url":"/mobs/615"}},"Maturity":{"Name":null,"Links":{"$Url":"/mobmaturities/null"}},"Item":{"Name":"Synchronization Chip 14 (L)","Properties":{"Type":"EffectChip"},"Links":{"$Url":"/effectchips/20017"}},"Frequency":"Uncommon","LastVU":"17.0.4","IsEvent":false,"IsDropping":true}],"Links":{"$Url":"/mobs/615"}}