{"Id":147,"Name":"Cosmic Horror","Type":null,"Properties":{"Description":null,"AttackRange":null,"AggressionRange":null,"IsSweatable":false},"DefensiveProfession":null,"ScanningProfession":null,"Planet":{"Name":"Space","Links":{"$Url":"/planets/17"}},"Species":{"Name":"Cosmic Horror","Properties":{"CodexBaseCost":81.25,"CodexType":"Mob"},"Links":{"$Url":"/mobspecies/26"}},"Maturities":[{"Id":769,"Name":"Old","Properties":{"Description":null,"Health":770,"AttacksPerMinute":null,"Level":32,"RegenerationInterval":null,"RegenerationAmount":null,"MissChance":null,"Taming":{"IsTameable":false,"TamingLevel":null},"Attributes":{"Strength":241,"Agility":47,"Intelligence":143,"Psyche":63,"Stamina":77},"Defense":{"Stab":null,"Cut":null,"Impact":null,"Penetration":null,"Shrapnel":null,"Burn":null,"Cold":null,"Acid":null,"Electric":null}},"Attacks":[],"Mob":{"Name":"Cosmic Horror","Links":{"$Url":"/mobs/147"}},"Links":{"$Url":"/mobmaturities/769"}},{"Id":770,"Name":"Mature","Properties":{"Description":null,"Health":720,"AttacksPerMinute":null,"Level":30,"RegenerationInterval":null,"RegenerationAmount":null,"MissChance":null,"Taming":{"IsTameable":false,"TamingLevel":null},"Attributes":{"Strength":227,"Agility":46,"Intelligence":131,"Psyche":62,"Stamina":72},"Defense":{"Stab":null,"Cut":null,"Impact":null,"Penetration":null,"Shrapnel":null,"Burn":null,"Cold":null,"Acid":null,"Electric":null}},"Attacks":[],"Mob":{"Name":"Cosmic Horror","Links":{"$Url":"/mobs/147"}},"Links":{"$Url":"/mobmaturities/770"}},{"Id":771,"Name":"Provider","Properties":{"Description":null,"Health":840,"AttacksPerMinute":null,"Level":35,"RegenerationInterval":null,"RegenerationAmount":null,"MissChance":null,"Taming":{"IsTameable":false,"TamingLevel":null},"Attributes":{"Strength":256,"Agility":47,"Intelligence":155,"Psyche":65,"Stamina":84},"Defense":{"Stab":null,"Cut":null,"Impact":null,"Penetration":null,"Shrapnel":null,"Burn":null,"Cold":null,"Acid":null,"Electric":null}},"Attacks":[],"Mob":{"Name":"Cosmic Horror","Links":{"$Url":"/mobs/147"}},"Links":{"$Url":"/mobmaturities/771"}},{"Id":772,"Name":"Guardian","Properties":{"Description":null,"Health":900,"AttacksPerMinute":null,"Level":37,"RegenerationInterval":null,"RegenerationAmount":null,"MissChance":null,"Taming":{"IsTameable":false,"TamingLevel":null},"Attributes":{"Strength":269,"Agility":48,"Intelligence":168,"Psyche":66,"Stamina":90},"Defense":{"Stab":null,"Cut":null,"Impact":null,"Penetration":null,"Shrapnel":null,"Burn":null,"Cold":null,"Acid":null,"Electric":null}},"Attacks":[],"Mob":{"Name":"Cosmic Horror","Links":{"$Url":"/mobs/147"}},"Links":{"$Url":"/mobmaturities/772"}},{"Id":773,"Name":"Dominant","Properties":{"Description":null,"Health":970,"AttacksPerMinute":null,"Level":39,"RegenerationInterval":null,"RegenerationAmount":null,"MissChance":null,"Taming":{"IsTameable":false,"TamingLevel":null},"Attributes":{"Strength":285,"Agility":49,"Intelligence":180,"Psyche":68,"Stamina":97},"Defense":{"Stab":null,"Cut":null,"Impact":null,"Penetration":null,"Shrapnel":null,"Burn":null,"Cold":null,"Acid":null,"Electric":null}},"Attacks":[],"Mob":{"Name":"Cosmic Horror","Links":{"$Url":"/mobs/147"}},"Links":{"$Url":"/mobmaturities/773"}},{"Id":774,"Name":"Alpha","Properties":{"Description":null,"Health":1050,"AttacksPerMinute":null,"Level":42,"RegenerationInterval":null,"RegenerationAmount":null,"MissChance":null,"Taming":{"IsTameable":false,"TamingLevel":null},"Attributes":{"Strength":301,"Agility":50,"Intelligence":194,"Psyche":70,"Stamina":105},"Defense":{"Stab":null,"Cut":null,"Impact":null,"Penetration":null,"Shrapnel":null,"Burn":null,"Cold":null,"Acid":null,"Electric":null}},"Attacks":[],"Mob":{"Name":"Cosmic Horror","Links":{"$Url":"/mobs/147"}},"Links":{"$Url":"/mobmaturities/774"}},{"Id":775,"Name":"Old Alpha","Properties":{"Description":null,"Health":1140,"AttacksPerMinute":null,"Level":45,"RegenerationInterval":null,"RegenerationAmount":null,"MissChance":null,"Taming":{"IsTameable":false,"TamingLevel":null},"Attributes":{"Strength":318,"Agility":51,"Intelligence":205,"Psyche":71,"Stamina":114},"Defense":{"Stab":null,"Cut":null,"Impact":null,"Penetration":null,"Shrapnel":null,"Burn":null,"Cold":null,"Acid":null,"Electric":null}},"Attacks":[],"Mob":{"Name":"Cosmic Horror","Links":{"$Url":"/mobs/147"}},"Links":{"$Url":"/mobmaturities/775"}},{"Id":776,"Name":"Prowler","Properties":{"Description":null,"Health":null,"AttacksPerMinute":null,"Level":54,"RegenerationInterval":null,"RegenerationAmount":null,"MissChance":null,"Taming":{"IsTameable":false,"TamingLevel":null},"Attributes":{"Strength":null,"Agility":null,"Intelligence":null,"Psyche":null,"Stamina":null},"Defense":{"Stab":null,"Cut":null,"Impact":null,"Penetration":null,"Shrapnel":null,"Burn":null,"Cold":null,"Acid":null,"Electric":null}},"Attacks":[],"Mob":{"Name":"Cosmic Horror","Links":{"$Url":"/mobs/147"}},"Links":{"$Url":"/mobmaturities/776"}},{"Id":777,"Name":"Stalker","Properties":{"Description":null,"Health":null,"AttacksPerMinute":null,"Level":51,"RegenerationInterval":null,"RegenerationAmount":null,"MissChance":null,"Taming":{"IsTameable":false,"TamingLevel":null},"Attributes":{"Strength":null,"Agility":null,"Intelligence":null,"Psyche":null,"Stamina":null},"Defense":{"Stab":null,"Cut":null,"Impact":null,"Penetration":null,"Shrapnel":null,"Burn":null,"Cold":null,"Acid":null,"Electric":null}},"Attacks":[],"Mob":{"Name":"Cosmic Horror","Links":{"$Url":"/mobs/147"}},"Links":{"$Url":"/mobmaturities/777"}},{"Id":778,"Name":"Young","Properties":{"Description":null,"Health":650,"AttacksPerMinute":null,"Level":28,"RegenerationInterval":null,"RegenerationAmount":null,"MissChance":null,"Taming":{"IsTameable":false,"TamingLevel":null},"Attributes":{"Strength":215,"Agility":45,"Intelligence":118,"Psyche":60,"Stamina":65},"Defense":{"Stab":null,"Cut":null,"Impact":null,"Penetration":null,"Shrapnel":null,"Burn":null,"Cold":null,"Acid":null,"Electric":null}},"Attacks":[],"Mob":{"Name":"Cosmic Horror","Links":{"$Url":"/mobs/147"}},"Links":{"$Url":"/mobmaturities/778"}}],"Spawns":[],"Loots":[{"Mob":{"Name":"Cosmic Horror","Planet":{"Name":"Space","Links":{"$Url":"/planets/17"}},"Links":{"$Url":"/mobs/147"}},"Maturity":{"Name":"Young","Links":{"$Url":"/mobmaturities/778"}},"Item":{"Name":"Adaptive Fire Rate Component","Properties":{"Type":"Material"},"Links":{"$Url":"/materials/24"}},"Frequency":"Common","LastVU":"17.18.1","IsEvent":false,"IsDropping":true},{"Mob":{"Name":"Cosmic Horror","Planet":{"Name":"Space","Links":{"$Url":"/planets/17"}},"Links":{"$Url":"/mobs/147"}},"Maturity":{"Name":"Mature","Links":{"$Url":"/mobmaturities/770"}},"Item":{"Name":"Advanced Leather Extractor","Properties":{"Type":"Material"},"Links":{"$Url":"/materials/38"}},"Frequency":"Common","LastVU":"17.20.1a","IsEvent":false,"IsDropping":true},{"Mob":{"Name":"Cosmic Horror","Planet":{"Name":"Space","Links":{"$Url":"/planets/17"}},"Links":{"$Url":"/mobs/147"}},"Maturity":{"Name":"Young","Links":{"$Url":"/mobmaturities/778"}},"Item":{"Name":"Advanced Wood Extractor","Properties":{"Type":"Material"},"Links":{"$Url":"/materials/55"}},"Frequency":"Uncommon","LastVU":"17.6","IsEvent":false,"IsDropping":true},{"Mob":{"Name":"Cosmic Horror","Planet":{"Name":"Space","Links":{"$Url":"/planets/17"}},"Links":{"$Url":"/mobs/147"}},"Maturity":{"Name":"Young","Links":{"$Url":"/mobmaturities/778"}},"Item":{"Name":"Animal Adrenal Oil","Properties":{"Type":"Material"},"Links":{"$Url":"/materials/115"}},"Frequency":"Often","LastVU":"17.23.2.a","IsEvent":false,"IsDropping":true},{"Mob":{"Name":"Cosmic Horror","Planet":{"Name":"Space","Links":{"$Url":"/planets/17"}},"Links":{"$Url":"/mobs/147"}},"Maturity":{"Name":"Young","Links":{"$Url":"/mobmaturities/778"}},"Item":{"Name":"Animal Eye Oil","Properties":{"Type":"Material"},"Links":{"$Url":"/materials/119"}},"Frequency":"Often","LastVU":"17.23.0","IsEvent":false,"IsDropping":true},{"Mob":{"Name":"Cosmic Horror","Planet":{"Name":"Space","Links":{"$Url":"/planets/17"}},"Links":{"$Url":"/mobs/147"}},"Maturity":{"Name":"Young","Links":{"$Url":"/mobmaturities/778"}},"Item":{"Name":"Animal Hide","Properties":{"Type":"Material"},"Links":{"$Url":"/materials/121"}},"Frequency":"Often","LastVU":"17.6","IsEvent":false,"IsDropping":true},{"Mob":{"Name":"Cosmic Horror","Planet":{"Name":"Space","Links":{"$Url":"/planets/17"}},"Links":{"$Url":"/mobs/147"}},"Maturity":{"Name":"Young","Links":{"$Url":"/mobmaturities/778"}},"Item":{"Name":"Animal Muscle Oil","Properties":{"Type":"Material"},"Links":{"$Url":"/materials/124"}},"Frequency":"Common","LastVU":"17.23.2.a","IsEvent":false,"IsDropping":true},{"Mob":{"Name":"Cosmic Horror","Planet":{"Name":"Space","Links":{"$Url":"/planets/17"}},"Links":{"$Url":"/mobs/147"}},"Maturity":{"Name":"Young","Links":{"$Url":"/mobmaturities/778"}},"Item":{"Name":"Animal Oil Residue","Properties":{"Type":"Material"},"Links":{"$Url":"/materials/125"}},"Frequency":"Common","LastVU":"17.23.2.a","IsEvent":false,"IsDropping":true},{"Mob":{"Name":"Cosmic Horror","Planet":{"Name":"Space","Links":{"$Url":"/planets/17"}},"Links":{"$Url":"/mobs/147"}},"Maturity":{"Name":"Young","Links":{"$Url":"/mobmaturities/778"}},"Item":{"Name":"Basic Mineral Extractor","Properties":{"Type":"Material"},"Links":{"$Url":"/materials/249"}},"Frequency":"Common","LastVU":"17.19.1","IsEvent":false,"IsDropping":true},{"Mob":{"Name":"Cosmic Horror","Planet":{"Name":"Space","Links":{"$Url":"/planets/17"}},"Links":{"$Url":"/mobs/147"}},"Maturity":{"Name":"Young","Links":{"$Url":"/mobmaturities/778"}},"Item":{"Name":"Bio ID Verification","Properties":{"Type":"Material"},"Links":{"$Url":"/materials/316"}},"Frequency":"Rare","LastVU":"17.6","IsEvent":false,"IsDropping":true},{"Mob":{"Name":"Cosmic Horror","Planet":{"Name":"Space","Links":{"$Url":"/planets/17"}},"Links":{"$Url":"/mobs/147"}},"Maturity":{"Name":"Mature","Links":{"$Url":"/mobmaturities/770"}},"Item":{"Name":"Blazar Fragment","Properties":{"Type":"Material"},"Links":{"$Url":"/materials/331"}},"Frequency":"Common","LastVU":"17.23.2.a","IsEvent":false,"IsDropping":true},{"Mob":{"Name":"Cosmic Horror","Planet":{"Name":"Space","Links":{"$Url":"/planets/17"}},"Links":{"$Url":"/mobs/147"}},"Maturity":{"Name":"Young","Links":{"$Url":"/mobmaturities/778"}},"Item":{"Name":"Generic Fuse","Properties":{"Type":"Material"},"Links":{"$Url":"/materials/912"}},"Frequency":"Uncommon","LastVU":"17.1.2","IsEvent":false,"IsDropping":true},{"Mob":{"Name":"Cosmic Horror","Planet":{"Name":"Space","Links":{"$Url":"/planets/17"}},"Links":{"$Url":"/mobs/147"}},"Maturity":{"Name":null,"Links":{"$Url":"/mobmaturities/null"}},"Item":{"Name":"Generic Transformer","Properties":{"Type":"Material"},"Links":{"$Url":"/materials/915"}},"Frequency":"Uncommon","LastVU":"12.1","IsEvent":false,"IsDropping":true},{"Mob":{"Name":"Cosmic Horror","Planet":{"Name":"Space","Links":{"$Url":"/planets/17"}},"Links":{"$Url":"/mobs/147"}},"Maturity":{"Name":"Young","Links":{"$Url":"/mobmaturities/778"}},"Item":{"Name":"Paint Can (Burgundy)","Properties":{"Type":"Material"},"Links":{"$Url":"/materials/1648"}},"Frequency":"Uncommon","LastVU":"17.1.2","IsEvent":false,"IsDropping":true},{"Mob":{"Name":"Cosmic Horror","Planet":{"Name":"Space","Links":{"$Url":"/planets/17"}},"Links":{"$Url":"/mobs/147"}},"Maturity":{"Name":"Young","Links":{"$Url":"/mobmaturities/778"}},"Item":{"Name":"Paint Can (Dark Lavender)","Properties":{"Type":"Material"},"Links":{"$Url":"/materials/1655"}},"Frequency":"Uncommon","LastVU":"17.18.1","IsEvent":false,"IsDropping":true},{"Mob":{"Name":"Cosmic Horror","Planet":{"Name":"Space","Links":{"$Url":"/planets/17"}},"Links":{"$Url":"/mobs/147"}},"Maturity":{"Name":"Young","Links":{"$Url":"/mobmaturities/778"}},"Item":{"Name":"Paint Can (Green)","Properties":{"Type":"Material"},"Links":{"$Url":"/materials/1662"}},"Frequency":"Common","LastVU":"17.23.2.a","IsEvent":false,"IsDropping":true},{"Mob":{"Name":"Cosmic Horror","Planet":{"Name":"Space","Links":{"$Url":"/planets/17"}},"Links":{"$Url":"/mobs/147"}},"Maturity":{"Name":"Young","Links":{"$Url":"/mobmaturities/778"}},"Item":{"Name":"Paint Can (Purple)","Properties":{"Type":"Material"},"Links":{"$Url":"/materials/1669"}},"Frequency":"Common","LastVU":"17.23.2.a","IsEvent":false,"IsDropping":true},{"Mob":{"Name":"Cosmic Horror","Planet":{"Name":"Space","Links":{"$Url":"/planets/17"}},"Links":{"$Url":"/mobs/147"}},"Maturity":{"Name":"Young","Links":{"$Url":"/mobmaturities/778"}},"Item":{"Name":"Paint Can (Umber)","Properties":{"Type":"Material"},"Links":{"$Url":"/materials/1674"}},"Frequency":"Common","LastVU":"17.23.2.a","IsEvent":false,"IsDropping":true},{"Mob":{"Name":"Cosmic Horror","Planet":{"Name":"Space","Links":{"$Url":"/planets/17"}},"Links":{"$Url":"/mobs/147"}},"Maturity":{"Name":null,"Links":{"$Url":"/mobmaturities/null"}},"Item":{"Name":"Rad Conveyor","Properties":{"Type":"Material"},"Links":{"$Url":"/materials/1828"}},"Frequency":"Uncommon","LastVU":"17.6.1","IsEvent":false,"IsDropping":true},{"Mob":{"Name":"Cosmic Horror","Planet":{"Name":"Space","Links":{"$Url":"/planets/17"}},"Links":{"$Url":"/mobs/147"}},"Maturity":{"Name":"Young","Links":{"$Url":"/mobmaturities/778"}},"Item":{"Name":"Socket 3 Component","Properties":{"Type":"Material"},"Links":{"$Url":"/materials/2183"}},"Frequency":"Often","LastVU":"17.18.1","IsEvent":false,"IsDropping":true},{"Mob":{"Name":"Cosmic Horror","Planet":{"Name":"Space","Links":{"$Url":"/planets/17"}},"Links":{"$Url":"/mobs/147"}},"Maturity":{"Name":"Young","Links":{"$Url":"/mobmaturities/778"}},"Item":{"Name":"Soft Hide","Properties":{"Type":"Material"},"Links":{"$Url":"/materials/2193"}},"Frequency":"Often","LastVU":"17.1.2","IsEvent":false,"IsDropping":true},{"Mob":{"Name":"Cosmic Horror","Planet":{"Name":"Space","Links":{"$Url":"/planets/17"}},"Links":{"$Url":"/mobs/147"}},"Maturity":{"Name":"Young","Links":{"$Url":"/mobmaturities/778"}},"Item":{"Name":"Strong Cloth Extractor","Properties":{"Type":"Material"},"Links":{"$Url":"/materials/2254"}},"Frequency":"Common","LastVU":"17.23.2.a","IsEvent":false,"IsDropping":true},{"Mob":{"Name":"Cosmic Horror","Planet":{"Name":"Space","Links":{"$Url":"/planets/17"}},"Links":{"$Url":"/mobs/147"}},"Maturity":{"Name":"Young","Links":{"$Url":"/mobmaturities/778"}},"Item":{"Name":"Surface Hardener Component","Properties":{"Type":"Material"},"Links":{"$Url":"/materials/2273"}},"Frequency":"Often","LastVU":"17.23.0","IsEvent":false,"IsDropping":true},{"Mob":{"Name":"Cosmic Horror","Planet":{"Name":"Space","Links":{"$Url":"/planets/17"}},"Links":{"$Url":"/mobs/147"}},"Maturity":{"Name":"Young","Links":{"$Url":"/mobmaturities/778"}},"Item":{"Name":"Thin Wool","Properties":{"Type":"Material"},"Links":{"$Url":"/materials/2347"}},"Frequency":"Often","LastVU":"17.18.1","IsEvent":false,"IsDropping":true},{"Mob":{"Name":"Cosmic Horror","Planet":{"Name":"Space","Links":{"$Url":"/planets/17"}},"Links":{"$Url":"/mobs/147"}},"Maturity":{"Name":"Old","Links":{"$Url":"/mobmaturities/769"}},"Item":{"Name":"Tier 3 Component","Properties":{"Type":"Material"},"Links":{"$Url":"/materials/2356"}},"Frequency":"Uncommon","LastVU":"17.6","IsEvent":false,"IsDropping":true},{"Mob":{"Name":"Cosmic Horror","Planet":{"Name":"Space","Links":{"$Url":"/planets/17"}},"Links":{"$Url":"/mobs/147"}},"Maturity":{"Name":"Old","Links":{"$Url":"/mobmaturities/769"}},"Item":{"Name":"Weak Cloth Extractor","Properties":{"Type":"Material"},"Links":{"$Url":"/materials/2496"}},"Frequency":"Common","LastVU":"17.6","IsEvent":false,"IsDropping":true},{"Mob":{"Name":"Cosmic Horror","Planet":{"Name":"Space","Links":{"$Url":"/planets/17"}},"Links":{"$Url":"/mobs/147"}},"Maturity":{"Name":"Young","Links":{"$Url":"/mobmaturities/778"}},"Item":{"Name":"Wool","Properties":{"Type":"Material"},"Links":{"$Url":"/materials/2533"}},"Frequency":"Often","LastVU":"17.6","IsEvent":false,"IsDropping":true},{"Mob":{"Name":"Cosmic Horror","Planet":{"Name":"Space","Links":{"$Url":"/planets/17"}},"Links":{"$Url":"/mobs/147"}},"Maturity":{"Name":"Young","Links":{"$Url":"/mobmaturities/778"}},"Item":{"Name":"Cryogenic Attack Chip 1 (L)","Properties":{"Type":"Weapon"},"Links":{"$Url":"/weapons/625"}},"Frequency":"Uncommon","LastVU":"17.1.2","IsEvent":false,"IsDropping":true},{"Mob":{"Name":"Cosmic Horror","Planet":{"Name":"Space","Links":{"$Url":"/planets/17"}},"Links":{"$Url":"/mobs/147"}},"Maturity":{"Name":"Young","Links":{"$Url":"/mobmaturities/778"}},"Item":{"Name":"Arsonistic Chip 1 (L)","Properties":{"Type":"Weapon"},"Links":{"$Url":"/weapons/217"}},"Frequency":"Uncommon","LastVU":"17.6","IsEvent":false,"IsDropping":true},{"Mob":{"Name":"Cosmic Horror","Planet":{"Name":"Space","Links":{"$Url":"/planets/17"}},"Links":{"$Url":"/mobs/147"}},"Maturity":{"Name":null,"Links":{"$Url":"/mobmaturities/null"}},"Item":{"Name":"Arsonistic Chip 2 (L)","Properties":{"Type":"Weapon"},"Links":{"$Url":"/weapons/218"}},"Frequency":"Uncommon","LastVU":"17.1.2","IsEvent":false,"IsDropping":true}],"Links":{"$Url":"/mobs/147"}}