{"Id":237,"Name":"Faucervix","Type":"Animal","Properties":{"Description":null,"AttackRange":null,"AggressionRange":null,"IsSweatable":true},"DefensiveProfession":{"Name":"Evader","Links":{"$Url":"/professions/42"}},"ScanningProfession":{"Name":"Animal Investigator","Links":{"$Url":"/professions/1"}},"Planet":{"Name":"Calypso","Links":{"$Url":"/planets/1"}},"Species":{"Name":"Faucervix","Properties":{"CodexBaseCost":10,"CodexType":"Mob"},"Links":{"$Url":"/mobspecies/44"}},"Maturities":[{"Id":1315,"Name":"Prowler","Properties":{"Description":null,"Health":460,"AttacksPerMinute":20,"Level":11,"RegenerationInterval":null,"RegenerationAmount":null,"MissChance":null,"Taming":{"IsTameable":false,"TamingLevel":null},"Attributes":{"Strength":83,"Agility":41,"Intelligence":19,"Psyche":3,"Stamina":46},"Defense":{"Stab":null,"Cut":null,"Impact":null,"Penetration":null,"Shrapnel":null,"Burn":null,"Cold":null,"Acid":null,"Electric":null}},"Attacks":[],"Mob":{"Name":"Faucervix","Links":{"$Url":"/mobs/237"}},"Links":{"$Url":"/mobmaturities/1315"}},{"Id":1316,"Name":"Old Alpha","Properties":{"Description":null,"Health":420,"AttacksPerMinute":20,"Level":10,"RegenerationInterval":null,"RegenerationAmount":null,"MissChance":null,"Taming":{"IsTameable":false,"TamingLevel":null},"Attributes":{"Strength":80,"Agility":40,"Intelligence":18,"Psyche":3,"Stamina":42},"Defense":{"Stab":null,"Cut":null,"Impact":null,"Penetration":null,"Shrapnel":null,"Burn":null,"Cold":null,"Acid":null,"Electric":null}},"Attacks":[],"Mob":{"Name":"Faucervix","Links":{"$Url":"/mobs/237"}},"Links":{"$Url":"/mobmaturities/1316"}},{"Id":1317,"Name":"Stalker","Properties":{"Description":null,"Health":520,"AttacksPerMinute":20,"Level":null,"RegenerationInterval":null,"RegenerationAmount":null,"MissChance":null,"Taming":{"IsTameable":false,"TamingLevel":null},"Attributes":{"Strength":83,"Agility":42,"Intelligence":20,"Psyche":3,"Stamina":52},"Defense":{"Stab":null,"Cut":null,"Impact":null,"Penetration":null,"Shrapnel":null,"Burn":null,"Cold":null,"Acid":null,"Electric":null}},"Attacks":[],"Mob":{"Name":"Faucervix","Links":{"$Url":"/mobs/237"}},"Links":{"$Url":"/mobmaturities/1317"}},{"Id":1318,"Name":"Young","Properties":{"Description":null,"Health":100,"AttacksPerMinute":20,"Level":5,"RegenerationInterval":null,"RegenerationAmount":null,"MissChance":null,"Taming":{"IsTameable":false,"TamingLevel":null},"Attributes":{"Strength":63,"Agility":35,"Intelligence":10,"Psyche":3,"Stamina":10},"Defense":{"Stab":null,"Cut":null,"Impact":null,"Penetration":null,"Shrapnel":null,"Burn":null,"Cold":null,"Acid":null,"Electric":null}},"Attacks":[],"Mob":{"Name":"Faucervix","Links":{"$Url":"/mobs/237"}},"Links":{"$Url":"/mobmaturities/1318"}},{"Id":1319,"Name":"Mature","Properties":{"Description":null,"Health":130,"AttacksPerMinute":20,"Level":5,"RegenerationInterval":null,"RegenerationAmount":null,"MissChance":null,"Taming":{"IsTameable":false,"TamingLevel":null},"Attributes":{"Strength":65,"Agility":35,"Intelligence":14,"Psyche":2,"Stamina":13},"Defense":{"Stab":null,"Cut":null,"Impact":null,"Penetration":null,"Shrapnel":null,"Burn":null,"Cold":null,"Acid":null,"Electric":null}},"Attacks":[],"Mob":{"Name":"Faucervix","Links":{"$Url":"/mobs/237"}},"Links":{"$Url":"/mobmaturities/1319"}},{"Id":1320,"Name":"Old","Properties":{"Description":null,"Health":170,"AttacksPerMinute":20,"Level":6,"RegenerationInterval":null,"RegenerationAmount":null,"MissChance":null,"Taming":{"IsTameable":false,"TamingLevel":null},"Attributes":{"Strength":50,"Agility":34,"Intelligence":15,"Psyche":3,"Stamina":17},"Defense":{"Stab":null,"Cut":null,"Impact":null,"Penetration":null,"Shrapnel":null,"Burn":null,"Cold":null,"Acid":null,"Electric":null}},"Attacks":[],"Mob":{"Name":"Faucervix","Links":{"$Url":"/mobs/237"}},"Links":{"$Url":"/mobmaturities/1320"}},{"Id":1321,"Name":"Provider","Properties":{"Description":null,"Health":230,"AttacksPerMinute":20,"Level":7,"RegenerationInterval":null,"RegenerationAmount":null,"MissChance":null,"Taming":{"IsTameable":false,"TamingLevel":null},"Attributes":{"Strength":63,"Agility":35,"Intelligence":16,"Psyche":2,"Stamina":23},"Defense":{"Stab":null,"Cut":null,"Impact":null,"Penetration":null,"Shrapnel":null,"Burn":null,"Cold":null,"Acid":null,"Electric":null}},"Attacks":[],"Mob":{"Name":"Faucervix","Links":{"$Url":"/mobs/237"}},"Links":{"$Url":"/mobmaturities/1321"}},{"Id":1322,"Name":"Guardian","Properties":{"Description":null,"Health":290,"AttacksPerMinute":20,"Level":8,"RegenerationInterval":null,"RegenerationAmount":null,"MissChance":null,"Taming":{"IsTameable":false,"TamingLevel":null},"Attributes":{"Strength":69,"Agility":35,"Intelligence":16,"Psyche":3,"Stamina":29},"Defense":{"Stab":null,"Cut":null,"Impact":null,"Penetration":null,"Shrapnel":null,"Burn":null,"Cold":null,"Acid":null,"Electric":null}},"Attacks":[],"Mob":{"Name":"Faucervix","Links":{"$Url":"/mobs/237"}},"Links":{"$Url":"/mobmaturities/1322"}},{"Id":1323,"Name":"Alpha","Properties":{"Description":null,"Health":360,"AttacksPerMinute":20,"Level":9,"RegenerationInterval":null,"RegenerationAmount":null,"MissChance":null,"Taming":{"IsTameable":false,"TamingLevel":null},"Attributes":{"Strength":70,"Agility":35,"Intelligence":17,"Psyche":10,"Stamina":36},"Defense":{"Stab":null,"Cut":null,"Impact":null,"Penetration":null,"Shrapnel":null,"Burn":null,"Cold":null,"Acid":null,"Electric":null}},"Attacks":[],"Mob":{"Name":"Faucervix","Links":{"$Url":"/mobs/237"}},"Links":{"$Url":"/mobmaturities/1323"}},{"Id":1324,"Name":"Dominant","Properties":{"Description":null,"Health":320,"AttacksPerMinute":20,"Level":8,"RegenerationInterval":null,"RegenerationAmount":null,"MissChance":null,"Taming":{"IsTameable":false,"TamingLevel":null},"Attributes":{"Strength":70,"Agility":36,"Intelligence":10,"Psyche":3,"Stamina":32},"Defense":{"Stab":null,"Cut":null,"Impact":null,"Penetration":null,"Shrapnel":null,"Burn":null,"Cold":null,"Acid":null,"Electric":null}},"Attacks":[],"Mob":{"Name":"Faucervix","Links":{"$Url":"/mobs/237"}},"Links":{"$Url":"/mobmaturities/1324"}}],"Spawns":[{"Id":2137,"Name":"Berycled - Mature/Old/Young, Faucervix - Mature/Old/Provider/Young, Prototype Drone - Gen 02/Gen 03/Gen 04/Gen 05","Properties":{"Description":null,"Density":3,"IsShared":false,"IsEvent":false,"Notes":"","Type":"MobArea","Shape":"Polygon","Data":{"vertices":[63159.66,78324,63327.3,78648,63638.61,78648,63674.54,78828,63566.77,79020,63638.61,79080,63878.09,79212,64045.72,79260,64237.3,79296,64321.12,79524,64309.14,79764,64440.86,79932,64716.25,79896,64764.15,79776,64764.15,79476,64907.83,79284,65015.6,79248,65482.57,79260,65470.6,78024,64955.73,77748,64991.65,78048,64835.99,78060,64752.17,77940,64536.65,78240,64572.57,78336,64297.17,78480,64045.72,78420,63925.98,78372,63902.04,78240,63650.59,78144,63542.82,78132,63303.35,78216,63159.66,78324]},"Coordinates":{"Longitude":64944,"Latitude":78719,"Altitude":150}},"Planet":{"Name":"Calypso","Properties":{"TechnicalName":"Calypso"},"Links":{"$Url":"/planets/1"}},"Maturities":[{"IsRare":false,"Maturity":{"Id":427,"Name":"Young","Properties":{"Description":null,"Health":70,"AttacksPerMinute":20,"Level":3,"RegenerationInterval":360,"RegenerationAmount":0.19,"MissChance":null,"Taming":{"IsTameable":false,"TamingLevel":null},"Attributes":{"Strength":20,"Agility":20,"Intelligence":10,"Psyche":10,"Stamina":7},"Defense":{"Stab":null,"Cut":null,"Impact":null,"Penetration":null,"Shrapnel":null,"Burn":null,"Cold":null,"Acid":null,"Electric":null}},"Attacks":[],"Mob":{"Name":"Berycled","Links":{"$Url":"/mobs/82"}},"Links":{"$Url":"/mobmaturities/427"}}},{"IsRare":false,"Maturity":{"Id":428,"Name":"Mature","Properties":{"Description":null,"Health":140,"AttacksPerMinute":20,"Level":4,"RegenerationInterval":null,"RegenerationAmount":null,"MissChance":null,"Taming":{"IsTameable":false,"TamingLevel":null},"Attributes":{"Strength":26,"Agility":28,"Intelligence":10,"Psyche":10,"Stamina":14},"Defense":{"Stab":null,"Cut":null,"Impact":null,"Penetration":null,"Shrapnel":null,"Burn":null,"Cold":null,"Acid":null,"Electric":null}},"Attacks":[],"Mob":{"Name":"Berycled","Links":{"$Url":"/mobs/82"}},"Links":{"$Url":"/mobmaturities/428"}}},{"IsRare":false,"Maturity":{"Id":429,"Name":"Old","Properties":{"Description":null,"Health":180,"AttacksPerMinute":20,"Level":5,"RegenerationInterval":null,"RegenerationAmount":null,"MissChance":null,"Taming":{"IsTameable":false,"TamingLevel":null},"Attributes":{"Strength":22,"Agility":22,"Intelligence":10,"Psyche":10,"Stamina":18},"Defense":{"Stab":null,"Cut":null,"Impact":null,"Penetration":null,"Shrapnel":null,"Burn":null,"Cold":null,"Acid":null,"Electric":null}},"Attacks":[],"Mob":{"Name":"Berycled","Links":{"$Url":"/mobs/82"}},"Links":{"$Url":"/mobmaturities/429"}}},{"IsRare":false,"Maturity":{"Id":1318,"Name":"Young","Properties":{"Description":null,"Health":100,"AttacksPerMinute":20,"Level":5,"RegenerationInterval":null,"RegenerationAmount":null,"MissChance":null,"Taming":{"IsTameable":false,"TamingLevel":null},"Attributes":{"Strength":63,"Agility":35,"Intelligence":10,"Psyche":3,"Stamina":10},"Defense":{"Stab":null,"Cut":null,"Impact":null,"Penetration":null,"Shrapnel":null,"Burn":null,"Cold":null,"Acid":null,"Electric":null}},"Attacks":[],"Mob":{"Name":"Faucervix","Links":{"$Url":"/mobs/237"}},"Links":{"$Url":"/mobmaturities/1318"}}},{"IsRare":false,"Maturity":{"Id":1319,"Name":"Mature","Properties":{"Description":null,"Health":130,"AttacksPerMinute":20,"Level":5,"RegenerationInterval":null,"RegenerationAmount":null,"MissChance":null,"Taming":{"IsTameable":false,"TamingLevel":null},"Attributes":{"Strength":65,"Agility":35,"Intelligence":14,"Psyche":2,"Stamina":13},"Defense":{"Stab":null,"Cut":null,"Impact":null,"Penetration":null,"Shrapnel":null,"Burn":null,"Cold":null,"Acid":null,"Electric":null}},"Attacks":[],"Mob":{"Name":"Faucervix","Links":{"$Url":"/mobs/237"}},"Links":{"$Url":"/mobmaturities/1319"}}},{"IsRare":false,"Maturity":{"Id":1320,"Name":"Old","Properties":{"Description":null,"Health":170,"AttacksPerMinute":20,"Level":6,"RegenerationInterval":null,"RegenerationAmount":null,"MissChance":null,"Taming":{"IsTameable":false,"TamingLevel":null},"Attributes":{"Strength":50,"Agility":34,"Intelligence":15,"Psyche":3,"Stamina":17},"Defense":{"Stab":null,"Cut":null,"Impact":null,"Penetration":null,"Shrapnel":null,"Burn":null,"Cold":null,"Acid":null,"Electric":null}},"Attacks":[],"Mob":{"Name":"Faucervix","Links":{"$Url":"/mobs/237"}},"Links":{"$Url":"/mobmaturities/1320"}}},{"IsRare":false,"Maturity":{"Id":1321,"Name":"Provider","Properties":{"Description":null,"Health":230,"AttacksPerMinute":20,"Level":7,"RegenerationInterval":null,"RegenerationAmount":null,"MissChance":null,"Taming":{"IsTameable":false,"TamingLevel":null},"Attributes":{"Strength":63,"Agility":35,"Intelligence":16,"Psyche":2,"Stamina":23},"Defense":{"Stab":null,"Cut":null,"Impact":null,"Penetration":null,"Shrapnel":null,"Burn":null,"Cold":null,"Acid":null,"Electric":null}},"Attacks":[],"Mob":{"Name":"Faucervix","Links":{"$Url":"/mobs/237"}},"Links":{"$Url":"/mobmaturities/1321"}}},{"IsRare":false,"Maturity":{"Id":3175,"Name":"Gen 02","Properties":{"Description":null,"Health":30,"AttacksPerMinute":null,"Level":2,"RegenerationInterval":null,"RegenerationAmount":null,"MissChance":null,"Taming":{"IsTameable":false,"TamingLevel":null},"Attributes":{"Strength":5,"Agility":5,"Intelligence":5,"Psyche":5,"Stamina":3},"Defense":{"Stab":null,"Cut":null,"Impact":null,"Penetration":null,"Shrapnel":null,"Burn":null,"Cold":null,"Acid":null,"Electric":null}},"Attacks":[],"Mob":{"Name":"Prototype Drone","Links":{"$Url":"/mobs/519"}},"Links":{"$Url":"/mobmaturities/3175"}}},{"IsRare":false,"Maturity":{"Id":3176,"Name":"Gen 04","Properties":{"Description":null,"Health":50,"AttacksPerMinute":null,"Level":2,"RegenerationInterval":null,"RegenerationAmount":null,"MissChance":null,"Taming":{"IsTameable":false,"TamingLevel":null},"Attributes":{"Strength":5,"Agility":5,"Intelligence":5,"Psyche":5,"Stamina":5},"Defense":{"Stab":null,"Cut":null,"Impact":null,"Penetration":null,"Shrapnel":null,"Burn":null,"Cold":null,"Acid":null,"Electric":null}},"Attacks":[],"Mob":{"Name":"Prototype Drone","Links":{"$Url":"/mobs/519"}},"Links":{"$Url":"/mobmaturities/3176"}}},{"IsRare":false,"Maturity":{"Id":3177,"Name":"Gen 05","Properties":{"Description":null,"Health":70,"AttacksPerMinute":null,"Level":3,"RegenerationInterval":null,"RegenerationAmount":null,"MissChance":null,"Taming":{"IsTameable":false,"TamingLevel":null},"Attributes":{"Strength":5,"Agility":5,"Intelligence":5,"Psyche":5,"Stamina":7},"Defense":{"Stab":null,"Cut":null,"Impact":null,"Penetration":null,"Shrapnel":null,"Burn":null,"Cold":null,"Acid":null,"Electric":null}},"Attacks":[],"Mob":{"Name":"Prototype Drone","Links":{"$Url":"/mobs/519"}},"Links":{"$Url":"/mobmaturities/3177"}}},{"IsRare":false,"Maturity":{"Id":3180,"Name":"Gen 03","Properties":{"Description":null,"Health":40,"AttacksPerMinute":null,"Level":2,"RegenerationInterval":null,"RegenerationAmount":null,"MissChance":null,"Taming":{"IsTameable":false,"TamingLevel":null},"Attributes":{"Strength":5,"Agility":5,"Intelligence":5,"Psyche":5,"Stamina":4},"Defense":{"Stab":null,"Cut":null,"Impact":null,"Penetration":null,"Shrapnel":null,"Burn":null,"Cold":null,"Acid":null,"Electric":null}},"Attacks":[],"Mob":{"Name":"Prototype Drone","Links":{"$Url":"/mobs/519"}},"Links":{"$Url":"/mobmaturities/3180"}}}],"Links":{"$Url":"/mobspawns/2137"}},{"Id":2841,"Name":"Exarosaur (Calypso) - Dominant/Guardian/Mature/Old/Provider/Young, Faucervix - Mature/Old/Provider/Young","Properties":{"Description":null,"Density":3,"IsShared":false,"IsEvent":false,"Notes":"","Type":"MobArea","Shape":"Polygon","Data":{"vertices":[73965.97,74712,74253.34,74712,74373.08,74616,74420.98,74676,74768.21,74676,74768.21,73836,73822.29,73836,73954,74052,73870.18,74184,73954,74412,73918.08,74664,73965.97,74712]},"Coordinates":{"Longitude":74305,"Latitude":74229,"Altitude":150}},"Planet":{"Name":"Calypso","Properties":{"TechnicalName":"Calypso"},"Links":{"$Url":"/planets/1"}},"Maturities":[{"IsRare":false,"Maturity":{"Id":1281,"Name":"Young","Properties":{"Description":null,"Health":50,"AttacksPerMinute":20,"Level":3,"RegenerationInterval":520,"RegenerationAmount":0.1,"MissChance":null,"Taming":{"IsTameable":true,"TamingLevel":2.5},"Attributes":{"Strength":39,"Agility":15,"Intelligence":2,"Psyche":2,"Stamina":5},"Defense":{"Stab":null,"Cut":null,"Impact":null,"Penetration":null,"Shrapnel":null,"Burn":null,"Cold":null,"Acid":null,"Electric":null}},"Attacks":[],"Mob":{"Name":"Exarosaur (Calypso)","Links":{"$Url":"/mobs/226"}},"Links":{"$Url":"/mobmaturities/1281"}}},{"IsRare":false,"Maturity":{"Id":1282,"Name":"Mature","Properties":{"Description":null,"Health":60,"AttacksPerMinute":20,"Level":3,"RegenerationInterval":620,"RegenerationAmount":0.1,"MissChance":null,"Taming":{"IsTameable":true,"TamingLevel":3},"Attributes":{"Strength":36,"Agility":15,"Intelligence":2,"Psyche":2,"Stamina":6},"Defense":{"Stab":null,"Cut":null,"Impact":null,"Penetration":null,"Shrapnel":null,"Burn":null,"Cold":null,"Acid":null,"Electric":null}},"Attacks":[],"Mob":{"Name":"Exarosaur (Calypso)","Links":{"$Url":"/mobs/226"}},"Links":{"$Url":"/mobmaturities/1282"}}},{"IsRare":false,"Maturity":{"Id":1283,"Name":"Old","Properties":{"Description":null,"Health":70,"AttacksPerMinute":20,"Level":3,"RegenerationInterval":360,"RegenerationAmount":0.19,"MissChance":null,"Taming":{"IsTameable":true,"TamingLevel":3.5},"Attributes":{"Strength":40,"Agility":16,"Intelligence":2,"Psyche":2,"Stamina":7},"Defense":{"Stab":null,"Cut":null,"Impact":null,"Penetration":null,"Shrapnel":null,"Burn":null,"Cold":null,"Acid":null,"Electric":null}},"Attacks":[],"Mob":{"Name":"Exarosaur (Calypso)","Links":{"$Url":"/mobs/226"}},"Links":{"$Url":"/mobmaturities/1283"}}},{"IsRare":false,"Maturity":{"Id":1284,"Name":"Provider","Properties":{"Description":null,"Health":120,"AttacksPerMinute":20,"Level":4,"RegenerationInterval":360,"RegenerationAmount":0.33,"MissChance":null,"Taming":{"IsTameable":true,"TamingLevel":4},"Attributes":{"Strength":39,"Agility":15,"Intelligence":2,"Psyche":2,"Stamina":12},"Defense":{"Stab":null,"Cut":null,"Impact":null,"Penetration":null,"Shrapnel":null,"Burn":null,"Cold":null,"Acid":null,"Electric":null}},"Attacks":[],"Mob":{"Name":"Exarosaur (Calypso)","Links":{"$Url":"/mobs/226"}},"Links":{"$Url":"/mobmaturities/1284"}}},{"IsRare":false,"Maturity":{"Id":1285,"Name":"Guardian","Properties":{"Description":null,"Health":140,"AttacksPerMinute":20,"Level":4,"RegenerationInterval":480,"RegenerationAmount":0.29,"MissChance":null,"Taming":{"IsTameable":true,"TamingLevel":4.5},"Attributes":{"Strength":39,"Agility":19,"Intelligence":2,"Psyche":2,"Stamina":14},"Defense":{"Stab":null,"Cut":null,"Impact":null,"Penetration":null,"Shrapnel":null,"Burn":null,"Cold":null,"Acid":null,"Electric":null}},"Attacks":[],"Mob":{"Name":"Exarosaur (Calypso)","Links":{"$Url":"/mobs/226"}},"Links":{"$Url":"/mobmaturities/1285"}}},{"IsRare":false,"Maturity":{"Id":1286,"Name":"Dominant","Properties":{"Description":null,"Health":160,"AttacksPerMinute":20,"Level":5,"RegenerationInterval":420,"RegenerationAmount":0.38,"MissChance":null,"Taming":{"IsTameable":true,"TamingLevel":5},"Attributes":{"Strength":39,"Agility":10,"Intelligence":2,"Psyche":2,"Stamina":16},"Defense":{"Stab":null,"Cut":null,"Impact":null,"Penetration":null,"Shrapnel":null,"Burn":null,"Cold":null,"Acid":null,"Electric":null}},"Attacks":[],"Mob":{"Name":"Exarosaur (Calypso)","Links":{"$Url":"/mobs/226"}},"Links":{"$Url":"/mobmaturities/1286"}}},{"IsRare":false,"Maturity":{"Id":1318,"Name":"Young","Properties":{"Description":null,"Health":100,"AttacksPerMinute":20,"Level":5,"RegenerationInterval":null,"RegenerationAmount":null,"MissChance":null,"Taming":{"IsTameable":false,"TamingLevel":null},"Attributes":{"Strength":63,"Agility":35,"Intelligence":10,"Psyche":3,"Stamina":10},"Defense":{"Stab":null,"Cut":null,"Impact":null,"Penetration":null,"Shrapnel":null,"Burn":null,"Cold":null,"Acid":null,"Electric":null}},"Attacks":[],"Mob":{"Name":"Faucervix","Links":{"$Url":"/mobs/237"}},"Links":{"$Url":"/mobmaturities/1318"}}},{"IsRare":false,"Maturity":{"Id":1319,"Name":"Mature","Properties":{"Description":null,"Health":130,"AttacksPerMinute":20,"Level":5,"RegenerationInterval":null,"RegenerationAmount":null,"MissChance":null,"Taming":{"IsTameable":false,"TamingLevel":null},"Attributes":{"Strength":65,"Agility":35,"Intelligence":14,"Psyche":2,"Stamina":13},"Defense":{"Stab":null,"Cut":null,"Impact":null,"Penetration":null,"Shrapnel":null,"Burn":null,"Cold":null,"Acid":null,"Electric":null}},"Attacks":[],"Mob":{"Name":"Faucervix","Links":{"$Url":"/mobs/237"}},"Links":{"$Url":"/mobmaturities/1319"}}},{"IsRare":false,"Maturity":{"Id":1320,"Name":"Old","Properties":{"Description":null,"Health":170,"AttacksPerMinute":20,"Level":6,"RegenerationInterval":null,"RegenerationAmount":null,"MissChance":null,"Taming":{"IsTameable":false,"TamingLevel":null},"Attributes":{"Strength":50,"Agility":34,"Intelligence":15,"Psyche":3,"Stamina":17},"Defense":{"Stab":null,"Cut":null,"Impact":null,"Penetration":null,"Shrapnel":null,"Burn":null,"Cold":null,"Acid":null,"Electric":null}},"Attacks":[],"Mob":{"Name":"Faucervix","Links":{"$Url":"/mobs/237"}},"Links":{"$Url":"/mobmaturities/1320"}}},{"IsRare":false,"Maturity":{"Id":1321,"Name":"Provider","Properties":{"Description":null,"Health":230,"AttacksPerMinute":20,"Level":7,"RegenerationInterval":null,"RegenerationAmount":null,"MissChance":null,"Taming":{"IsTameable":false,"TamingLevel":null},"Attributes":{"Strength":63,"Agility":35,"Intelligence":16,"Psyche":2,"Stamina":23},"Defense":{"Stab":null,"Cut":null,"Impact":null,"Penetration":null,"Shrapnel":null,"Burn":null,"Cold":null,"Acid":null,"Electric":null}},"Attacks":[],"Mob":{"Name":"Faucervix","Links":{"$Url":"/mobs/237"}},"Links":{"$Url":"/mobmaturities/1321"}}}],"Links":{"$Url":"/mobspawns/2841"}},{"Id":2855,"Name":"Faucervix - Mature/Old/Provider/Young","Properties":{"Description":null,"Density":3,"IsShared":false,"IsEvent":false,"Notes":"","Type":"MobArea","Shape":"Polygon","Data":{"vertices":[64740.2,80220,64907.83,80316,65554.41,80316,65554.57,79320,64943.75,79308,64847.96,79464,64871.91,79824,64752.17,80028,64752.17,80208,64740.2,80220]},"Coordinates":{"Longitude":65199,"Latitude":79961,"Altitude":150}},"Planet":{"Name":"Calypso","Properties":{"TechnicalName":"Calypso"},"Links":{"$Url":"/planets/1"}},"Maturities":[{"IsRare":false,"Maturity":{"Id":1318,"Name":"Young","Properties":{"Description":null,"Health":100,"AttacksPerMinute":20,"Level":5,"RegenerationInterval":null,"RegenerationAmount":null,"MissChance":null,"Taming":{"IsTameable":false,"TamingLevel":null},"Attributes":{"Strength":63,"Agility":35,"Intelligence":10,"Psyche":3,"Stamina":10},"Defense":{"Stab":null,"Cut":null,"Impact":null,"Penetration":null,"Shrapnel":null,"Burn":null,"Cold":null,"Acid":null,"Electric":null}},"Attacks":[],"Mob":{"Name":"Faucervix","Links":{"$Url":"/mobs/237"}},"Links":{"$Url":"/mobmaturities/1318"}}},{"IsRare":false,"Maturity":{"Id":1319,"Name":"Mature","Properties":{"Description":null,"Health":130,"AttacksPerMinute":20,"Level":5,"RegenerationInterval":null,"RegenerationAmount":null,"MissChance":null,"Taming":{"IsTameable":false,"TamingLevel":null},"Attributes":{"Strength":65,"Agility":35,"Intelligence":14,"Psyche":2,"Stamina":13},"Defense":{"Stab":null,"Cut":null,"Impact":null,"Penetration":null,"Shrapnel":null,"Burn":null,"Cold":null,"Acid":null,"Electric":null}},"Attacks":[],"Mob":{"Name":"Faucervix","Links":{"$Url":"/mobs/237"}},"Links":{"$Url":"/mobmaturities/1319"}}},{"IsRare":false,"Maturity":{"Id":1320,"Name":"Old","Properties":{"Description":null,"Health":170,"AttacksPerMinute":20,"Level":6,"RegenerationInterval":null,"RegenerationAmount":null,"MissChance":null,"Taming":{"IsTameable":false,"TamingLevel":null},"Attributes":{"Strength":50,"Agility":34,"Intelligence":15,"Psyche":3,"Stamina":17},"Defense":{"Stab":null,"Cut":null,"Impact":null,"Penetration":null,"Shrapnel":null,"Burn":null,"Cold":null,"Acid":null,"Electric":null}},"Attacks":[],"Mob":{"Name":"Faucervix","Links":{"$Url":"/mobs/237"}},"Links":{"$Url":"/mobmaturities/1320"}}},{"IsRare":false,"Maturity":{"Id":1321,"Name":"Provider","Properties":{"Description":null,"Health":230,"AttacksPerMinute":20,"Level":7,"RegenerationInterval":null,"RegenerationAmount":null,"MissChance":null,"Taming":{"IsTameable":false,"TamingLevel":null},"Attributes":{"Strength":63,"Agility":35,"Intelligence":16,"Psyche":2,"Stamina":23},"Defense":{"Stab":null,"Cut":null,"Impact":null,"Penetration":null,"Shrapnel":null,"Burn":null,"Cold":null,"Acid":null,"Electric":null}},"Attacks":[],"Mob":{"Name":"Faucervix","Links":{"$Url":"/mobs/237"}},"Links":{"$Url":"/mobmaturities/1321"}}}],"Links":{"$Url":"/mobspawns/2855"}},{"Id":2856,"Name":"Faucervix - Mature/Old/Provider/Young","Properties":{"Description":null,"Density":3,"IsShared":false,"IsEvent":false,"Notes":"","Type":"MobArea","Shape":"Polygon","Data":{"vertices":[69864.19,68941.98,69912.08,69028.38,70065.35,69028.38,70247.35,68961.18,70630.51,68807.58,70525.14,68730.78,70630.51,68721.18,70659.24,68653.98,70410.19,68596.38,70314.4,68596.38,70266.51,68740.38,70228.19,68788.38,70209.03,68884.38,70122.82,68922.78,70103.66,68817.18,70103.66,68673.18,69959.98,68730.78,69873.77,68845.98,69864.19,68941.98]},"Coordinates":{"Longitude":70398,"Latitude":68760,"Altitude":150}},"Planet":{"Name":"Calypso","Properties":{"TechnicalName":"Calypso"},"Links":{"$Url":"/planets/1"}},"Maturities":[{"IsRare":false,"Maturity":{"Id":1318,"Name":"Young","Properties":{"Description":null,"Health":100,"AttacksPerMinute":20,"Level":5,"RegenerationInterval":null,"RegenerationAmount":null,"MissChance":null,"Taming":{"IsTameable":false,"TamingLevel":null},"Attributes":{"Strength":63,"Agility":35,"Intelligence":10,"Psyche":3,"Stamina":10},"Defense":{"Stab":null,"Cut":null,"Impact":null,"Penetration":null,"Shrapnel":null,"Burn":null,"Cold":null,"Acid":null,"Electric":null}},"Attacks":[],"Mob":{"Name":"Faucervix","Links":{"$Url":"/mobs/237"}},"Links":{"$Url":"/mobmaturities/1318"}}},{"IsRare":false,"Maturity":{"Id":1319,"Name":"Mature","Properties":{"Description":null,"Health":130,"AttacksPerMinute":20,"Level":5,"RegenerationInterval":null,"RegenerationAmount":null,"MissChance":null,"Taming":{"IsTameable":false,"TamingLevel":null},"Attributes":{"Strength":65,"Agility":35,"Intelligence":14,"Psyche":2,"Stamina":13},"Defense":{"Stab":null,"Cut":null,"Impact":null,"Penetration":null,"Shrapnel":null,"Burn":null,"Cold":null,"Acid":null,"Electric":null}},"Attacks":[],"Mob":{"Name":"Faucervix","Links":{"$Url":"/mobs/237"}},"Links":{"$Url":"/mobmaturities/1319"}}},{"IsRare":false,"Maturity":{"Id":1320,"Name":"Old","Properties":{"Description":null,"Health":170,"AttacksPerMinute":20,"Level":6,"RegenerationInterval":null,"RegenerationAmount":null,"MissChance":null,"Taming":{"IsTameable":false,"TamingLevel":null},"Attributes":{"Strength":50,"Agility":34,"Intelligence":15,"Psyche":3,"Stamina":17},"Defense":{"Stab":null,"Cut":null,"Impact":null,"Penetration":null,"Shrapnel":null,"Burn":null,"Cold":null,"Acid":null,"Electric":null}},"Attacks":[],"Mob":{"Name":"Faucervix","Links":{"$Url":"/mobs/237"}},"Links":{"$Url":"/mobmaturities/1320"}}},{"IsRare":false,"Maturity":{"Id":1321,"Name":"Provider","Properties":{"Description":null,"Health":230,"AttacksPerMinute":20,"Level":7,"RegenerationInterval":null,"RegenerationAmount":null,"MissChance":null,"Taming":{"IsTameable":false,"TamingLevel":null},"Attributes":{"Strength":63,"Agility":35,"Intelligence":16,"Psyche":2,"Stamina":23},"Defense":{"Stab":null,"Cut":null,"Impact":null,"Penetration":null,"Shrapnel":null,"Burn":null,"Cold":null,"Acid":null,"Electric":null}},"Attacks":[],"Mob":{"Name":"Faucervix","Links":{"$Url":"/mobs/237"}},"Links":{"$Url":"/mobmaturities/1321"}}}],"Links":{"$Url":"/mobspawns/2856"}},{"Id":2857,"Name":"Faucervix - Dominant/Guardian/Provider, Molisk - Adult/Gatherer/Scout/Young","Properties":{"Description":null,"Density":3,"IsShared":false,"IsEvent":false,"Notes":"","Type":"MobArea","Shape":"Polygon","Data":{"vertices":[57520.03,84024,57998.98,83904,58681.48,83760,58777.27,83904,58645.56,84096,58322.27,84216,58010.95,84264,57723.58,84300,57496.08,84168,57520.03,84024]},"Coordinates":{"Longitude":58275,"Latitude":84035,"Altitude":150}},"Planet":{"Name":"Calypso","Properties":{"TechnicalName":"Calypso"},"Links":{"$Url":"/planets/1"}},"Maturities":[{"IsRare":false,"Maturity":{"Id":1321,"Name":"Provider","Properties":{"Description":null,"Health":230,"AttacksPerMinute":20,"Level":7,"RegenerationInterval":null,"RegenerationAmount":null,"MissChance":null,"Taming":{"IsTameable":false,"TamingLevel":null},"Attributes":{"Strength":63,"Agility":35,"Intelligence":16,"Psyche":2,"Stamina":23},"Defense":{"Stab":null,"Cut":null,"Impact":null,"Penetration":null,"Shrapnel":null,"Burn":null,"Cold":null,"Acid":null,"Electric":null}},"Attacks":[],"Mob":{"Name":"Faucervix","Links":{"$Url":"/mobs/237"}},"Links":{"$Url":"/mobmaturities/1321"}}},{"IsRare":false,"Maturity":{"Id":1322,"Name":"Guardian","Properties":{"Description":null,"Health":290,"AttacksPerMinute":20,"Level":8,"RegenerationInterval":null,"RegenerationAmount":null,"MissChance":null,"Taming":{"IsTameable":false,"TamingLevel":null},"Attributes":{"Strength":69,"Agility":35,"Intelligence":16,"Psyche":3,"Stamina":29},"Defense":{"Stab":null,"Cut":null,"Impact":null,"Penetration":null,"Shrapnel":null,"Burn":null,"Cold":null,"Acid":null,"Electric":null}},"Attacks":[],"Mob":{"Name":"Faucervix","Links":{"$Url":"/mobs/237"}},"Links":{"$Url":"/mobmaturities/1322"}}},{"IsRare":false,"Maturity":{"Id":1324,"Name":"Dominant","Properties":{"Description":null,"Health":320,"AttacksPerMinute":20,"Level":8,"RegenerationInterval":null,"RegenerationAmount":null,"MissChance":null,"Taming":{"IsTameable":false,"TamingLevel":null},"Attributes":{"Strength":70,"Agility":36,"Intelligence":10,"Psyche":3,"Stamina":32},"Defense":{"Stab":null,"Cut":null,"Impact":null,"Penetration":null,"Shrapnel":null,"Burn":null,"Cold":null,"Acid":null,"Electric":null}},"Attacks":[],"Mob":{"Name":"Faucervix","Links":{"$Url":"/mobs/237"}},"Links":{"$Url":"/mobmaturities/1324"}}},{"IsRare":false,"Maturity":{"Id":2434,"Name":"Young","Properties":{"Description":null,"Health":160,"AttacksPerMinute":20,"Level":7,"RegenerationInterval":100,"RegenerationAmount":1.6,"MissChance":null,"Taming":{"IsTameable":false,"TamingLevel":null},"Attributes":{"Strength":35,"Agility":29,"Intelligence":12,"Psyche":6,"Stamina":16},"Defense":{"Stab":null,"Cut":null,"Impact":null,"Penetration":null,"Shrapnel":null,"Burn":null,"Cold":null,"Acid":null,"Electric":null}},"Attacks":[],"Mob":{"Name":"Molisk","Links":{"$Url":"/mobs/420"}},"Links":{"$Url":"/mobmaturities/2434"}}},{"IsRare":false,"Maturity":{"Id":2435,"Name":"Adult","Properties":{"Description":null,"Health":230,"AttacksPerMinute":20,"Level":9,"RegenerationInterval":100,"RegenerationAmount":2.3,"MissChance":null,"Taming":{"IsTameable":false,"TamingLevel":null},"Attributes":{"Strength":37,"Agility":30,"Intelligence":13,"Psyche":8,"Stamina":23},"Defense":{"Stab":null,"Cut":null,"Impact":null,"Penetration":null,"Shrapnel":null,"Burn":null,"Cold":null,"Acid":null,"Electric":null}},"Attacks":[],"Mob":{"Name":"Molisk","Links":{"$Url":"/mobs/420"}},"Links":{"$Url":"/mobmaturities/2435"}}},{"IsRare":false,"Maturity":{"Id":2436,"Name":"Scout","Properties":{"Description":null,"Health":280,"AttacksPerMinute":20,"Level":12,"RegenerationInterval":100,"RegenerationAmount":2.8,"MissChance":null,"Taming":{"IsTameable":false,"TamingLevel":null},"Attributes":{"Strength":40,"Agility":30,"Intelligence":15,"Psyche":8,"Stamina":28},"Defense":{"Stab":null,"Cut":null,"Impact":null,"Penetration":null,"Shrapnel":null,"Burn":null,"Cold":null,"Acid":null,"Electric":null}},"Attacks":[],"Mob":{"Name":"Molisk","Links":{"$Url":"/mobs/420"}},"Links":{"$Url":"/mobmaturities/2436"}}},{"IsRare":false,"Maturity":{"Id":2437,"Name":"Gatherer","Properties":{"Description":null,"Health":360,"AttacksPerMinute":20,"Level":14,"RegenerationInterval":100,"RegenerationAmount":3.6,"MissChance":null,"Taming":{"IsTameable":false,"TamingLevel":null},"Attributes":{"Strength":40,"Agility":33,"Intelligence":15,"Psyche":9,"Stamina":36},"Defense":{"Stab":null,"Cut":null,"Impact":null,"Penetration":null,"Shrapnel":null,"Burn":null,"Cold":null,"Acid":null,"Electric":null}},"Attacks":[],"Mob":{"Name":"Molisk","Links":{"$Url":"/mobs/420"}},"Links":{"$Url":"/mobmaturities/2437"}}}],"Links":{"$Url":"/mobspawns/2857"}},{"Id":2912,"Name":"Gokibusagi - Young, Atrax - Mature/Young, Berycled - Dominant/Guardian/Old/Provider, Faucervix - Mature/Old/Provider/Young, Molisk - Adult/Scout/Young","Properties":{"Description":null,"Density":3,"IsShared":false,"IsEvent":false,"Notes":"","Type":"MobArea","Shape":"Polygon","Data":{"vertices":[81898.58,87204,82796.61,87180,83099.13,86885.65,83290.71,86490.35,83263.59,86124,83395.3,85716,83443.2,84972,83395.3,84576,83263.59,84348,83131.88,84504,82856.48,84624,81898.58,84612,81898.58,87204]},"Coordinates":{"Longitude":82657,"Latitude":85381,"Altitude":150}},"Planet":{"Name":"Calypso","Properties":{"TechnicalName":"Calypso"},"Links":{"$Url":"/planets/1"}},"Maturities":[{"IsRare":false,"Maturity":{"Id":238,"Name":"Young","Properties":{"Description":null,"Health":270,"AttacksPerMinute":null,"Level":9,"RegenerationInterval":960,"RegenerationAmount":0.28,"MissChance":null,"Taming":{"IsTameable":false,"TamingLevel":null},"Attributes":{"Strength":40,"Agility":35,"Intelligence":10,"Psyche":10,"Stamina":27},"Defense":{"Stab":null,"Cut":null,"Impact":null,"Penetration":null,"Shrapnel":null,"Burn":null,"Cold":null,"Acid":null,"Electric":null}},"Attacks":[],"Mob":{"Name":"Atrax","Links":{"$Url":"/mobs/56"}},"Links":{"$Url":"/mobmaturities/238"}}},{"IsRare":false,"Maturity":{"Id":239,"Name":"Mature","Properties":{"Description":null,"Health":330,"AttacksPerMinute":null,"Level":10,"RegenerationInterval":717,"RegenerationAmount":0.46,"MissChance":null,"Taming":{"IsTameable":false,"TamingLevel":null},"Attributes":{"Strength":100,"Agility":110,"Intelligence":18,"Psyche":6,"Stamina":33},"Defense":{"Stab":null,"Cut":null,"Impact":null,"Penetration":null,"Shrapnel":null,"Burn":null,"Cold":null,"Acid":null,"Electric":null}},"Attacks":[],"Mob":{"Name":"Atrax","Links":{"$Url":"/mobs/56"}},"Links":{"$Url":"/mobmaturities/239"}}},{"IsRare":false,"Maturity":{"Id":429,"Name":"Old","Properties":{"Description":null,"Health":180,"AttacksPerMinute":20,"Level":5,"RegenerationInterval":null,"RegenerationAmount":null,"MissChance":null,"Taming":{"IsTameable":false,"TamingLevel":null},"Attributes":{"Strength":22,"Agility":22,"Intelligence":10,"Psyche":10,"Stamina":18},"Defense":{"Stab":null,"Cut":null,"Impact":null,"Penetration":null,"Shrapnel":null,"Burn":null,"Cold":null,"Acid":null,"Electric":null}},"Attacks":[],"Mob":{"Name":"Berycled","Links":{"$Url":"/mobs/82"}},"Links":{"$Url":"/mobmaturities/429"}}},{"IsRare":false,"Maturity":{"Id":430,"Name":"Provider","Properties":{"Description":null,"Health":230,"AttacksPerMinute":20,"Level":7,"RegenerationInterval":null,"RegenerationAmount":null,"MissChance":null,"Taming":{"IsTameable":false,"TamingLevel":null},"Attributes":{"Strength":28,"Agility":28,"Intelligence":10,"Psyche":10,"Stamina":23},"Defense":{"Stab":null,"Cut":null,"Impact":null,"Penetration":null,"Shrapnel":null,"Burn":null,"Cold":null,"Acid":null,"Electric":null}},"Attacks":[],"Mob":{"Name":"Berycled","Links":{"$Url":"/mobs/82"}},"Links":{"$Url":"/mobmaturities/430"}}},{"IsRare":false,"Maturity":{"Id":431,"Name":"Guardian","Properties":{"Description":null,"Health":290,"AttacksPerMinute":20,"Level":7,"RegenerationInterval":null,"RegenerationAmount":null,"MissChance":null,"Taming":{"IsTameable":false,"TamingLevel":null},"Attributes":{"Strength":28,"Agility":28,"Intelligence":10,"Psyche":10,"Stamina":29},"Defense":{"Stab":null,"Cut":null,"Impact":null,"Penetration":null,"Shrapnel":null,"Burn":null,"Cold":null,"Acid":null,"Electric":null}},"Attacks":[],"Mob":{"Name":"Berycled","Links":{"$Url":"/mobs/82"}},"Links":{"$Url":"/mobmaturities/431"}}},{"IsRare":false,"Maturity":{"Id":432,"Name":"Dominant","Properties":{"Description":null,"Health":340,"AttacksPerMinute":20,"Level":8,"RegenerationInterval":null,"RegenerationAmount":null,"MissChance":null,"Taming":{"IsTameable":false,"TamingLevel":null},"Attributes":{"Strength":30,"Agility":30,"Intelligence":10,"Psyche":10,"Stamina":34},"Defense":{"Stab":null,"Cut":null,"Impact":null,"Penetration":null,"Shrapnel":null,"Burn":null,"Cold":null,"Acid":null,"Electric":null}},"Attacks":[],"Mob":{"Name":"Berycled","Links":{"$Url":"/mobs/82"}},"Links":{"$Url":"/mobmaturities/432"}}},{"IsRare":false,"Maturity":{"Id":1318,"Name":"Young","Properties":{"Description":null,"Health":100,"AttacksPerMinute":20,"Level":5,"RegenerationInterval":null,"RegenerationAmount":null,"MissChance":null,"Taming":{"IsTameable":false,"TamingLevel":null},"Attributes":{"Strength":63,"Agility":35,"Intelligence":10,"Psyche":3,"Stamina":10},"Defense":{"Stab":null,"Cut":null,"Impact":null,"Penetration":null,"Shrapnel":null,"Burn":null,"Cold":null,"Acid":null,"Electric":null}},"Attacks":[],"Mob":{"Name":"Faucervix","Links":{"$Url":"/mobs/237"}},"Links":{"$Url":"/mobmaturities/1318"}}},{"IsRare":false,"Maturity":{"Id":1319,"Name":"Mature","Properties":{"Description":null,"Health":130,"AttacksPerMinute":20,"Level":5,"RegenerationInterval":null,"RegenerationAmount":null,"MissChance":null,"Taming":{"IsTameable":false,"TamingLevel":null},"Attributes":{"Strength":65,"Agility":35,"Intelligence":14,"Psyche":2,"Stamina":13},"Defense":{"Stab":null,"Cut":null,"Impact":null,"Penetration":null,"Shrapnel":null,"Burn":null,"Cold":null,"Acid":null,"Electric":null}},"Attacks":[],"Mob":{"Name":"Faucervix","Links":{"$Url":"/mobs/237"}},"Links":{"$Url":"/mobmaturities/1319"}}},{"IsRare":false,"Maturity":{"Id":1320,"Name":"Old","Properties":{"Description":null,"Health":170,"AttacksPerMinute":20,"Level":6,"RegenerationInterval":null,"RegenerationAmount":null,"MissChance":null,"Taming":{"IsTameable":false,"TamingLevel":null},"Attributes":{"Strength":50,"Agility":34,"Intelligence":15,"Psyche":3,"Stamina":17},"Defense":{"Stab":null,"Cut":null,"Impact":null,"Penetration":null,"Shrapnel":null,"Burn":null,"Cold":null,"Acid":null,"Electric":null}},"Attacks":[],"Mob":{"Name":"Faucervix","Links":{"$Url":"/mobs/237"}},"Links":{"$Url":"/mobmaturities/1320"}}},{"IsRare":false,"Maturity":{"Id":1321,"Name":"Provider","Properties":{"Description":null,"Health":230,"AttacksPerMinute":20,"Level":7,"RegenerationInterval":null,"RegenerationAmount":null,"MissChance":null,"Taming":{"IsTameable":false,"TamingLevel":null},"Attributes":{"Strength":63,"Agility":35,"Intelligence":16,"Psyche":2,"Stamina":23},"Defense":{"Stab":null,"Cut":null,"Impact":null,"Penetration":null,"Shrapnel":null,"Burn":null,"Cold":null,"Acid":null,"Electric":null}},"Attacks":[],"Mob":{"Name":"Faucervix","Links":{"$Url":"/mobs/237"}},"Links":{"$Url":"/mobmaturities/1321"}}},{"IsRare":false,"Maturity":{"Id":1542,"Name":"Young","Properties":{"Description":null,"Health":280,"AttacksPerMinute":null,"Level":10,"RegenerationInterval":null,"RegenerationAmount":null,"MissChance":null,"Taming":{"IsTameable":false,"TamingLevel":null},"Attributes":{"Strength":30,"Agility":30,"Intelligence":15,"Psyche":8,"Stamina":28},"Defense":{"Stab":null,"Cut":null,"Impact":null,"Penetration":null,"Shrapnel":null,"Burn":null,"Cold":null,"Acid":null,"Electric":null}},"Attacks":[],"Mob":{"Name":"Gokibusagi","Links":{"$Url":"/mobs/281"}},"Links":{"$Url":"/mobmaturities/1542"}}},{"IsRare":false,"Maturity":{"Id":2434,"Name":"Young","Properties":{"Description":null,"Health":160,"AttacksPerMinute":20,"Level":7,"RegenerationInterval":100,"RegenerationAmount":1.6,"MissChance":null,"Taming":{"IsTameable":false,"TamingLevel":null},"Attributes":{"Strength":35,"Agility":29,"Intelligence":12,"Psyche":6,"Stamina":16},"Defense":{"Stab":null,"Cut":null,"Impact":null,"Penetration":null,"Shrapnel":null,"Burn":null,"Cold":null,"Acid":null,"Electric":null}},"Attacks":[],"Mob":{"Name":"Molisk","Links":{"$Url":"/mobs/420"}},"Links":{"$Url":"/mobmaturities/2434"}}},{"IsRare":false,"Maturity":{"Id":2435,"Name":"Adult","Properties":{"Description":null,"Health":230,"AttacksPerMinute":20,"Level":9,"RegenerationInterval":100,"RegenerationAmount":2.3,"MissChance":null,"Taming":{"IsTameable":false,"TamingLevel":null},"Attributes":{"Strength":37,"Agility":30,"Intelligence":13,"Psyche":8,"Stamina":23},"Defense":{"Stab":null,"Cut":null,"Impact":null,"Penetration":null,"Shrapnel":null,"Burn":null,"Cold":null,"Acid":null,"Electric":null}},"Attacks":[],"Mob":{"Name":"Molisk","Links":{"$Url":"/mobs/420"}},"Links":{"$Url":"/mobmaturities/2435"}}},{"IsRare":false,"Maturity":{"Id":2436,"Name":"Scout","Properties":{"Description":null,"Health":280,"AttacksPerMinute":20,"Level":12,"RegenerationInterval":100,"RegenerationAmount":2.8,"MissChance":null,"Taming":{"IsTameable":false,"TamingLevel":null},"Attributes":{"Strength":40,"Agility":30,"Intelligence":15,"Psyche":8,"Stamina":28},"Defense":{"Stab":null,"Cut":null,"Impact":null,"Penetration":null,"Shrapnel":null,"Burn":null,"Cold":null,"Acid":null,"Electric":null}},"Attacks":[],"Mob":{"Name":"Molisk","Links":{"$Url":"/mobs/420"}},"Links":{"$Url":"/mobmaturities/2436"}}}],"Links":{"$Url":"/mobspawns/2912"}}],"Loots":[{"Mob":{"Name":"Faucervix","Planet":{"Name":"Calypso","Links":{"$Url":"/planets/1"}},"Links":{"$Url":"/mobs/237"}},"Maturity":{"Name":"Young","Links":{"$Url":"/mobmaturities/1318"}},"Item":{"Name":"Animal Hide","Properties":{"Type":"Material"},"Links":{"$Url":"/materials/121"}},"Frequency":"Often","LastVU":"17.22.3","IsEvent":false,"IsDropping":true},{"Mob":{"Name":"Faucervix","Planet":{"Name":"Calypso","Links":{"$Url":"/planets/1"}},"Links":{"$Url":"/mobs/237"}},"Maturity":{"Name":"Young","Links":{"$Url":"/mobmaturities/1318"}},"Item":{"Name":"Animal Muscle Oil","Properties":{"Type":"Material"},"Links":{"$Url":"/materials/124"}},"Frequency":"Often","LastVU":"17.22.3","IsEvent":false,"IsDropping":true},{"Mob":{"Name":"Faucervix","Planet":{"Name":"Calypso","Links":{"$Url":"/planets/1"}},"Links":{"$Url":"/mobs/237"}},"Maturity":{"Name":"Young","Links":{"$Url":"/mobmaturities/1318"}},"Item":{"Name":"Diluted Mineral Extractor","Properties":{"Type":"Material"},"Links":{"$Url":"/materials/612"}},"Frequency":"Common","LastVU":"17.15.1","IsEvent":false,"IsDropping":true},{"Mob":{"Name":"Faucervix","Planet":{"Name":"Calypso","Links":{"$Url":"/planets/1"}},"Links":{"$Url":"/mobs/237"}},"Maturity":{"Name":"Young","Links":{"$Url":"/mobmaturities/1318"}},"Item":{"Name":"Diluted Sweat","Properties":{"Type":"Material"},"Links":{"$Url":"/materials/613"}},"Frequency":"Common","LastVU":"17.22.3","IsEvent":false,"IsDropping":true},{"Mob":{"Name":"Faucervix","Planet":{"Name":"Calypso","Links":{"$Url":"/planets/1"}},"Links":{"$Url":"/mobs/237"}},"Maturity":{"Name":"Young","Links":{"$Url":"/mobmaturities/1318"}},"Item":{"Name":"Faucervix Skin","Properties":{"Type":"Material"},"Links":{"$Url":"/materials/769"}},"Frequency":"Common","LastVU":"17.22.3","IsEvent":false,"IsDropping":true},{"Mob":{"Name":"Faucervix","Planet":{"Name":"Calypso","Links":{"$Url":"/planets/1"}},"Links":{"$Url":"/mobs/237"}},"Maturity":{"Name":"Mature","Links":{"$Url":"/mobmaturities/1319"}},"Item":{"Name":"Material Efficiency Component","Properties":{"Type":"Material"},"Links":{"$Url":"/materials/1399"}},"Frequency":"Common","LastVU":"17.22.0","IsEvent":false,"IsDropping":true},{"Mob":{"Name":"Faucervix","Planet":{"Name":"Calypso","Links":{"$Url":"/planets/1"}},"Links":{"$Url":"/mobs/237"}},"Maturity":{"Name":"Young","Links":{"$Url":"/mobmaturities/1318"}},"Item":{"Name":"Strong Cloth Extractor","Properties":{"Type":"Material"},"Links":{"$Url":"/materials/2254"}},"Frequency":"Common","LastVU":"17.21.2","IsEvent":false,"IsDropping":true},{"Mob":{"Name":"Faucervix","Planet":{"Name":"Calypso","Links":{"$Url":"/planets/1"}},"Links":{"$Url":"/mobs/237"}},"Maturity":{"Name":"Young","Links":{"$Url":"/mobmaturities/1318"}},"Item":{"Name":"Isis LBP 3 (L)","Properties":{"Type":"Weapon"},"Links":{"$Url":"/weapons/1549"}},"Frequency":"Uncommon","LastVU":"17.16.1","IsEvent":false,"IsDropping":true},{"Mob":{"Name":"Faucervix","Planet":{"Name":"Calypso","Links":{"$Url":"/planets/1"}},"Links":{"$Url":"/mobs/237"}},"Maturity":{"Name":null,"Links":{"$Url":"/mobmaturities/null"}},"Item":{"Name":"Electric Attack Nanochip 1","Properties":{"Type":"Weapon"},"Links":{"$Url":"/weapons/747"}},"Frequency":"Uncommon","LastVU":"17.15.0","IsEvent":false,"IsDropping":true},{"Mob":{"Name":"Faucervix","Planet":{"Name":"Calypso","Links":{"$Url":"/planets/1"}},"Links":{"$Url":"/mobs/237"}},"Maturity":{"Name":null,"Links":{"$Url":"/mobmaturities/null"}},"Item":{"Name":"Gremlin Gloves","Properties":{"Type":"Armor"},"Links":{"$Url":"/armors/647"}},"Frequency":"Rare","LastVU":"17.13.0","IsEvent":false,"IsDropping":true},{"Mob":{"Name":"Faucervix","Planet":{"Name":"Calypso","Links":{"$Url":"/planets/1"}},"Links":{"$Url":"/mobs/237"}},"Maturity":{"Name":"Guardian","Links":{"$Url":"/mobmaturities/1322"}},"Item":{"Name":"Regeneration Chip 1 (L)","Properties":{"Type":"MedicalChip"},"Links":{"$Url":"/medicalchips/8"}},"Frequency":"Common","LastVU":"17.18.1","IsEvent":false,"IsDropping":true}],"Links":{"$Url":"/mobs/237"}}